Workbook

Sheet Dashboard
A1: Liquidity Happy Hours / Money View Lab: AI Data Center Ledger Certificate Dashboard
A3: Project name | B3: =IF('Project Profile'!B3="","",'Project Profile'!B3) | D3: Ledger | E3: Exposure | F3: Credited resources | G3: Gap | H3: Status
A4: Version | B4: v1.0 RC2 | May 22, 2026, 11:54 ET | D4: Electric ledger | E4: =IF('Electric Ledger'!K22="No entries yet","",IF('Electric Ledger'!G22<>"",'Electric Ledger'!G22,'Electric Ledger'!F22)) | F4: =IF('Electric Ledger'!K22="No entries yet","",'Electric Ledger'!H22) | G4: =IF('Electric Ledger'!K22="No entries yet","",IF('Electric Ledger'!J22<>"",'Electric Ledger'!J22,'Electric Ledger'!I22)) | H4: ='Electric Ledger'!K22
A5: Prepared by | B5: =IF('Project Profile'!B14="","",'Project Profile'!B14) | D5: RTO / capacity ledger | E5: =IF('RTO Capacity'!K22="No entries yet","",IF('RTO Capacity'!G22<>"",'RTO Capacity'!G22,'RTO Capacity'!F22)) | F5: =IF('RTO Capacity'!K22="No entries yet","",'RTO Capacity'!H22) | G5: =IF('RTO Capacity'!K22="No entries yet","",IF('RTO Capacity'!J22<>"",'RTO Capacity'!J22,'RTO Capacity'!I22)) | H5: ='RTO Capacity'!K22
A6: Prepared date | B6: =IF('Project Profile'!B15="","",'Project Profile'!B15) | D6: Local fiscal ledger | E6: =IF('Local Fiscal'!K22="No entries yet","",IF('Local Fiscal'!G22<>"",'Local Fiscal'!G22,'Local Fiscal'!F22)) | F6: =IF('Local Fiscal'!K22="No entries yet","",'Local Fiscal'!H22) | G6: =IF('Local Fiscal'!K22="No entries yet","",IF('Local Fiscal'!J22<>"",'Local Fiscal'!J22,'Local Fiscal'!I22)) | H6: ='Local Fiscal'!K22
A7: Overall status | B7: =IF(COUNTIF(H4:H9,"Failed under stress")>0,"Failed under stress",IF(COUNTIF(H4:H9,"*Unresolved*")>0,"Unresolved",IF(COUNTIF(H4:H9,"Conditional pass")>0,"Conditional pass",IF(COUNTIF(H4:H9,"Public-welfare override")>0,"Public-welfare override",IF(COUNTIF(H4:H9,"Pass")>0,"Pass where documented","No reviewed ledger lines"))))) | D7: Water / environmental ledger | E7: =IF('Water Env'!K22="No entries yet","",IF('Water Env'!G22<>"",'Water Env'!G22,'Water Env'!F22)) | F7: =IF('Water Env'!K22="No entries yet","",'Water Env'!H22) | G7: =IF('Water Env'!K22="No entries yet","",IF('Water Env'!J22<>"",'Water Env'!J22,'Water Env'!I22)) | H7: ='Water Env'!K22
A8: Anti-misuse rule | B8: Unknown is not failure. One clean ledger is not a clean project. | D8: Credit / collateral ledger | E8: =IF('Credit Collateral'!K22="No entries yet","",IF('Credit Collateral'!G22<>"",'Credit Collateral'!G22,'Credit Collateral'!F22)) | F8: =IF('Credit Collateral'!K22="No entries yet","",'Credit Collateral'!H22) | G8: =IF('Credit Collateral'!K22="No entries yet","",IF('Credit Collateral'!J22<>"",'Credit Collateral'!J22,'Credit Collateral'!I22)) | H8: ='Credit Collateral'!K22
A9: Public-risk note | B9: No hidden ledger should become a public bill. No single clean ledger should be mistaken for a clean project. | D9: Distributional flags | H9: ='Distributional'!I22
A10: Working release for public review and issue-spotting. Not a legal filing, expert report, or commission-ready evidentiary record.
A12: Dashboard rule | B12: Blank or unknown entries do not enter totals.
A13: Cross-ledger rule | B13: A local benefit cannot offset electric, RTO, or water exposure without an enforceable transfer.
A14: Status vocabulary | B14: See Instructions for status, evidence, applicability, and evidence-band values.
A15: Required stress cases unresolved | B15: =COUNTIFS('Stress Cases'!C4:C12,"Required",'Stress Cases'!I4:I12,"<>Pass")&" / "&COUNTIF('Stress Cases'!C4:C12,"Required")&" required open"
A16: Required stress failed | B16: =COUNTIFS('Stress Cases'!C4:C12,"Required",'Stress Cases'!I4:I12,"Failed under stress")&" required failed"
A17: Citation completeness | B17: =COUNTIF('Evidence Register'!J4:J60,"Needs pin")+COUNTIF('Evidence Register'!J4:J60,"Needs update")+COUNTIF('Evidence Register'!J4:J60,"Needs legal pin")+COUNTIF('Evidence Register'!J4:J60,"Missing")&" open evidence pins"
A18: Substantive evidence gaps | B18: =COUNTIF('Evidence Register'!K4:K60,"Missing")+COUNTIF('Evidence Register'!K4:K60,"Contested")&" missing or contested substantive evidence items"
A19: Publication status | B19: Update PJM/FERC/state items before filing or citation.
A20: Stress trigger review | B20: =COUNTIF('Stress Cases'!C4:C12,"Check trigger")&" check-trigger cases need trigger resolution"
A21: Cross-ledger warnings | B21: =COUNTIF('Electric Ledger'!R4:R21,"Yes")+COUNTIF('Electric Ledger'!R4:R21,"Missing origin")+COUNTIF('RTO Capacity'!R4:R21,"Yes")+COUNTIF('RTO Capacity'!R4:R21,"Missing origin")+COUNTIF('Local Fiscal'!R4:R21,"Yes")+COUNTIF('Local Fiscal'!R4:R21,"Missing origin")+COUNTIF('Water Env'!R4:R21,"Yes")+COUNTIF('Water Env'!R4:R21,"Missing origin")+COUNTIF('Credit Collateral'!R4:R21,"Yes")+COUNTIF('Credit Collateral'!R4:R21,"Missing origin")&" cross-ledger or origin warnings"
A22: Filing readiness | B22: =IF(OR(COUNTIF(H4:H9,"*Failed*")>0,COUNTIF(H4:H9,"*Unresolved*")>0,COUNTIF(H4:H9,"No entries yet")=6,COUNTIFS('Stress Cases'!C4:C12,"Required",'Stress Cases'!I4:I12,"<>Pass")>0,COUNTIF('Stress Cases'!C4:C12,"Check trigger")>0,COUNTIF('Evidence Register'!J4:J60,"Needs pin")+COUNTIF('Evidence Register'!J4:J60,"Needs update")+COUNTIF('Evidence Register'!J4:J60,"Needs legal pin")+COUNTIF('Evidence Register'!J4:J60,"Missing")>0,COUNTIF('Evidence Register'!K4:K60,"Missing")+COUNTIF('Evidence Register'!K4:K60,"Contested")>0,COUNTIF('Electric Ledger'!R4:R21,"Yes")+COUNTIF('Electric Ledger'!R4:R21,"Missing origin")+COUNTIF('RTO Capacity'!R4:R21,"Yes")+COUNTIF('RTO Capacity'!R4:R21,"Missing origin")+COUNTIF('Local Fiscal'!R4:R21,"Yes")+COUNTIF('Local Fiscal'!R4:R21,"Missing origin")+COUNTIF('Water Env'!R4:R21,"Yes")+COUNTIF('Water Env'!R4:R21,"Missing origin")+COUNTIF('Credit Collateral'!R4:R21,"Yes")+COUNTIF('Credit Collateral'!R4:R21,"Missing origin")>0,B23<>"Enabled"),"Not filing-ready","Ready where documented")
A23: Formula protection status | B23: Enabled
A24: Model caution | B24: This workbook screens evidentiary adequacy; it does not estimate formal expected loss.

Sheet Instructions
A1: Instructions / Definitions
A3: Purpose | B3: Use this workbook as a ledger certificate, not a project advocacy sheet.
A4: No-zero-unknown rule | B4: Unknown or blank exposure is not treated as zero. It remains unresolved until evidence is entered.
A5: Same-ledger rule | B5: Settlement resources offset only the exposure they legally cover.
A6: Evidence register | B6: Every material line should point to an Evidence ID with source URL, docket, page/table/order pin, and status.
A7: Input cells | B7: Yellow cells are intended for user input.
A8: Formula cells | B8: Blue cells are formulas or summary logic.
A9: Status options | B9: Pass; Conditional pass; Failed under stress; Unresolved, evidence missing; Unresolved, mitigation missing; Unresolved, resource origin missing; Unresolved, cross-ledger transfer missing; Unresolved, confidential but reviewable; Unresolved, contested; Not applicable; Not triggered; Check trigger unresolved; Public-welfare override.
A10: Applicability options | B10: Triggered; Not triggered; Not applicable; Unknown.
A11: Evidence options | B11: Public; Confidential-reviewable; Proxy; Missing; Contested.
A12: Evidence bands | B12: Settled cash; Callable secured credit; Enforceable scoped promise; Unsecured promise; Narrative-only promise; Unaccredited performance claim.
A13: Model caution | B13: This workbook screens evidentiary adequacy; it does not estimate formal expected loss, bankruptcy recovery, or market causation.
A14: Discount-rate basis | B14: Use and disclose the relevant basis: utility carrying cost, bond rate, social discount rate, customer credit-adjusted rate, or commission-approved rate.
... A16: Citation lockdown | B16: Before filing, pin contested numbers to page, table, docket, tariff section, or order paragraph.

Sheet Trigger Screen
A1: Trigger Screen
A3: Trigger | B3: Default threshold | C3: Applies? (Y/N/Unknown) | D3: Evidence ID | E3: Notes
A4: MW threshold | B4: 25 / 50 / 100 MW or state tariff threshold | C4: Unknown
A5: System peak share | B5: Material effect on utility/LSE/zone peak | C5: Unknown
A6: Capex threshold | B6: Grid/water/local capex above filing or board threshold | C6: Unknown
A7: Forecast trigger | B7: IRP/RTO/utility/water/capacity forecast inclusion | C7: Unknown
A8: Public support trigger | B8: Tax abatement, PILOT, public bond, infrastructure, expedited approval | C8: Unknown
A9: Credit trigger | B9: Thin SPV, affiliate split, colo lease, unidentified payer | C9: Unknown
A10: Local trigger | B10: Water reservation, backup generation, road/fire/school/site burden | C10: Unknown
A11: Full review needed? | B11: =IF(COUNTIF(C4:C10,"Y")>0,"Yes",IF(COUNTIF(C4:C10,"Unknown")>0,"Unresolved","No"))

Sheet Project Profile
A1: Project Profile
A3: Project name
A4: Site / jurisdiction
A5: Utility / LSE
A6: RTO / ISO
A7: Legal payer
A8: Parent / guarantor
A9: Project type
A10: Contracted MW
A11: Expected service date
A12: Ramp schedule
A13: Public-risk trigger | B13: Rate recovery / tax incentive / RTO forecast / public debt / expedited approval
A14: Prepared by
A15: Prepared date
A16: Evidence status | B16: Public / Confidential-reviewable / Proxy / Missing / Contested
A17: Version | B17: v1.0 RC2
A18: Project type examples | B18: Hyperscaler owned / colo lease / speculative developer / behind-the-meter / flexible load
A19: Discount rate basis | B19: Utility carrying cost / bond rate / social discount rate / customer credit-adjusted rate / commission-approved rate
A20: Formal model needed? | B20: Y / N / Unknown
A21: Notes

Sheet Electric Ledger
A1: Electric Ledger
A3: Ledger line | B3: Applicability | C3: Causation category | D3: Evidence band | E3: Unit | F3: Base exposure | G3: Stress exposure | H3: Credited resources | I3: Base gap | J3: Stress gap | K3: Status | L3: Evidence status | M3: Residual claimant | N3: Source URL / docket | O3: Page / table / order pin | P3: Evidence ID | Q3: Evidence quality check | R3: Cross-ledger check | S3: Resource ledger of origin | T3: Notes
A4: Direct interconnection | B4: Unknown | C4: But-for direct | D4: Strong / Medium / Proxy / Unknown | E4: one-time $ | I4: =IF(OR(A4="",B4<>"Triggered",F4="",H4=""),"",H4-F4) | J4: =IF(OR(A4="",B4<>"Triggered",G4="",H4=""),"",H4-G4) | K4: =IF(A4="","",IF(B4="Not applicable","Not applicable",IF(B4="Not triggered","Not triggered",IF(B4="Unknown","Unresolved, evidence missing",IF(L4="Confidential-reviewable","Unresolved, confidential but reviewable",IF(L4="Contested","Unresolved, contested",IF(COUNTIFS('Stress Cases'!$K$4:$K$12,"Electric Ledger",'Stress Cases'!$L$4:$L$12,A4,'Stress Cases'!$I$4:$I$12,"Failed under stress")>0,"Failed under linked stress case",IF(COUNTIFS('Stress Cases'!$K$4:$K$12,"Electric Ledger",'Stress Cases'!$L$4:$L$12,A4,'Stress Cases'!$I$4:$I$12,"Unresolved*")>0,"Unresolved, linked stress missing",IF(OR(F4="",H4=""),"Unresolved, evidence missing",IF(AND(H4>0,S4=""),"Unresolved, resource origin missing",IF(OR(ISNUMBER(SEARCH("No evidence",Q4)),ISNUMBER(SEARCH("Missing substantive",Q4)),ISNUMBER(SEARCH("Contested substantive",Q4))),"Unresolved, evidence missing",IF(AND(R4="Yes",S4<>"Public-welfare transfer"),"Unresolved, cross-ledger transfer missing",IF(I4<0,"Failed under stress",IF(AND(J4<>"",J4<0),"Conditional pass","Pass")))))))))))))) | L4: Missing | Q4: =IF(A4="","",IF(P4="","No evidence ID",IFERROR(IF(VLOOKUP(P4,'Evidence Register'!A:M,11,FALSE)="Missing","Missing substantive evidence",IF(VLOOKUP(P4,'Evidence Register'!A:M,11,FALSE)="Contested","Contested substantive evidence",IF(VLOOKUP(P4,'Evidence Register'!A:M,10,FALSE)="Pinned","Pinned evidence",IF(VLOOKUP(P4,'Evidence Register'!A:M,10,FALSE)="Confidential-reviewable","Reviewable evidence","Pin issue: "&VLOOKUP(P4,'Evidence Register'!A:M,10,FALSE))))),"Missing evidence ID"))) | R4: =IF(A4="","",IF(OR(H4="",H4=0),"",IF(S4="","Missing origin",IF(S4<>"Electric Ledger","Yes","No"))))
A5: Shared network upgrade | B5: Unknown | C5: Triggered shared | E5: one-time $ / NPV | I5: =IF(OR(A5="",B5<>"Triggered",F5="",H5=""),"",H5-F5) | J5: =IF(OR(A5="",B5<>"Triggered",G5="",H5=""),"",H5-G5) | K5: =IF(A5="","",IF(B5="Not applicable","Not applicable",IF(B5="Not triggered","Not triggered",IF(B5="Unknown","Unresolved, evidence missing",IF(L5="Confidential-reviewable","Unresolved, confidential but reviewable",IF(L5="Contested","Unresolved, contested",IF(COUNTIFS('Stress Cases'!$K$4:$K$12,"Electric Ledger",'Stress Cases'!$L$4:$L$12,A5,'Stress Cases'!$I$4:$I$12,"Failed under stress")>0,"Failed under linked stress case",IF(COUNTIFS('Stress Cases'!$K$4:$K$12,"Electric Ledger",'Stress Cases'!$L$4:$L$12,A5,'Stress Cases'!$I$4:$I$12,"Unresolved*")>0,"Unresolved, linked stress missing",IF(OR(F5="",H5=""),"Unresolved, evidence missing",IF(AND(H5>0,S5=""),"Unresolved, resource origin missing",IF(OR(ISNUMBER(SEARCH("No evidence",Q5)),ISNUMBER(SEARCH("Missing substantive",Q5)),ISNUMBER(SEARCH("Contested substantive",Q5))),"Unresolved, evidence missing",IF(AND(R5="Yes",S5<>"Public-welfare transfer"),"Unresolved, cross-ledger transfer missing",IF(I5<0,"Failed under stress",IF(AND(J5<>"",J5<0),"Conditional pass","Pass")))))))))))))) | L5: Missing | Q5: =IF(A5="","",IF(P5="","No evidence ID",IFERROR(IF(VLOOKUP(P5,'Evidence Register'!A:M,11,FALSE)="Missing","Missing substantive evidence",IF(VLOOKUP(P5,'Evidence Register'!A:M,11,FALSE)="Contested","Contested substantive evidence",IF(VLOOKUP(P5,'Evidence Register'!A:M,10,FALSE)="Pinned","Pinned evidence",IF(VLOOKUP(P5,'Evidence Register'!A:M,10,FALSE)="Confidential-reviewable","Reviewable evidence","Pin issue: "&VLOOKUP(P5,'Evidence Register'!A:M,10,FALSE))))),"Missing evidence ID"))) | R5: =IF(A5="","",IF(OR(H5="",H5=0),"",IF(S5="","Missing origin",IF(S5<>"Electric Ledger","Yes","No"))))
A6: Underuse fixed-cost exposure | B6: Unknown | C6: Forecast-reliance | E6: $/year or NPV | I6: =IF(OR(A6="",B6<>"Triggered",F6="",H6=""),"",H6-F6) | J6: =IF(OR(A6="",B6<>"Triggered",G6="",H6=""),"",H6-G6) | K6: =IF(A6="","",IF(B6="Not applicable","Not applicable",IF(B6="Not triggered","Not triggered",IF(B6="Unknown","Unresolved, evidence missing",IF(L6="Confidential-reviewable","Unresolved, confidential but reviewable",IF(L6="Contested","Unresolved, contested",IF(COUNTIFS('Stress Cases'!$K$4:$K$12,"Electric Ledger",'Stress Cases'!$L$4:$L$12,A6,'Stress Cases'!$I$4:$I$12,"Failed under stress")>0,"Failed under linked stress case",IF(COUNTIFS('Stress Cases'!$K$4:$K$12,"Electric Ledger",'Stress Cases'!$L$4:$L$12,A6,'Stress Cases'!$I$4:$I$12,"Unresolved*")>0,"Unresolved, linked stress missing",IF(OR(F6="",H6=""),"Unresolved, evidence missing",IF(AND(H6>0,S6=""),"Unresolved, resource origin missing",IF(OR(ISNUMBER(SEARCH("No evidence",Q6)),ISNUMBER(SEARCH("Missing substantive",Q6)),ISNUMBER(SEARCH("Contested substantive",Q6))),"Unresolved, evidence missing",IF(AND(R6="Yes",S6<>"Public-welfare transfer"),"Unresolved, cross-ledger transfer missing",IF(I6<0,"Failed under stress",IF(AND(J6<>"",J6<0),"Conditional pass","Pass")))))))))))))) | L6: Missing | Q6: =IF(A6="","",IF(P6="","No evidence ID",IFERROR(IF(VLOOKUP(P6,'Evidence Register'!A:M,11,FALSE)="Missing","Missing substantive evidence",IF(VLOOKUP(P6,'Evidence Register'!A:M,11,FALSE)="Contested","Contested substantive evidence",IF(VLOOKUP(P6,'Evidence Register'!A:M,10,FALSE)="Pinned","Pinned evidence",IF(VLOOKUP(P6,'Evidence Register'!A:M,10,FALSE)="Confidential-reviewable","Reviewable evidence","Pin issue: "&VLOOKUP(P6,'Evidence Register'!A:M,10,FALSE))))),"Missing evidence ID"))) | R6: =IF(A6="","",IF(OR(H6="",H6=0),"",IF(S6="","Missing origin",IF(S6<>"Electric Ledger","Yes","No"))))
A7: Exit / stranded plant | B7: Unknown | C7: Forecast-reliance | E7: remaining NBV | I7: =IF(OR(A7="",B7<>"Triggered",F7="",H7=""),"",H7-F7) | J7: =IF(OR(A7="",B7<>"Triggered",G7="",H7=""),"",H7-G7) | K7: =IF(A7="","",IF(B7="Not applicable","Not applicable",IF(B7="Not triggered","Not triggered",IF(B7="Unknown","Unresolved, evidence missing",IF(L7="Confidential-reviewable","Unresolved, confidential but reviewable",IF(L7="Contested","Unresolved, contested",IF(COUNTIFS('Stress Cases'!$K$4:$K$12,"Electric Ledger",'Stress Cases'!$L$4:$L$12,A7,'Stress Cases'!$I$4:$I$12,"Failed under stress")>0,"Failed under linked stress case",IF(COUNTIFS('Stress Cases'!$K$4:$K$12,"Electric Ledger",'Stress Cases'!$L$4:$L$12,A7,'Stress Cases'!$I$4:$I$12,"Unresolved*")>0,"Unresolved, linked stress missing",IF(OR(F7="",H7=""),"Unresolved, evidence missing",IF(AND(H7>0,S7=""),"Unresolved, resource origin missing",IF(OR(ISNUMBER(SEARCH("No evidence",Q7)),ISNUMBER(SEARCH("Missing substantive",Q7)),ISNUMBER(SEARCH("Contested substantive",Q7))),"Unresolved, evidence missing",IF(AND(R7="Yes",S7<>"Public-welfare transfer"),"Unresolved, cross-ledger transfer missing",IF(I7<0,"Failed under stress",IF(AND(J7<>"",J7<0),"Conditional pass","Pass")))))))))))))) | L7: Missing | Q7: =IF(A7="","",IF(P7="","No evidence ID",IFERROR(IF(VLOOKUP(P7,'Evidence Register'!A:M,11,FALSE)="Missing","Missing substantive evidence",IF(VLOOKUP(P7,'Evidence Register'!A:M,11,FALSE)="Contested","Contested substantive evidence",IF(VLOOKUP(P7,'Evidence Register'!A:M,10,FALSE)="Pinned","Pinned evidence",IF(VLOOKUP(P7,'Evidence Register'!A:M,10,FALSE)="Confidential-reviewable","Reviewable evidence","Pin issue: "&VLOOKUP(P7,'Evidence Register'!A:M,10,FALSE))))),"Missing evidence ID"))) | R7: =IF(A7="","",IF(OR(H7="",H7=0),"",IF(S7="","Missing origin",IF(S7<>"Electric Ledger","Yes","No"))))
A8: Rate-base / rider exposure | B8: Unknown | C8: Forecast-reliance | E8: NPV / annual rider | I8: =IF(OR(A8="",B8<>"Triggered",F8="",H8=""),"",H8-F8) | J8: =IF(OR(A8="",B8<>"Triggered",G8="",H8=""),"",H8-G8) | K8: =IF(A8="","",IF(B8="Not applicable","Not applicable",IF(B8="Not triggered","Not triggered",IF(B8="Unknown","Unresolved, evidence missing",IF(L8="Confidential-reviewable","Unresolved, confidential but reviewable",IF(L8="Contested","Unresolved, contested",IF(COUNTIFS('Stress Cases'!$K$4:$K$12,"Electric Ledger",'Stress Cases'!$L$4:$L$12,A8,'Stress Cases'!$I$4:$I$12,"Failed under stress")>0,"Failed under linked stress case",IF(COUNTIFS('Stress Cases'!$K$4:$K$12,"Electric Ledger",'Stress Cases'!$L$4:$L$12,A8,'Stress Cases'!$I$4:$I$12,"Unresolved*")>0,"Unresolved, linked stress missing",IF(OR(F8="",H8=""),"Unresolved, evidence missing",IF(AND(H8>0,S8=""),"Unresolved, resource origin missing",IF(OR(ISNUMBER(SEARCH("No evidence",Q8)),ISNUMBER(SEARCH("Missing substantive",Q8)),ISNUMBER(SEARCH("Contested substantive",Q8))),"Unresolved, evidence missing",IF(AND(R8="Yes",S8<>"Public-welfare transfer"),"Unresolved, cross-ledger transfer missing",IF(I8<0,"Failed under stress",IF(AND(J8<>"",J8<0),"Conditional pass","Pass")))))))))))))) | L8: Missing | Q8: =IF(A8="","",IF(P8="","No evidence ID",IFERROR(IF(VLOOKUP(P8,'Evidence Register'!A:M,11,FALSE)="Missing","Missing substantive evidence",IF(VLOOKUP(P8,'Evidence Register'!A:M,11,FALSE)="Contested","Contested substantive evidence",IF(VLOOKUP(P8,'Evidence Register'!A:M,10,FALSE)="Pinned","Pinned evidence",IF(VLOOKUP(P8,'Evidence Register'!A:M,10,FALSE)="Confidential-reviewable","Reviewable evidence","Pin issue: "&VLOOKUP(P8,'Evidence Register'!A:M,10,FALSE))))),"Missing evidence ID"))) | R8: =IF(A8="","",IF(OR(H8="",H8=0),"",IF(S8="","Missing origin",IF(S8<>"Electric Ledger","Yes","No"))))
I9: =IF(OR(A9="",B9<>"Triggered",F9="",H9=""),"",H9-F9) | J9: =IF(OR(A9="",B9<>"Triggered",G9="",H9=""),"",H9-G9) | K9: =IF(A9="","",IF(B9="Not applicable","Not applicable",IF(B9="Not triggered","Not triggered",IF(B9="Unknown","Unresolved, evidence missing",IF(L9="Confidential-reviewable","Unresolved, confidential but reviewable",IF(L9="Contested","Unresolved, contested",IF(COUNTIFS('Stress Cases'!$K$4:$K$12,"Electric Ledger",'Stress Cases'!$L$4:$L$12,A9,'Stress Cases'!$I$4:$I$12,"Failed under stress")>0,"Failed under linked stress case",IF(COUNTIFS('Stress Cases'!$K$4:$K$12,"Electric Ledger",'Stress Cases'!$L$4:$L$12,A9,'Stress Cases'!$I$4:$I$12,"Unresolved*")>0,"Unresolved, linked stress missing",IF(OR(F9="",H9=""),"Unresolved, evidence missing",IF(AND(H9>0,S9=""),"Unresolved, resource origin missing",IF(OR(ISNUMBER(SEARCH("No evidence",Q9)),ISNUMBER(SEARCH("Missing substantive",Q9)),ISNUMBER(SEARCH("Contested substantive",Q9))),"Unresolved, evidence missing",IF(AND(R9="Yes",S9<>"Public-welfare transfer"),"Unresolved, cross-ledger transfer missing",IF(I9<0,"Failed under stress",IF(AND(J9<>"",J9<0),"Conditional pass","Pass")))))))))))))) | Q9: =IF(A9="","",IF(P9="","No evidence ID",IFERROR(IF(VLOOKUP(P9,'Evidence Register'!A:M,11,FALSE)="Missing","Missing substantive evidence",IF(VLOOKUP(P9,'Evidence Register'!A:M,11,FALSE)="Contested","Contested substantive evidence",IF(VLOOKUP(P9,'Evidence Register'!A:M,10,FALSE)="Pinned","Pinned evidence",IF(VLOOKUP(P9,'Evidence Register'!A:M,10,FALSE)="Confidential-reviewable","Reviewable evidence","Pin issue: "&VLOOKUP(P9,'Evidence Register'!A:M,10,FALSE))))),"Missing evidence ID"))) | R9: =IF(A9="","",IF(OR(H9="",H9=0),"",IF(S9="","Missing origin",IF(S9<>"Electric Ledger","Yes","No"))))
I10: =IF(OR(A10="",B10<>"Triggered",F10="",H10=""),"",H10-F10) | J10: =IF(OR(A10="",B10<>"Triggered",G10="",H10=""),"",H10-G10) | K10: =IF(A10="","",IF(B10="Not applicable","Not applicable",IF(B10="Not triggered","Not triggered",IF(B10="Unknown","Unresolved, evidence missing",IF(L10="Confidential-reviewable","Unresolved, confidential but reviewable",IF(L10="Contested","Unresolved, contested",IF(COUNTIFS('Stress Cases'!$K$4:$K$12,"Electric Ledger",'Stress Cases'!$L$4:$L$12,A10,'Stress Cases'!$I$4:$I$12,"Failed under stress")>0,"Failed under linked stress case",IF(COUNTIFS('Stress Cases'!$K$4:$K$12,"Electric Ledger",'Stress Cases'!$L$4:$L$12,A10,'Stress Cases'!$I$4:$I$12,"Unresolved*")>0,"Unresolved, linked stress missing",IF(OR(F10="",H10=""),"Unresolved, evidence missing",IF(AND(H10>0,S10=""),"Unresolved, resource origin missing",IF(OR(ISNUMBER(SEARCH("No evidence",Q10)),ISNUMBER(SEARCH("Missing substantive",Q10)),ISNUMBER(SEARCH("Contested substantive",Q10))),"Unresolved, evidence missing",IF(AND(R10="Yes",S10<>"Public-welfare transfer"),"Unresolved, cross-ledger transfer missing",IF(I10<0,"Failed under stress",IF(AND(J10<>"",J10<0),"Conditional pass","Pass")))))))))))))) | Q10: =IF(A10="","",IF(P10="","No evidence ID",IFERROR(IF(VLOOKUP(P10,'Evidence Register'!A:M,11,FALSE)="Missing","Missing substantive evidence",IF(VLOOKUP(P10,'Evidence Register'!A:M,11,FALSE)="Contested","Contested substantive evidence",IF(VLOOKUP(P10,'Evidence Register'!A:M,10,FALSE)="Pinned","Pinned evidence",IF(VLOOKUP(P10,'Evidence Register'!A:M,10,FALSE)="Confidential-reviewable","Reviewable evidence","Pin issue: "&VLOOKUP(P10,'Evidence Register'!A:M,10,FALSE))))),"Missing evidence ID"))) | R10: =IF(A10="","",IF(OR(H10="",H10=0),"",IF(S10="","Missing origin",IF(S10<>"Electric Ledger","Yes","No"))))
I11: =IF(OR(A11="",B11<>"Triggered",F11="",H11=""),"",H11-F11) | J11: =IF(OR(A11="",B11<>"Triggered",G11="",H11=""),"",H11-G11) | K11: =IF(A11="","",IF(B11="Not applicable","Not applicable",IF(B11="Not triggered","Not triggered",IF(B11="Unknown","Unresolved, evidence missing",IF(L11="Confidential-reviewable","Unresolved, confidential but reviewable",IF(L11="Contested","Unresolved, contested",IF(COUNTIFS('Stress Cases'!$K$4:$K$12,"Electric Ledger",'Stress Cases'!$L$4:$L$12,A11,'Stress Cases'!$I$4:$I$12,"Failed under stress")>0,"Failed under linked stress case",IF(COUNTIFS('Stress Cases'!$K$4:$K$12,"Electric Ledger",'Stress Cases'!$L$4:$L$12,A11,'Stress Cases'!$I$4:$I$12,"Unresolved*")>0,"Unresolved, linked stress missing",IF(OR(F11="",H11=""),"Unresolved, evidence missing",IF(AND(H11>0,S11=""),"Unresolved, resource origin missing",IF(OR(ISNUMBER(SEARCH("No evidence",Q11)),ISNUMBER(SEARCH("Missing substantive",Q11)),ISNUMBER(SEARCH("Contested substantive",Q11))),"Unresolved, evidence missing",IF(AND(R11="Yes",S11<>"Public-welfare transfer"),"Unresolved, cross-ledger transfer missing",IF(I11<0,"Failed under stress",IF(AND(J11<>"",J11<0),"Conditional pass","Pass")))))))))))))) | Q11: =IF(A11="","",IF(P11="","No evidence ID",IFERROR(IF(VLOOKUP(P11,'Evidence Register'!A:M,11,FALSE)="Missing","Missing substantive evidence",IF(VLOOKUP(P11,'Evidence Register'!A:M,11,FALSE)="Contested","Contested substantive evidence",IF(VLOOKUP(P11,'Evidence Register'!A:M,10,FALSE)="Pinned","Pinned evidence",IF(VLOOKUP(P11,'Evidence Register'!A:M,10,FALSE)="Confidential-reviewable","Reviewable evidence","Pin issue: "&VLOOKUP(P11,'Evidence Register'!A:M,10,FALSE))))),"Missing evidence ID"))) | R11: =IF(A11="","",IF(OR(H11="",H11=0),"",IF(S11="","Missing origin",IF(S11<>"Electric Ledger","Yes","No"))))
I12: =IF(OR(A12="",B12<>"Triggered",F12="",H12=""),"",H12-F12) | J12: =IF(OR(A12="",B12<>"Triggered",G12="",H12=""),"",H12-G12) | K12: =IF(A12="","",IF(B12="Not applicable","Not applicable",IF(B12="Not triggered","Not triggered",IF(B12="Unknown","Unresolved, evidence missing",IF(L12="Confidential-reviewable","Unresolved, confidential but reviewable",IF(L12="Contested","Unresolved, contested",IF(COUNTIFS('Stress Cases'!$K$4:$K$12,"Electric Ledger",'Stress Cases'!$L$4:$L$12,A12,'Stress Cases'!$I$4:$I$12,"Failed under stress")>0,"Failed under linked stress case",IF(COUNTIFS('Stress Cases'!$K$4:$K$12,"Electric Ledger",'Stress Cases'!$L$4:$L$12,A12,'Stress Cases'!$I$4:$I$12,"Unresolved*")>0,"Unresolved, linked stress missing",IF(OR(F12="",H12=""),"Unresolved, evidence missing",IF(AND(H12>0,S12=""),"Unresolved, resource origin missing",IF(OR(ISNUMBER(SEARCH("No evidence",Q12)),ISNUMBER(SEARCH("Missing substantive",Q12)),ISNUMBER(SEARCH("Contested substantive",Q12))),"Unresolved, evidence missing",IF(AND(R12="Yes",S12<>"Public-welfare transfer"),"Unresolved, cross-ledger transfer missing",IF(I12<0,"Failed under stress",IF(AND(J12<>"",J12<0),"Conditional pass","Pass")))))))))))))) | Q12: =IF(A12="","",IF(P12="","No evidence ID",IFERROR(IF(VLOOKUP(P12,'Evidence Register'!A:M,11,FALSE)="Missing","Missing substantive evidence",IF(VLOOKUP(P12,'Evidence Register'!A:M,11,FALSE)="Contested","Contested substantive evidence",IF(VLOOKUP(P12,'Evidence Register'!A:M,10,FALSE)="Pinned","Pinned evidence",IF(VLOOKUP(P12,'Evidence Register'!A:M,10,FALSE)="Confidential-reviewable","Reviewable evidence","Pin issue: "&VLOOKUP(P12,'Evidence Register'!A:M,10,FALSE))))),"Missing evidence ID"))) | R12: =IF(A12="","",IF(OR(H12="",H12=0),"",IF(S12="","Missing origin",IF(S12<>"Electric Ledger","Yes","No"))))
I13: =IF(OR(A13="",B13<>"Triggered",F13="",H13=""),"",H13-F13) | J13: =IF(OR(A13="",B13<>"Triggered",G13="",H13=""),"",H13-G13) | K13: =IF(A13="","",IF(B13="Not applicable","Not applicable",IF(B13="Not triggered","Not triggered",IF(B13="Unknown","Unresolved, evidence missing",IF(L13="Confidential-reviewable","Unresolved, confidential but reviewable",IF(L13="Contested","Unresolved, contested",IF(COUNTIFS('Stress Cases'!$K$4:$K$12,"Electric Ledger",'Stress Cases'!$L$4:$L$12,A13,'Stress Cases'!$I$4:$I$12,"Failed under stress")>0,"Failed under linked stress case",IF(COUNTIFS('Stress Cases'!$K$4:$K$12,"Electric Ledger",'Stress Cases'!$L$4:$L$12,A13,'Stress Cases'!$I$4:$I$12,"Unresolved*")>0,"Unresolved, linked stress missing",IF(OR(F13="",H13=""),"Unresolved, evidence missing",IF(AND(H13>0,S13=""),"Unresolved, resource origin missing",IF(OR(ISNUMBER(SEARCH("No evidence",Q13)),ISNUMBER(SEARCH("Missing substantive",Q13)),ISNUMBER(SEARCH("Contested substantive",Q13))),"Unresolved, evidence missing",IF(AND(R13="Yes",S13<>"Public-welfare transfer"),"Unresolved, cross-ledger transfer missing",IF(I13<0,"Failed under stress",IF(AND(J13<>"",J13<0),"Conditional pass","Pass")))))))))))))) | Q13: =IF(A13="","",IF(P13="","No evidence ID",IFERROR(IF(VLOOKUP(P13,'Evidence Register'!A:M,11,FALSE)="Missing","Missing substantive evidence",IF(VLOOKUP(P13,'Evidence Register'!A:M,11,FALSE)="Contested","Contested substantive evidence",IF(VLOOKUP(P13,'Evidence Register'!A:M,10,FALSE)="Pinned","Pinned evidence",IF(VLOOKUP(P13,'Evidence Register'!A:M,10,FALSE)="Confidential-reviewable","Reviewable evidence","Pin issue: "&VLOOKUP(P13,'Evidence Register'!A:M,10,FALSE))))),"Missing evidence ID"))) | R13: =IF(A13="","",IF(OR(H13="",H13=0),"",IF(S13="","Missing origin",IF(S13<>"Electric Ledger","Yes","No"))))
I14: =IF(OR(A14="",B14<>"Triggered",F14="",H14=""),"",H14-F14) | J14: =IF(OR(A14="",B14<>"Triggered",G14="",H14=""),"",H14-G14) | K14: =IF(A14="","",IF(B14="Not applicable","Not applicable",IF(B14="Not triggered","Not triggered",IF(B14="Unknown","Unresolved, evidence missing",IF(L14="Confidential-reviewable","Unresolved, confidential but reviewable",IF(L14="Contested","Unresolved, contested",IF(COUNTIFS('Stress Cases'!$K$4:$K$12,"Electric Ledger",'Stress Cases'!$L$4:$L$12,A14,'Stress Cases'!$I$4:$I$12,"Failed under stress")>0,"Failed under linked stress case",IF(COUNTIFS('Stress Cases'!$K$4:$K$12,"Electric Ledger",'Stress Cases'!$L$4:$L$12,A14,'Stress Cases'!$I$4:$I$12,"Unresolved*")>0,"Unresolved, linked stress missing",IF(OR(F14="",H14=""),"Unresolved, evidence missing",IF(AND(H14>0,S14=""),"Unresolved, resource origin missing",IF(OR(ISNUMBER(SEARCH("No evidence",Q14)),ISNUMBER(SEARCH("Missing substantive",Q14)),ISNUMBER(SEARCH("Contested substantive",Q14))),"Unresolved, evidence missing",IF(AND(R14="Yes",S14<>"Public-welfare transfer"),"Unresolved, cross-ledger transfer missing",IF(I14<0,"Failed under stress",IF(AND(J14<>"",J14<0),"Conditional pass","Pass")))))))))))))) | Q14: =IF(A14="","",IF(P14="","No evidence ID",IFERROR(IF(VLOOKUP(P14,'Evidence Register'!A:M,11,FALSE)="Missing","Missing substantive evidence",IF(VLOOKUP(P14,'Evidence Register'!A:M,11,FALSE)="Contested","Contested substantive evidence",IF(VLOOKUP(P14,'Evidence Register'!A:M,10,FALSE)="Pinned","Pinned evidence",IF(VLOOKUP(P14,'Evidence Register'!A:M,10,FALSE)="Confidential-reviewable","Reviewable evidence","Pin issue: "&VLOOKUP(P14,'Evidence Register'!A:M,10,FALSE))))),"Missing evidence ID"))) | R14: =IF(A14="","",IF(OR(H14="",H14=0),"",IF(S14="","Missing origin",IF(S14<>"Electric Ledger","Yes","No"))))
I15: =IF(OR(A15="",B15<>"Triggered",F15="",H15=""),"",H15-F15) | J15: =IF(OR(A15="",B15<>"Triggered",G15="",H15=""),"",H15-G15) | K15: =IF(A15="","",IF(B15="Not applicable","Not applicable",IF(B15="Not triggered","Not triggered",IF(B15="Unknown","Unresolved, evidence missing",IF(L15="Confidential-reviewable","Unresolved, confidential but reviewable",IF(L15="Contested","Unresolved, contested",IF(COUNTIFS('Stress Cases'!$K$4:$K$12,"Electric Ledger",'Stress Cases'!$L$4:$L$12,A15,'Stress Cases'!$I$4:$I$12,"Failed under stress")>0,"Failed under linked stress case",IF(COUNTIFS('Stress Cases'!$K$4:$K$12,"Electric Ledger",'Stress Cases'!$L$4:$L$12,A15,'Stress Cases'!$I$4:$I$12,"Unresolved*")>0,"Unresolved, linked stress missing",IF(OR(F15="",H15=""),"Unresolved, evidence missing",IF(AND(H15>0,S15=""),"Unresolved, resource origin missing",IF(OR(ISNUMBER(SEARCH("No evidence",Q15)),ISNUMBER(SEARCH("Missing substantive",Q15)),ISNUMBER(SEARCH("Contested substantive",Q15))),"Unresolved, evidence missing",IF(AND(R15="Yes",S15<>"Public-welfare transfer"),"Unresolved, cross-ledger transfer missing",IF(I15<0,"Failed under stress",IF(AND(J15<>"",J15<0),"Conditional pass","Pass")))))))))))))) | Q15: =IF(A15="","",IF(P15="","No evidence ID",IFERROR(IF(VLOOKUP(P15,'Evidence Register'!A:M,11,FALSE)="Missing","Missing substantive evidence",IF(VLOOKUP(P15,'Evidence Register'!A:M,11,FALSE)="Contested","Contested substantive evidence",IF(VLOOKUP(P15,'Evidence Register'!A:M,10,FALSE)="Pinned","Pinned evidence",IF(VLOOKUP(P15,'Evidence Register'!A:M,10,FALSE)="Confidential-reviewable","Reviewable evidence","Pin issue: "&VLOOKUP(P15,'Evidence Register'!A:M,10,FALSE))))),"Missing evidence ID"))) | R15: =IF(A15="","",IF(OR(H15="",H15=0),"",IF(S15="","Missing origin",IF(S15<>"Electric Ledger","Yes","No"))))
I16: =IF(OR(A16="",B16<>"Triggered",F16="",H16=""),"",H16-F16) | J16: =IF(OR(A16="",B16<>"Triggered",G16="",H16=""),"",H16-G16) | K16: =IF(A16="","",IF(B16="Not applicable","Not applicable",IF(B16="Not triggered","Not triggered",IF(B16="Unknown","Unresolved, evidence missing",IF(L16="Confidential-reviewable","Unresolved, confidential but reviewable",IF(L16="Contested","Unresolved, contested",IF(COUNTIFS('Stress Cases'!$K$4:$K$12,"Electric Ledger",'Stress Cases'!$L$4:$L$12,A16,'Stress Cases'!$I$4:$I$12,"Failed under stress")>0,"Failed under linked stress case",IF(COUNTIFS('Stress Cases'!$K$4:$K$12,"Electric Ledger",'Stress Cases'!$L$4:$L$12,A16,'Stress Cases'!$I$4:$I$12,"Unresolved*")>0,"Unresolved, linked stress missing",IF(OR(F16="",H16=""),"Unresolved, evidence missing",IF(AND(H16>0,S16=""),"Unresolved, resource origin missing",IF(OR(ISNUMBER(SEARCH("No evidence",Q16)),ISNUMBER(SEARCH("Missing substantive",Q16)),ISNUMBER(SEARCH("Contested substantive",Q16))),"Unresolved, evidence missing",IF(AND(R16="Yes",S16<>"Public-welfare transfer"),"Unresolved, cross-ledger transfer missing",IF(I16<0,"Failed under stress",IF(AND(J16<>"",J16<0),"Conditional pass","Pass")))))))))))))) | Q16: =IF(A16="","",IF(P16="","No evidence ID",IFERROR(IF(VLOOKUP(P16,'Evidence Register'!A:M,11,FALSE)="Missing","Missing substantive evidence",IF(VLOOKUP(P16,'Evidence Register'!A:M,11,FALSE)="Contested","Contested substantive evidence",IF(VLOOKUP(P16,'Evidence Register'!A:M,10,FALSE)="Pinned","Pinned evidence",IF(VLOOKUP(P16,'Evidence Register'!A:M,10,FALSE)="Confidential-reviewable","Reviewable evidence","Pin issue: "&VLOOKUP(P16,'Evidence Register'!A:M,10,FALSE))))),"Missing evidence ID"))) | R16: =IF(A16="","",IF(OR(H16="",H16=0),"",IF(S16="","Missing origin",IF(S16<>"Electric Ledger","Yes","No"))))
I17: =IF(OR(A17="",B17<>"Triggered",F17="",H17=""),"",H17-F17) | J17: =IF(OR(A17="",B17<>"Triggered",G17="",H17=""),"",H17-G17) | K17: =IF(A17="","",IF(B17="Not applicable","Not applicable",IF(B17="Not triggered","Not triggered",IF(B17="Unknown","Unresolved, evidence missing",IF(L17="Confidential-reviewable","Unresolved, confidential but reviewable",IF(L17="Contested","Unresolved, contested",IF(COUNTIFS('Stress Cases'!$K$4:$K$12,"Electric Ledger",'Stress Cases'!$L$4:$L$12,A17,'Stress Cases'!$I$4:$I$12,"Failed under stress")>0,"Failed under linked stress case",IF(COUNTIFS('Stress Cases'!$K$4:$K$12,"Electric Ledger",'Stress Cases'!$L$4:$L$12,A17,'Stress Cases'!$I$4:$I$12,"Unresolved*")>0,"Unresolved, linked stress missing",IF(OR(F17="",H17=""),"Unresolved, evidence missing",IF(AND(H17>0,S17=""),"Unresolved, resource origin missing",IF(OR(ISNUMBER(SEARCH("No evidence",Q17)),ISNUMBER(SEARCH("Missing substantive",Q17)),ISNUMBER(SEARCH("Contested substantive",Q17))),"Unresolved, evidence missing",IF(AND(R17="Yes",S17<>"Public-welfare transfer"),"Unresolved, cross-ledger transfer missing",IF(I17<0,"Failed under stress",IF(AND(J17<>"",J17<0),"Conditional pass","Pass")))))))))))))) | Q17: =IF(A17="","",IF(P17="","No evidence ID",IFERROR(IF(VLOOKUP(P17,'Evidence Register'!A:M,11,FALSE)="Missing","Missing substantive evidence",IF(VLOOKUP(P17,'Evidence Register'!A:M,11,FALSE)="Contested","Contested substantive evidence",IF(VLOOKUP(P17,'Evidence Register'!A:M,10,FALSE)="Pinned","Pinned evidence",IF(VLOOKUP(P17,'Evidence Register'!A:M,10,FALSE)="Confidential-reviewable","Reviewable evidence","Pin issue: "&VLOOKUP(P17,'Evidence Register'!A:M,10,FALSE))))),"Missing evidence ID"))) | R17: =IF(A17="","",IF(OR(H17="",H17=0),"",IF(S17="","Missing origin",IF(S17<>"Electric Ledger","Yes","No"))))
I18: =IF(OR(A18="",B18<>"Triggered",F18="",H18=""),"",H18-F18) | J18: =IF(OR(A18="",B18<>"Triggered",G18="",H18=""),"",H18-G18) | K18: =IF(A18="","",IF(B18="Not applicable","Not applicable",IF(B18="Not triggered","Not triggered",IF(B18="Unknown","Unresolved, evidence missing",IF(L18="Confidential-reviewable","Unresolved, confidential but reviewable",IF(L18="Contested","Unresolved, contested",IF(COUNTIFS('Stress Cases'!$K$4:$K$12,"Electric Ledger",'Stress Cases'!$L$4:$L$12,A18,'Stress Cases'!$I$4:$I$12,"Failed under stress")>0,"Failed under linked stress case",IF(COUNTIFS('Stress Cases'!$K$4:$K$12,"Electric Ledger",'Stress Cases'!$L$4:$L$12,A18,'Stress Cases'!$I$4:$I$12,"Unresolved*")>0,"Unresolved, linked stress missing",IF(OR(F18="",H18=""),"Unresolved, evidence missing",IF(AND(H18>0,S18=""),"Unresolved, resource origin missing",IF(OR(ISNUMBER(SEARCH("No evidence",Q18)),ISNUMBER(SEARCH("Missing substantive",Q18)),ISNUMBER(SEARCH("Contested substantive",Q18))),"Unresolved, evidence missing",IF(AND(R18="Yes",S18<>"Public-welfare transfer"),"Unresolved, cross-ledger transfer missing",IF(I18<0,"Failed under stress",IF(AND(J18<>"",J18<0),"Conditional pass","Pass")))))))))))))) | Q18: =IF(A18="","",IF(P18="","No evidence ID",IFERROR(IF(VLOOKUP(P18,'Evidence Register'!A:M,11,FALSE)="Missing","Missing substantive evidence",IF(VLOOKUP(P18,'Evidence Register'!A:M,11,FALSE)="Contested","Contested substantive evidence",IF(VLOOKUP(P18,'Evidence Register'!A:M,10,FALSE)="Pinned","Pinned evidence",IF(VLOOKUP(P18,'Evidence Register'!A:M,10,FALSE)="Confidential-reviewable","Reviewable evidence","Pin issue: "&VLOOKUP(P18,'Evidence Register'!A:M,10,FALSE))))),"Missing evidence ID"))) | R18: =IF(A18="","",IF(OR(H18="",H18=0),"",IF(S18="","Missing origin",IF(S18<>"Electric Ledger","Yes","No"))))
I19: =IF(OR(A19="",B19<>"Triggered",F19="",H19=""),"",H19-F19) | J19: =IF(OR(A19="",B19<>"Triggered",G19="",H19=""),"",H19-G19) | K19: =IF(A19="","",IF(B19="Not applicable","Not applicable",IF(B19="Not triggered","Not triggered",IF(B19="Unknown","Unresolved, evidence missing",IF(L19="Confidential-reviewable","Unresolved, confidential but reviewable",IF(L19="Contested","Unresolved, contested",IF(COUNTIFS('Stress Cases'!$K$4:$K$12,"Electric Ledger",'Stress Cases'!$L$4:$L$12,A19,'Stress Cases'!$I$4:$I$12,"Failed under stress")>0,"Failed under linked stress case",IF(COUNTIFS('Stress Cases'!$K$4:$K$12,"Electric Ledger",'Stress Cases'!$L$4:$L$12,A19,'Stress Cases'!$I$4:$I$12,"Unresolved*")>0,"Unresolved, linked stress missing",IF(OR(F19="",H19=""),"Unresolved, evidence missing",IF(AND(H19>0,S19=""),"Unresolved, resource origin missing",IF(OR(ISNUMBER(SEARCH("No evidence",Q19)),ISNUMBER(SEARCH("Missing substantive",Q19)),ISNUMBER(SEARCH("Contested substantive",Q19))),"Unresolved, evidence missing",IF(AND(R19="Yes",S19<>"Public-welfare transfer"),"Unresolved, cross-ledger transfer missing",IF(I19<0,"Failed under stress",IF(AND(J19<>"",J19<0),"Conditional pass","Pass")))))))))))))) | Q19: =IF(A19="","",IF(P19="","No evidence ID",IFERROR(IF(VLOOKUP(P19,'Evidence Register'!A:M,11,FALSE)="Missing","Missing substantive evidence",IF(VLOOKUP(P19,'Evidence Register'!A:M,11,FALSE)="Contested","Contested substantive evidence",IF(VLOOKUP(P19,'Evidence Register'!A:M,10,FALSE)="Pinned","Pinned evidence",IF(VLOOKUP(P19,'Evidence Register'!A:M,10,FALSE)="Confidential-reviewable","Reviewable evidence","Pin issue: "&VLOOKUP(P19,'Evidence Register'!A:M,10,FALSE))))),"Missing evidence ID"))) | R19: =IF(A19="","",IF(OR(H19="",H19=0),"",IF(S19="","Missing origin",IF(S19<>"Electric Ledger","Yes","No"))))
I20: =IF(OR(A20="",B20<>"Triggered",F20="",H20=""),"",H20-F20) | J20: =IF(OR(A20="",B20<>"Triggered",G20="",H20=""),"",H20-G20) | K20: =IF(A20="","",IF(B20="Not applicable","Not applicable",IF(B20="Not triggered","Not triggered",IF(B20="Unknown","Unresolved, evidence missing",IF(L20="Confidential-reviewable","Unresolved, confidential but reviewable",IF(L20="Contested","Unresolved, contested",IF(COUNTIFS('Stress Cases'!$K$4:$K$12,"Electric Ledger",'Stress Cases'!$L$4:$L$12,A20,'Stress Cases'!$I$4:$I$12,"Failed under stress")>0,"Failed under linked stress case",IF(COUNTIFS('Stress Cases'!$K$4:$K$12,"Electric Ledger",'Stress Cases'!$L$4:$L$12,A20,'Stress Cases'!$I$4:$I$12,"Unresolved*")>0,"Unresolved, linked stress missing",IF(OR(F20="",H20=""),"Unresolved, evidence missing",IF(AND(H20>0,S20=""),"Unresolved, resource origin missing",IF(OR(ISNUMBER(SEARCH("No evidence",Q20)),ISNUMBER(SEARCH("Missing substantive",Q20)),ISNUMBER(SEARCH("Contested substantive",Q20))),"Unresolved, evidence missing",IF(AND(R20="Yes",S20<>"Public-welfare transfer"),"Unresolved, cross-ledger transfer missing",IF(I20<0,"Failed under stress",IF(AND(J20<>"",J20<0),"Conditional pass","Pass")))))))))))))) | Q20: =IF(A20="","",IF(P20="","No evidence ID",IFERROR(IF(VLOOKUP(P20,'Evidence Register'!A:M,11,FALSE)="Missing","Missing substantive evidence",IF(VLOOKUP(P20,'Evidence Register'!A:M,11,FALSE)="Contested","Contested substantive evidence",IF(VLOOKUP(P20,'Evidence Register'!A:M,10,FALSE)="Pinned","Pinned evidence",IF(VLOOKUP(P20,'Evidence Register'!A:M,10,FALSE)="Confidential-reviewable","Reviewable evidence","Pin issue: "&VLOOKUP(P20,'Evidence Register'!A:M,10,FALSE))))),"Missing evidence ID"))) | R20: =IF(A20="","",IF(OR(H20="",H20=0),"",IF(S20="","Missing origin",IF(S20<>"Electric Ledger","Yes","No"))))
I21: =IF(OR(A21="",B21<>"Triggered",F21="",H21=""),"",H21-F21) | J21: =IF(OR(A21="",B21<>"Triggered",G21="",H21=""),"",H21-G21) | K21: =IF(A21="","",IF(B21="Not applicable","Not applicable",IF(B21="Not triggered","Not triggered",IF(B21="Unknown","Unresolved, evidence missing",IF(L21="Confidential-reviewable","Unresolved, confidential but reviewable",IF(L21="Contested","Unresolved, contested",IF(COUNTIFS('Stress Cases'!$K$4:$K$12,"Electric Ledger",'Stress Cases'!$L$4:$L$12,A21,'Stress Cases'!$I$4:$I$12,"Failed under stress")>0,"Failed under linked stress case",IF(COUNTIFS('Stress Cases'!$K$4:$K$12,"Electric Ledger",'Stress Cases'!$L$4:$L$12,A21,'Stress Cases'!$I$4:$I$12,"Unresolved*")>0,"Unresolved, linked stress missing",IF(OR(F21="",H21=""),"Unresolved, evidence missing",IF(AND(H21>0,S21=""),"Unresolved, resource origin missing",IF(OR(ISNUMBER(SEARCH("No evidence",Q21)),ISNUMBER(SEARCH("Missing substantive",Q21)),ISNUMBER(SEARCH("Contested substantive",Q21))),"Unresolved, evidence missing",IF(AND(R21="Yes",S21<>"Public-welfare transfer"),"Unresolved, cross-ledger transfer missing",IF(I21<0,"Failed under stress",IF(AND(J21<>"",J21<0),"Conditional pass","Pass")))))))))))))) | Q21: =IF(A21="","",IF(P21="","No evidence ID",IFERROR(IF(VLOOKUP(P21,'Evidence Register'!A:M,11,FALSE)="Missing","Missing substantive evidence",IF(VLOOKUP(P21,'Evidence Register'!A:M,11,FALSE)="Contested","Contested substantive evidence",IF(VLOOKUP(P21,'Evidence Register'!A:M,10,FALSE)="Pinned","Pinned evidence",IF(VLOOKUP(P21,'Evidence Register'!A:M,10,FALSE)="Confidential-reviewable","Reviewable evidence","Pin issue: "&VLOOKUP(P21,'Evidence Register'!A:M,10,FALSE))))),"Missing evidence ID"))) | R21: =IF(A21="","",IF(OR(H21="",H21=0),"",IF(S21="","Missing origin",IF(S21<>"Electric Ledger","Yes","No"))))
A22: Total / dashboard line | F22: =IF(COUNTIF(B4:B21,"Triggered")=0,"",SUM(F4:F21)) | G22: =IF(COUNTIF(B4:B21,"Triggered")=0,"",IF(COUNT(G4:G21)=0,"",SUM(G4:G21))) | H22: =IF(COUNTIF(B4:B21,"Triggered")=0,"",SUM(H4:H21)) | I22: =IF(F22="","",H22-F22) | J22: =IF(OR(G22="",H22=""),"",H22-G22) | K22: =IF(COUNTIF(B4:B21,"Triggered")=0,"No entries yet",IF(COUNTIF(K4:K21,"*Failed*")>0,"Failed under stress",IF(COUNTIF(K4:K21,"Unresolved*")>0,"Unresolved",IF(COUNTIF(K4:K21,"Conditional pass")>0,"Conditional pass",IF(I22<0,"Failed under stress",IF(AND(J22<>"",J22<0),"Conditional pass","Pass")))))) | R22: =IF(OR(COUNTIFS(B4:B21,"Triggered",R4:R21,"Yes")>0,COUNTIFS(B4:B21,"Triggered",R4:R21,"Missing origin")>0),"Flag: cross-ledger or origin issue",IF(OR(COUNTIFS(B4:B21,"Triggered",Q4:Q21,"Missing evidence ID")>0,COUNTIFS(B4:B21,"Triggered",Q4:Q21,"Needs pin*")>0,COUNTIFS(B4:B21,"Triggered",Q4:Q21,"No evidence ID")>0),"Flag: evidence pin incomplete",""))

Sheet RTO Capacity
A1: RTO Capacity
A3: Ledger line | B3: Applicability | C3: Causation category | D3: Evidence band | E3: Unit | F3: Base exposure | G3: Stress exposure | H3: Credited resources | I3: Base gap | J3: Stress gap | K3: Status | L3: Evidence status | M3: Residual claimant | N3: Source URL / docket | O3: Page / table / order pin | P3: Evidence ID | Q3: Evidence quality check | R3: Cross-ledger check | S3: Resource ledger of origin | T3: Notes
A4: Forecast inclusion | B4: Unknown | C4: Forecast-reliance | E4: MW / UCAP / obligation | I4: =IF(OR(A4="",B4<>"Triggered",F4="",H4=""),"",H4-F4) | J4: =IF(OR(A4="",B4<>"Triggered",G4="",H4=""),"",H4-G4) | K4: =IF(A4="","",IF(B4="Not applicable","Not applicable",IF(B4="Not triggered","Not triggered",IF(B4="Unknown","Unresolved, evidence missing",IF(L4="Confidential-reviewable","Unresolved, confidential but reviewable",IF(L4="Contested","Unresolved, contested",IF(COUNTIFS('Stress Cases'!$K$4:$K$12,"RTO Capacity",'Stress Cases'!$L$4:$L$12,A4,'Stress Cases'!$I$4:$I$12,"Failed under stress")>0,"Failed under linked stress case",IF(COUNTIFS('Stress Cases'!$K$4:$K$12,"RTO Capacity",'Stress Cases'!$L$4:$L$12,A4,'Stress Cases'!$I$4:$I$12,"Unresolved*")>0,"Unresolved, linked stress missing",IF(OR(F4="",H4=""),"Unresolved, evidence missing",IF(AND(H4>0,S4=""),"Unresolved, resource origin missing",IF(OR(ISNUMBER(SEARCH("No evidence",Q4)),ISNUMBER(SEARCH("Missing substantive",Q4)),ISNUMBER(SEARCH("Contested substantive",Q4))),"Unresolved, evidence missing",IF(AND(R4="Yes",S4<>"Public-welfare transfer"),"Unresolved, cross-ledger transfer missing",IF(I4<0,"Failed under stress",IF(AND(J4<>"",J4<0),"Conditional pass","Pass")))))))))))))) | L4: Missing | Q4: =IF(A4="","",IF(P4="","No evidence ID",IFERROR(IF(VLOOKUP(P4,'Evidence Register'!A:M,11,FALSE)="Missing","Missing substantive evidence",IF(VLOOKUP(P4,'Evidence Register'!A:M,11,FALSE)="Contested","Contested substantive evidence",IF(VLOOKUP(P4,'Evidence Register'!A:M,10,FALSE)="Pinned","Pinned evidence",IF(VLOOKUP(P4,'Evidence Register'!A:M,10,FALSE)="Confidential-reviewable","Reviewable evidence","Pin issue: "&VLOOKUP(P4,'Evidence Register'!A:M,10,FALSE))))),"Missing evidence ID"))) | R4: =IF(A4="","",IF(OR(H4="",H4=0),"",IF(S4="","Missing origin",IF(S4<>"RTO Capacity","Yes","No"))))
A5: Capacity price / obligation | B5: Unknown | C5: Pooled market | E5: delivery-year $ | I5: =IF(OR(A5="",B5<>"Triggered",F5="",H5=""),"",H5-F5) | J5: =IF(OR(A5="",B5<>"Triggered",G5="",H5=""),"",H5-G5) | K5: =IF(A5="","",IF(B5="Not applicable","Not applicable",IF(B5="Not triggered","Not triggered",IF(B5="Unknown","Unresolved, evidence missing",IF(L5="Confidential-reviewable","Unresolved, confidential but reviewable",IF(L5="Contested","Unresolved, contested",IF(COUNTIFS('Stress Cases'!$K$4:$K$12,"RTO Capacity",'Stress Cases'!$L$4:$L$12,A5,'Stress Cases'!$I$4:$I$12,"Failed under stress")>0,"Failed under linked stress case",IF(COUNTIFS('Stress Cases'!$K$4:$K$12,"RTO Capacity",'Stress Cases'!$L$4:$L$12,A5,'Stress Cases'!$I$4:$I$12,"Unresolved*")>0,"Unresolved, linked stress missing",IF(OR(F5="",H5=""),"Unresolved, evidence missing",IF(AND(H5>0,S5=""),"Unresolved, resource origin missing",IF(OR(ISNUMBER(SEARCH("No evidence",Q5)),ISNUMBER(SEARCH("Missing substantive",Q5)),ISNUMBER(SEARCH("Contested substantive",Q5))),"Unresolved, evidence missing",IF(AND(R5="Yes",S5<>"Public-welfare transfer"),"Unresolved, cross-ledger transfer missing",IF(I5<0,"Failed under stress",IF(AND(J5<>"",J5<0),"Conditional pass","Pass")))))))))))))) | L5: Missing | Q5: =IF(A5="","",IF(P5="","No evidence ID",IFERROR(IF(VLOOKUP(P5,'Evidence Register'!A:M,11,FALSE)="Missing","Missing substantive evidence",IF(VLOOKUP(P5,'Evidence Register'!A:M,11,FALSE)="Contested","Contested substantive evidence",IF(VLOOKUP(P5,'Evidence Register'!A:M,10,FALSE)="Pinned","Pinned evidence",IF(VLOOKUP(P5,'Evidence Register'!A:M,10,FALSE)="Confidential-reviewable","Reviewable evidence","Pin issue: "&VLOOKUP(P5,'Evidence Register'!A:M,10,FALSE))))),"Missing evidence ID"))) | R5: =IF(A5="","",IF(OR(H5="",H5=0),"",IF(S5="","Missing origin",IF(S5<>"RTO Capacity","Yes","No"))))
A6: Backstop procurement | B6: Unknown | C6: Pooled market | E6: delivery-year $ | I6: =IF(OR(A6="",B6<>"Triggered",F6="",H6=""),"",H6-F6) | J6: =IF(OR(A6="",B6<>"Triggered",G6="",H6=""),"",H6-G6) | K6: =IF(A6="","",IF(B6="Not applicable","Not applicable",IF(B6="Not triggered","Not triggered",IF(B6="Unknown","Unresolved, evidence missing",IF(L6="Confidential-reviewable","Unresolved, confidential but reviewable",IF(L6="Contested","Unresolved, contested",IF(COUNTIFS('Stress Cases'!$K$4:$K$12,"RTO Capacity",'Stress Cases'!$L$4:$L$12,A6,'Stress Cases'!$I$4:$I$12,"Failed under stress")>0,"Failed under linked stress case",IF(COUNTIFS('Stress Cases'!$K$4:$K$12,"RTO Capacity",'Stress Cases'!$L$4:$L$12,A6,'Stress Cases'!$I$4:$I$12,"Unresolved*")>0,"Unresolved, linked stress missing",IF(OR(F6="",H6=""),"Unresolved, evidence missing",IF(AND(H6>0,S6=""),"Unresolved, resource origin missing",IF(OR(ISNUMBER(SEARCH("No evidence",Q6)),ISNUMBER(SEARCH("Missing substantive",Q6)),ISNUMBER(SEARCH("Contested substantive",Q6))),"Unresolved, evidence missing",IF(AND(R6="Yes",S6<>"Public-welfare transfer"),"Unresolved, cross-ledger transfer missing",IF(I6<0,"Failed under stress",IF(AND(J6<>"",J6<0),"Conditional pass","Pass")))))))))))))) | L6: Missing | Q6: =IF(A6="","",IF(P6="","No evidence ID",IFERROR(IF(VLOOKUP(P6,'Evidence Register'!A:M,11,FALSE)="Missing","Missing substantive evidence",IF(VLOOKUP(P6,'Evidence Register'!A:M,11,FALSE)="Contested","Contested substantive evidence",IF(VLOOKUP(P6,'Evidence Register'!A:M,10,FALSE)="Pinned","Pinned evidence",IF(VLOOKUP(P6,'Evidence Register'!A:M,10,FALSE)="Confidential-reviewable","Reviewable evidence","Pin issue: "&VLOOKUP(P6,'Evidence Register'!A:M,10,FALSE))))),"Missing evidence ID"))) | R6: =IF(A6="","",IF(OR(H6="",H6=0),"",IF(S6="","Missing origin",IF(S6<>"RTO Capacity","Yes","No"))))
A7: Curtailment / qualifying capacity | B7: Unknown | C7: Technical performance | E7: UCAP MW / $ | I7: =IF(OR(A7="",B7<>"Triggered",F7="",H7=""),"",H7-F7) | J7: =IF(OR(A7="",B7<>"Triggered",G7="",H7=""),"",H7-G7) | K7: =IF(A7="","",IF(B7="Not applicable","Not applicable",IF(B7="Not triggered","Not triggered",IF(B7="Unknown","Unresolved, evidence missing",IF(L7="Confidential-reviewable","Unresolved, confidential but reviewable",IF(L7="Contested","Unresolved, contested",IF(COUNTIFS('Stress Cases'!$K$4:$K$12,"RTO Capacity",'Stress Cases'!$L$4:$L$12,A7,'Stress Cases'!$I$4:$I$12,"Failed under stress")>0,"Failed under linked stress case",IF(COUNTIFS('Stress Cases'!$K$4:$K$12,"RTO Capacity",'Stress Cases'!$L$4:$L$12,A7,'Stress Cases'!$I$4:$I$12,"Unresolved*")>0,"Unresolved, linked stress missing",IF(OR(F7="",H7=""),"Unresolved, evidence missing",IF(AND(H7>0,S7=""),"Unresolved, resource origin missing",IF(OR(ISNUMBER(SEARCH("No evidence",Q7)),ISNUMBER(SEARCH("Missing substantive",Q7)),ISNUMBER(SEARCH("Contested substantive",Q7))),"Unresolved, evidence missing",IF(AND(R7="Yes",S7<>"Public-welfare transfer"),"Unresolved, cross-ledger transfer missing",IF(I7<0,"Failed under stress",IF(AND(J7<>"",J7<0),"Conditional pass","Pass")))))))))))))) | L7: Missing | Q7: =IF(A7="","",IF(P7="","No evidence ID",IFERROR(IF(VLOOKUP(P7,'Evidence Register'!A:M,11,FALSE)="Missing","Missing substantive evidence",IF(VLOOKUP(P7,'Evidence Register'!A:M,11,FALSE)="Contested","Contested substantive evidence",IF(VLOOKUP(P7,'Evidence Register'!A:M,10,FALSE)="Pinned","Pinned evidence",IF(VLOOKUP(P7,'Evidence Register'!A:M,10,FALSE)="Confidential-reviewable","Reviewable evidence","Pin issue: "&VLOOKUP(P7,'Evidence Register'!A:M,10,FALSE))))),"Missing evidence ID"))) | R7: =IF(A7="","",IF(OR(H7="",H7=0),"",IF(S7="","Missing origin",IF(S7<>"RTO Capacity","Yes","No"))))
A8: Retail pass-through | B8: Unknown | C8: Regulatory assignment | E8: class allocation / rider | I8: =IF(OR(A8="",B8<>"Triggered",F8="",H8=""),"",H8-F8) | J8: =IF(OR(A8="",B8<>"Triggered",G8="",H8=""),"",H8-G8) | K8: =IF(A8="","",IF(B8="Not applicable","Not applicable",IF(B8="Not triggered","Not triggered",IF(B8="Unknown","Unresolved, evidence missing",IF(L8="Confidential-reviewable","Unresolved, confidential but reviewable",IF(L8="Contested","Unresolved, contested",IF(COUNTIFS('Stress Cases'!$K$4:$K$12,"RTO Capacity",'Stress Cases'!$L$4:$L$12,A8,'Stress Cases'!$I$4:$I$12,"Failed under stress")>0,"Failed under linked stress case",IF(COUNTIFS('Stress Cases'!$K$4:$K$12,"RTO Capacity",'Stress Cases'!$L$4:$L$12,A8,'Stress Cases'!$I$4:$I$12,"Unresolved*")>0,"Unresolved, linked stress missing",IF(OR(F8="",H8=""),"Unresolved, evidence missing",IF(AND(H8>0,S8=""),"Unresolved, resource origin missing",IF(OR(ISNUMBER(SEARCH("No evidence",Q8)),ISNUMBER(SEARCH("Missing substantive",Q8)),ISNUMBER(SEARCH("Contested substantive",Q8))),"Unresolved, evidence missing",IF(AND(R8="Yes",S8<>"Public-welfare transfer"),"Unresolved, cross-ledger transfer missing",IF(I8<0,"Failed under stress",IF(AND(J8<>"",J8<0),"Conditional pass","Pass")))))))))))))) | L8: Missing | Q8: =IF(A8="","",IF(P8="","No evidence ID",IFERROR(IF(VLOOKUP(P8,'Evidence Register'!A:M,11,FALSE)="Missing","Missing substantive evidence",IF(VLOOKUP(P8,'Evidence Register'!A:M,11,FALSE)="Contested","Contested substantive evidence",IF(VLOOKUP(P8,'Evidence Register'!A:M,10,FALSE)="Pinned","Pinned evidence",IF(VLOOKUP(P8,'Evidence Register'!A:M,10,FALSE)="Confidential-reviewable","Reviewable evidence","Pin issue: "&VLOOKUP(P8,'Evidence Register'!A:M,10,FALSE))))),"Missing evidence ID"))) | R8: =IF(A8="","",IF(OR(H8="",H8=0),"",IF(S8="","Missing origin",IF(S8<>"RTO Capacity","Yes","No"))))
I9: =IF(OR(A9="",B9<>"Triggered",F9="",H9=""),"",H9-F9) | J9: =IF(OR(A9="",B9<>"Triggered",G9="",H9=""),"",H9-G9) | K9: =IF(A9="","",IF(B9="Not applicable","Not applicable",IF(B9="Not triggered","Not triggered",IF(B9="Unknown","Unresolved, evidence missing",IF(L9="Confidential-reviewable","Unresolved, confidential but reviewable",IF(L9="Contested","Unresolved, contested",IF(COUNTIFS('Stress Cases'!$K$4:$K$12,"RTO Capacity",'Stress Cases'!$L$4:$L$12,A9,'Stress Cases'!$I$4:$I$12,"Failed under stress")>0,"Failed under linked stress case",IF(COUNTIFS('Stress Cases'!$K$4:$K$12,"RTO Capacity",'Stress Cases'!$L$4:$L$12,A9,'Stress Cases'!$I$4:$I$12,"Unresolved*")>0,"Unresolved, linked stress missing",IF(OR(F9="",H9=""),"Unresolved, evidence missing",IF(AND(H9>0,S9=""),"Unresolved, resource origin missing",IF(OR(ISNUMBER(SEARCH("No evidence",Q9)),ISNUMBER(SEARCH("Missing substantive",Q9)),ISNUMBER(SEARCH("Contested substantive",Q9))),"Unresolved, evidence missing",IF(AND(R9="Yes",S9<>"Public-welfare transfer"),"Unresolved, cross-ledger transfer missing",IF(I9<0,"Failed under stress",IF(AND(J9<>"",J9<0),"Conditional pass","Pass")))))))))))))) | Q9: =IF(A9="","",IF(P9="","No evidence ID",IFERROR(IF(VLOOKUP(P9,'Evidence Register'!A:M,11,FALSE)="Missing","Missing substantive evidence",IF(VLOOKUP(P9,'Evidence Register'!A:M,11,FALSE)="Contested","Contested substantive evidence",IF(VLOOKUP(P9,'Evidence Register'!A:M,10,FALSE)="Pinned","Pinned evidence",IF(VLOOKUP(P9,'Evidence Register'!A:M,10,FALSE)="Confidential-reviewable","Reviewable evidence","Pin issue: "&VLOOKUP(P9,'Evidence Register'!A:M,10,FALSE))))),"Missing evidence ID"))) | R9: =IF(A9="","",IF(OR(H9="",H9=0),"",IF(S9="","Missing origin",IF(S9<>"RTO Capacity","Yes","No"))))
I10: =IF(OR(A10="",B10<>"Triggered",F10="",H10=""),"",H10-F10) | J10: =IF(OR(A10="",B10<>"Triggered",G10="",H10=""),"",H10-G10) | K10: =IF(A10="","",IF(B10="Not applicable","Not applicable",IF(B10="Not triggered","Not triggered",IF(B10="Unknown","Unresolved, evidence missing",IF(L10="Confidential-reviewable","Unresolved, confidential but reviewable",IF(L10="Contested","Unresolved, contested",IF(COUNTIFS('Stress Cases'!$K$4:$K$12,"RTO Capacity",'Stress Cases'!$L$4:$L$12,A10,'Stress Cases'!$I$4:$I$12,"Failed under stress")>0,"Failed under linked stress case",IF(COUNTIFS('Stress Cases'!$K$4:$K$12,"RTO Capacity",'Stress Cases'!$L$4:$L$12,A10,'Stress Cases'!$I$4:$I$12,"Unresolved*")>0,"Unresolved, linked stress missing",IF(OR(F10="",H10=""),"Unresolved, evidence missing",IF(AND(H10>0,S10=""),"Unresolved, resource origin missing",IF(OR(ISNUMBER(SEARCH("No evidence",Q10)),ISNUMBER(SEARCH("Missing substantive",Q10)),ISNUMBER(SEARCH("Contested substantive",Q10))),"Unresolved, evidence missing",IF(AND(R10="Yes",S10<>"Public-welfare transfer"),"Unresolved, cross-ledger transfer missing",IF(I10<0,"Failed under stress",IF(AND(J10<>"",J10<0),"Conditional pass","Pass")))))))))))))) | Q10: =IF(A10="","",IF(P10="","No evidence ID",IFERROR(IF(VLOOKUP(P10,'Evidence Register'!A:M,11,FALSE)="Missing","Missing substantive evidence",IF(VLOOKUP(P10,'Evidence Register'!A:M,11,FALSE)="Contested","Contested substantive evidence",IF(VLOOKUP(P10,'Evidence Register'!A:M,10,FALSE)="Pinned","Pinned evidence",IF(VLOOKUP(P10,'Evidence Register'!A:M,10,FALSE)="Confidential-reviewable","Reviewable evidence","Pin issue: "&VLOOKUP(P10,'Evidence Register'!A:M,10,FALSE))))),"Missing evidence ID"))) | R10: =IF(A10="","",IF(OR(H10="",H10=0),"",IF(S10="","Missing origin",IF(S10<>"RTO Capacity","Yes","No"))))
I11: =IF(OR(A11="",B11<>"Triggered",F11="",H11=""),"",H11-F11) | J11: =IF(OR(A11="",B11<>"Triggered",G11="",H11=""),"",H11-G11) | K11: =IF(A11="","",IF(B11="Not applicable","Not applicable",IF(B11="Not triggered","Not triggered",IF(B11="Unknown","Unresolved, evidence missing",IF(L11="Confidential-reviewable","Unresolved, confidential but reviewable",IF(L11="Contested","Unresolved, contested",IF(COUNTIFS('Stress Cases'!$K$4:$K$12,"RTO Capacity",'Stress Cases'!$L$4:$L$12,A11,'Stress Cases'!$I$4:$I$12,"Failed under stress")>0,"Failed under linked stress case",IF(COUNTIFS('Stress Cases'!$K$4:$K$12,"RTO Capacity",'Stress Cases'!$L$4:$L$12,A11,'Stress Cases'!$I$4:$I$12,"Unresolved*")>0,"Unresolved, linked stress missing",IF(OR(F11="",H11=""),"Unresolved, evidence missing",IF(AND(H11>0,S11=""),"Unresolved, resource origin missing",IF(OR(ISNUMBER(SEARCH("No evidence",Q11)),ISNUMBER(SEARCH("Missing substantive",Q11)),ISNUMBER(SEARCH("Contested substantive",Q11))),"Unresolved, evidence missing",IF(AND(R11="Yes",S11<>"Public-welfare transfer"),"Unresolved, cross-ledger transfer missing",IF(I11<0,"Failed under stress",IF(AND(J11<>"",J11<0),"Conditional pass","Pass")))))))))))))) | Q11: =IF(A11="","",IF(P11="","No evidence ID",IFERROR(IF(VLOOKUP(P11,'Evidence Register'!A:M,11,FALSE)="Missing","Missing substantive evidence",IF(VLOOKUP(P11,'Evidence Register'!A:M,11,FALSE)="Contested","Contested substantive evidence",IF(VLOOKUP(P11,'Evidence Register'!A:M,10,FALSE)="Pinned","Pinned evidence",IF(VLOOKUP(P11,'Evidence Register'!A:M,10,FALSE)="Confidential-reviewable","Reviewable evidence","Pin issue: "&VLOOKUP(P11,'Evidence Register'!A:M,10,FALSE))))),"Missing evidence ID"))) | R11: =IF(A11="","",IF(OR(H11="",H11=0),"",IF(S11="","Missing origin",IF(S11<>"RTO Capacity","Yes","No"))))
I12: =IF(OR(A12="",B12<>"Triggered",F12="",H12=""),"",H12-F12) | J12: =IF(OR(A12="",B12<>"Triggered",G12="",H12=""),"",H12-G12) | K12: =IF(A12="","",IF(B12="Not applicable","Not applicable",IF(B12="Not triggered","Not triggered",IF(B12="Unknown","Unresolved, evidence missing",IF(L12="Confidential-reviewable","Unresolved, confidential but reviewable",IF(L12="Contested","Unresolved, contested",IF(COUNTIFS('Stress Cases'!$K$4:$K$12,"RTO Capacity",'Stress Cases'!$L$4:$L$12,A12,'Stress Cases'!$I$4:$I$12,"Failed under stress")>0,"Failed under linked stress case",IF(COUNTIFS('Stress Cases'!$K$4:$K$12,"RTO Capacity",'Stress Cases'!$L$4:$L$12,A12,'Stress Cases'!$I$4:$I$12,"Unresolved*")>0,"Unresolved, linked stress missing",IF(OR(F12="",H12=""),"Unresolved, evidence missing",IF(AND(H12>0,S12=""),"Unresolved, resource origin missing",IF(OR(ISNUMBER(SEARCH("No evidence",Q12)),ISNUMBER(SEARCH("Missing substantive",Q12)),ISNUMBER(SEARCH("Contested substantive",Q12))),"Unresolved, evidence missing",IF(AND(R12="Yes",S12<>"Public-welfare transfer"),"Unresolved, cross-ledger transfer missing",IF(I12<0,"Failed under stress",IF(AND(J12<>"",J12<0),"Conditional pass","Pass")))))))))))))) | Q12: =IF(A12="","",IF(P12="","No evidence ID",IFERROR(IF(VLOOKUP(P12,'Evidence Register'!A:M,11,FALSE)="Missing","Missing substantive evidence",IF(VLOOKUP(P12,'Evidence Register'!A:M,11,FALSE)="Contested","Contested substantive evidence",IF(VLOOKUP(P12,'Evidence Register'!A:M,10,FALSE)="Pinned","Pinned evidence",IF(VLOOKUP(P12,'Evidence Register'!A:M,10,FALSE)="Confidential-reviewable","Reviewable evidence","Pin issue: "&VLOOKUP(P12,'Evidence Register'!A:M,10,FALSE))))),"Missing evidence ID"))) | R12: =IF(A12="","",IF(OR(H12="",H12=0),"",IF(S12="","Missing origin",IF(S12<>"RTO Capacity","Yes","No"))))
I13: =IF(OR(A13="",B13<>"Triggered",F13="",H13=""),"",H13-F13) | J13: =IF(OR(A13="",B13<>"Triggered",G13="",H13=""),"",H13-G13) | K13: =IF(A13="","",IF(B13="Not applicable","Not applicable",IF(B13="Not triggered","Not triggered",IF(B13="Unknown","Unresolved, evidence missing",IF(L13="Confidential-reviewable","Unresolved, confidential but reviewable",IF(L13="Contested","Unresolved, contested",IF(COUNTIFS('Stress Cases'!$K$4:$K$12,"RTO Capacity",'Stress Cases'!$L$4:$L$12,A13,'Stress Cases'!$I$4:$I$12,"Failed under stress")>0,"Failed under linked stress case",IF(COUNTIFS('Stress Cases'!$K$4:$K$12,"RTO Capacity",'Stress Cases'!$L$4:$L$12,A13,'Stress Cases'!$I$4:$I$12,"Unresolved*")>0,"Unresolved, linked stress missing",IF(OR(F13="",H13=""),"Unresolved, evidence missing",IF(AND(H13>0,S13=""),"Unresolved, resource origin missing",IF(OR(ISNUMBER(SEARCH("No evidence",Q13)),ISNUMBER(SEARCH("Missing substantive",Q13)),ISNUMBER(SEARCH("Contested substantive",Q13))),"Unresolved, evidence missing",IF(AND(R13="Yes",S13<>"Public-welfare transfer"),"Unresolved, cross-ledger transfer missing",IF(I13<0,"Failed under stress",IF(AND(J13<>"",J13<0),"Conditional pass","Pass")))))))))))))) | Q13: =IF(A13="","",IF(P13="","No evidence ID",IFERROR(IF(VLOOKUP(P13,'Evidence Register'!A:M,11,FALSE)="Missing","Missing substantive evidence",IF(VLOOKUP(P13,'Evidence Register'!A:M,11,FALSE)="Contested","Contested substantive evidence",IF(VLOOKUP(P13,'Evidence Register'!A:M,10,FALSE)="Pinned","Pinned evidence",IF(VLOOKUP(P13,'Evidence Register'!A:M,10,FALSE)="Confidential-reviewable","Reviewable evidence","Pin issue: "&VLOOKUP(P13,'Evidence Register'!A:M,10,FALSE))))),"Missing evidence ID"))) | R13: =IF(A13="","",IF(OR(H13="",H13=0),"",IF(S13="","Missing origin",IF(S13<>"RTO Capacity","Yes","No"))))
I14: =IF(OR(A14="",B14<>"Triggered",F14="",H14=""),"",H14-F14) | J14: =IF(OR(A14="",B14<>"Triggered",G14="",H14=""),"",H14-G14) | K14: =IF(A14="","",IF(B14="Not applicable","Not applicable",IF(B14="Not triggered","Not triggered",IF(B14="Unknown","Unresolved, evidence missing",IF(L14="Confidential-reviewable","Unresolved, confidential but reviewable",IF(L14="Contested","Unresolved, contested",IF(COUNTIFS('Stress Cases'!$K$4:$K$12,"RTO Capacity",'Stress Cases'!$L$4:$L$12,A14,'Stress Cases'!$I$4:$I$12,"Failed under stress")>0,"Failed under linked stress case",IF(COUNTIFS('Stress Cases'!$K$4:$K$12,"RTO Capacity",'Stress Cases'!$L$4:$L$12,A14,'Stress Cases'!$I$4:$I$12,"Unresolved*")>0,"Unresolved, linked stress missing",IF(OR(F14="",H14=""),"Unresolved, evidence missing",IF(AND(H14>0,S14=""),"Unresolved, resource origin missing",IF(OR(ISNUMBER(SEARCH("No evidence",Q14)),ISNUMBER(SEARCH("Missing substantive",Q14)),ISNUMBER(SEARCH("Contested substantive",Q14))),"Unresolved, evidence missing",IF(AND(R14="Yes",S14<>"Public-welfare transfer"),"Unresolved, cross-ledger transfer missing",IF(I14<0,"Failed under stress",IF(AND(J14<>"",J14<0),"Conditional pass","Pass")))))))))))))) | Q14: =IF(A14="","",IF(P14="","No evidence ID",IFERROR(IF(VLOOKUP(P14,'Evidence Register'!A:M,11,FALSE)="Missing","Missing substantive evidence",IF(VLOOKUP(P14,'Evidence Register'!A:M,11,FALSE)="Contested","Contested substantive evidence",IF(VLOOKUP(P14,'Evidence Register'!A:M,10,FALSE)="Pinned","Pinned evidence",IF(VLOOKUP(P14,'Evidence Register'!A:M,10,FALSE)="Confidential-reviewable","Reviewable evidence","Pin issue: "&VLOOKUP(P14,'Evidence Register'!A:M,10,FALSE))))),"Missing evidence ID"))) | R14: =IF(A14="","",IF(OR(H14="",H14=0),"",IF(S14="","Missing origin",IF(S14<>"RTO Capacity","Yes","No"))))
I15: =IF(OR(A15="",B15<>"Triggered",F15="",H15=""),"",H15-F15) | J15: =IF(OR(A15="",B15<>"Triggered",G15="",H15=""),"",H15-G15) | K15: =IF(A15="","",IF(B15="Not applicable","Not applicable",IF(B15="Not triggered","Not triggered",IF(B15="Unknown","Unresolved, evidence missing",IF(L15="Confidential-reviewable","Unresolved, confidential but reviewable",IF(L15="Contested","Unresolved, contested",IF(COUNTIFS('Stress Cases'!$K$4:$K$12,"RTO Capacity",'Stress Cases'!$L$4:$L$12,A15,'Stress Cases'!$I$4:$I$12,"Failed under stress")>0,"Failed under linked stress case",IF(COUNTIFS('Stress Cases'!$K$4:$K$12,"RTO Capacity",'Stress Cases'!$L$4:$L$12,A15,'Stress Cases'!$I$4:$I$12,"Unresolved*")>0,"Unresolved, linked stress missing",IF(OR(F15="",H15=""),"Unresolved, evidence missing",IF(AND(H15>0,S15=""),"Unresolved, resource origin missing",IF(OR(ISNUMBER(SEARCH("No evidence",Q15)),ISNUMBER(SEARCH("Missing substantive",Q15)),ISNUMBER(SEARCH("Contested substantive",Q15))),"Unresolved, evidence missing",IF(AND(R15="Yes",S15<>"Public-welfare transfer"),"Unresolved, cross-ledger transfer missing",IF(I15<0,"Failed under stress",IF(AND(J15<>"",J15<0),"Conditional pass","Pass")))))))))))))) | Q15: =IF(A15="","",IF(P15="","No evidence ID",IFERROR(IF(VLOOKUP(P15,'Evidence Register'!A:M,11,FALSE)="Missing","Missing substantive evidence",IF(VLOOKUP(P15,'Evidence Register'!A:M,11,FALSE)="Contested","Contested substantive evidence",IF(VLOOKUP(P15,'Evidence Register'!A:M,10,FALSE)="Pinned","Pinned evidence",IF(VLOOKUP(P15,'Evidence Register'!A:M,10,FALSE)="Confidential-reviewable","Reviewable evidence","Pin issue: "&VLOOKUP(P15,'Evidence Register'!A:M,10,FALSE))))),"Missing evidence ID"))) | R15: =IF(A15="","",IF(OR(H15="",H15=0),"",IF(S15="","Missing origin",IF(S15<>"RTO Capacity","Yes","No"))))
I16: =IF(OR(A16="",B16<>"Triggered",F16="",H16=""),"",H16-F16) | J16: =IF(OR(A16="",B16<>"Triggered",G16="",H16=""),"",H16-G16) | K16: =IF(A16="","",IF(B16="Not applicable","Not applicable",IF(B16="Not triggered","Not triggered",IF(B16="Unknown","Unresolved, evidence missing",IF(L16="Confidential-reviewable","Unresolved, confidential but reviewable",IF(L16="Contested","Unresolved, contested",IF(COUNTIFS('Stress Cases'!$K$4:$K$12,"RTO Capacity",'Stress Cases'!$L$4:$L$12,A16,'Stress Cases'!$I$4:$I$12,"Failed under stress")>0,"Failed under linked stress case",IF(COUNTIFS('Stress Cases'!$K$4:$K$12,"RTO Capacity",'Stress Cases'!$L$4:$L$12,A16,'Stress Cases'!$I$4:$I$12,"Unresolved*")>0,"Unresolved, linked stress missing",IF(OR(F16="",H16=""),"Unresolved, evidence missing",IF(AND(H16>0,S16=""),"Unresolved, resource origin missing",IF(OR(ISNUMBER(SEARCH("No evidence",Q16)),ISNUMBER(SEARCH("Missing substantive",Q16)),ISNUMBER(SEARCH("Contested substantive",Q16))),"Unresolved, evidence missing",IF(AND(R16="Yes",S16<>"Public-welfare transfer"),"Unresolved, cross-ledger transfer missing",IF(I16<0,"Failed under stress",IF(AND(J16<>"",J16<0),"Conditional pass","Pass")))))))))))))) | Q16: =IF(A16="","",IF(P16="","No evidence ID",IFERROR(IF(VLOOKUP(P16,'Evidence Register'!A:M,11,FALSE)="Missing","Missing substantive evidence",IF(VLOOKUP(P16,'Evidence Register'!A:M,11,FALSE)="Contested","Contested substantive evidence",IF(VLOOKUP(P16,'Evidence Register'!A:M,10,FALSE)="Pinned","Pinned evidence",IF(VLOOKUP(P16,'Evidence Register'!A:M,10,FALSE)="Confidential-reviewable","Reviewable evidence","Pin issue: "&VLOOKUP(P16,'Evidence Register'!A:M,10,FALSE))))),"Missing evidence ID"))) | R16: =IF(A16="","",IF(OR(H16="",H16=0),"",IF(S16="","Missing origin",IF(S16<>"RTO Capacity","Yes","No"))))
I17: =IF(OR(A17="",B17<>"Triggered",F17="",H17=""),"",H17-F17) | J17: =IF(OR(A17="",B17<>"Triggered",G17="",H17=""),"",H17-G17) | K17: =IF(A17="","",IF(B17="Not applicable","Not applicable",IF(B17="Not triggered","Not triggered",IF(B17="Unknown","Unresolved, evidence missing",IF(L17="Confidential-reviewable","Unresolved, confidential but reviewable",IF(L17="Contested","Unresolved, contested",IF(COUNTIFS('Stress Cases'!$K$4:$K$12,"RTO Capacity",'Stress Cases'!$L$4:$L$12,A17,'Stress Cases'!$I$4:$I$12,"Failed under stress")>0,"Failed under linked stress case",IF(COUNTIFS('Stress Cases'!$K$4:$K$12,"RTO Capacity",'Stress Cases'!$L$4:$L$12,A17,'Stress Cases'!$I$4:$I$12,"Unresolved*")>0,"Unresolved, linked stress missing",IF(OR(F17="",H17=""),"Unresolved, evidence missing",IF(AND(H17>0,S17=""),"Unresolved, resource origin missing",IF(OR(ISNUMBER(SEARCH("No evidence",Q17)),ISNUMBER(SEARCH("Missing substantive",Q17)),ISNUMBER(SEARCH("Contested substantive",Q17))),"Unresolved, evidence missing",IF(AND(R17="Yes",S17<>"Public-welfare transfer"),"Unresolved, cross-ledger transfer missing",IF(I17<0,"Failed under stress",IF(AND(J17<>"",J17<0),"Conditional pass","Pass")))))))))))))) | Q17: =IF(A17="","",IF(P17="","No evidence ID",IFERROR(IF(VLOOKUP(P17,'Evidence Register'!A:M,11,FALSE)="Missing","Missing substantive evidence",IF(VLOOKUP(P17,'Evidence Register'!A:M,11,FALSE)="Contested","Contested substantive evidence",IF(VLOOKUP(P17,'Evidence Register'!A:M,10,FALSE)="Pinned","Pinned evidence",IF(VLOOKUP(P17,'Evidence Register'!A:M,10,FALSE)="Confidential-reviewable","Reviewable evidence","Pin issue: "&VLOOKUP(P17,'Evidence Register'!A:M,10,FALSE))))),"Missing evidence ID"))) | R17: =IF(A17="","",IF(OR(H17="",H17=0),"",IF(S17="","Missing origin",IF(S17<>"RTO Capacity","Yes","No"))))
I18: =IF(OR(A18="",B18<>"Triggered",F18="",H18=""),"",H18-F18) | J18: =IF(OR(A18="",B18<>"Triggered",G18="",H18=""),"",H18-G18) | K18: =IF(A18="","",IF(B18="Not applicable","Not applicable",IF(B18="Not triggered","Not triggered",IF(B18="Unknown","Unresolved, evidence missing",IF(L18="Confidential-reviewable","Unresolved, confidential but reviewable",IF(L18="Contested","Unresolved, contested",IF(COUNTIFS('Stress Cases'!$K$4:$K$12,"RTO Capacity",'Stress Cases'!$L$4:$L$12,A18,'Stress Cases'!$I$4:$I$12,"Failed under stress")>0,"Failed under linked stress case",IF(COUNTIFS('Stress Cases'!$K$4:$K$12,"RTO Capacity",'Stress Cases'!$L$4:$L$12,A18,'Stress Cases'!$I$4:$I$12,"Unresolved*")>0,"Unresolved, linked stress missing",IF(OR(F18="",H18=""),"Unresolved, evidence missing",IF(AND(H18>0,S18=""),"Unresolved, resource origin missing",IF(OR(ISNUMBER(SEARCH("No evidence",Q18)),ISNUMBER(SEARCH("Missing substantive",Q18)),ISNUMBER(SEARCH("Contested substantive",Q18))),"Unresolved, evidence missing",IF(AND(R18="Yes",S18<>"Public-welfare transfer"),"Unresolved, cross-ledger transfer missing",IF(I18<0,"Failed under stress",IF(AND(J18<>"",J18<0),"Conditional pass","Pass")))))))))))))) | Q18: =IF(A18="","",IF(P18="","No evidence ID",IFERROR(IF(VLOOKUP(P18,'Evidence Register'!A:M,11,FALSE)="Missing","Missing substantive evidence",IF(VLOOKUP(P18,'Evidence Register'!A:M,11,FALSE)="Contested","Contested substantive evidence",IF(VLOOKUP(P18,'Evidence Register'!A:M,10,FALSE)="Pinned","Pinned evidence",IF(VLOOKUP(P18,'Evidence Register'!A:M,10,FALSE)="Confidential-reviewable","Reviewable evidence","Pin issue: "&VLOOKUP(P18,'Evidence Register'!A:M,10,FALSE))))),"Missing evidence ID"))) | R18: =IF(A18="","",IF(OR(H18="",H18=0),"",IF(S18="","Missing origin",IF(S18<>"RTO Capacity","Yes","No"))))
I19: =IF(OR(A19="",B19<>"Triggered",F19="",H19=""),"",H19-F19) | J19: =IF(OR(A19="",B19<>"Triggered",G19="",H19=""),"",H19-G19) | K19: =IF(A19="","",IF(B19="Not applicable","Not applicable",IF(B19="Not triggered","Not triggered",IF(B19="Unknown","Unresolved, evidence missing",IF(L19="Confidential-reviewable","Unresolved, confidential but reviewable",IF(L19="Contested","Unresolved, contested",IF(COUNTIFS('Stress Cases'!$K$4:$K$12,"RTO Capacity",'Stress Cases'!$L$4:$L$12,A19,'Stress Cases'!$I$4:$I$12,"Failed under stress")>0,"Failed under linked stress case",IF(COUNTIFS('Stress Cases'!$K$4:$K$12,"RTO Capacity",'Stress Cases'!$L$4:$L$12,A19,'Stress Cases'!$I$4:$I$12,"Unresolved*")>0,"Unresolved, linked stress missing",IF(OR(F19="",H19=""),"Unresolved, evidence missing",IF(AND(H19>0,S19=""),"Unresolved, resource origin missing",IF(OR(ISNUMBER(SEARCH("No evidence",Q19)),ISNUMBER(SEARCH("Missing substantive",Q19)),ISNUMBER(SEARCH("Contested substantive",Q19))),"Unresolved, evidence missing",IF(AND(R19="Yes",S19<>"Public-welfare transfer"),"Unresolved, cross-ledger transfer missing",IF(I19<0,"Failed under stress",IF(AND(J19<>"",J19<0),"Conditional pass","Pass")))))))))))))) | Q19: =IF(A19="","",IF(P19="","No evidence ID",IFERROR(IF(VLOOKUP(P19,'Evidence Register'!A:M,11,FALSE)="Missing","Missing substantive evidence",IF(VLOOKUP(P19,'Evidence Register'!A:M,11,FALSE)="Contested","Contested substantive evidence",IF(VLOOKUP(P19,'Evidence Register'!A:M,10,FALSE)="Pinned","Pinned evidence",IF(VLOOKUP(P19,'Evidence Register'!A:M,10,FALSE)="Confidential-reviewable","Reviewable evidence","Pin issue: "&VLOOKUP(P19,'Evidence Register'!A:M,10,FALSE))))),"Missing evidence ID"))) | R19: =IF(A19="","",IF(OR(H19="",H19=0),"",IF(S19="","Missing origin",IF(S19<>"RTO Capacity","Yes","No"))))
I20: =IF(OR(A20="",B20<>"Triggered",F20="",H20=""),"",H20-F20) | J20: =IF(OR(A20="",B20<>"Triggered",G20="",H20=""),"",H20-G20) | K20: =IF(A20="","",IF(B20="Not applicable","Not applicable",IF(B20="Not triggered","Not triggered",IF(B20="Unknown","Unresolved, evidence missing",IF(L20="Confidential-reviewable","Unresolved, confidential but reviewable",IF(L20="Contested","Unresolved, contested",IF(COUNTIFS('Stress Cases'!$K$4:$K$12,"RTO Capacity",'Stress Cases'!$L$4:$L$12,A20,'Stress Cases'!$I$4:$I$12,"Failed under stress")>0,"Failed under linked stress case",IF(COUNTIFS('Stress Cases'!$K$4:$K$12,"RTO Capacity",'Stress Cases'!$L$4:$L$12,A20,'Stress Cases'!$I$4:$I$12,"Unresolved*")>0,"Unresolved, linked stress missing",IF(OR(F20="",H20=""),"Unresolved, evidence missing",IF(AND(H20>0,S20=""),"Unresolved, resource origin missing",IF(OR(ISNUMBER(SEARCH("No evidence",Q20)),ISNUMBER(SEARCH("Missing substantive",Q20)),ISNUMBER(SEARCH("Contested substantive",Q20))),"Unresolved, evidence missing",IF(AND(R20="Yes",S20<>"Public-welfare transfer"),"Unresolved, cross-ledger transfer missing",IF(I20<0,"Failed under stress",IF(AND(J20<>"",J20<0),"Conditional pass","Pass")))))))))))))) | Q20: =IF(A20="","",IF(P20="","No evidence ID",IFERROR(IF(VLOOKUP(P20,'Evidence Register'!A:M,11,FALSE)="Missing","Missing substantive evidence",IF(VLOOKUP(P20,'Evidence Register'!A:M,11,FALSE)="Contested","Contested substantive evidence",IF(VLOOKUP(P20,'Evidence Register'!A:M,10,FALSE)="Pinned","Pinned evidence",IF(VLOOKUP(P20,'Evidence Register'!A:M,10,FALSE)="Confidential-reviewable","Reviewable evidence","Pin issue: "&VLOOKUP(P20,'Evidence Register'!A:M,10,FALSE))))),"Missing evidence ID"))) | R20: =IF(A20="","",IF(OR(H20="",H20=0),"",IF(S20="","Missing origin",IF(S20<>"RTO Capacity","Yes","No"))))
I21: =IF(OR(A21="",B21<>"Triggered",F21="",H21=""),"",H21-F21) | J21: =IF(OR(A21="",B21<>"Triggered",G21="",H21=""),"",H21-G21) | K21: =IF(A21="","",IF(B21="Not applicable","Not applicable",IF(B21="Not triggered","Not triggered",IF(B21="Unknown","Unresolved, evidence missing",IF(L21="Confidential-reviewable","Unresolved, confidential but reviewable",IF(L21="Contested","Unresolved, contested",IF(COUNTIFS('Stress Cases'!$K$4:$K$12,"RTO Capacity",'Stress Cases'!$L$4:$L$12,A21,'Stress Cases'!$I$4:$I$12,"Failed under stress")>0,"Failed under linked stress case",IF(COUNTIFS('Stress Cases'!$K$4:$K$12,"RTO Capacity",'Stress Cases'!$L$4:$L$12,A21,'Stress Cases'!$I$4:$I$12,"Unresolved*")>0,"Unresolved, linked stress missing",IF(OR(F21="",H21=""),"Unresolved, evidence missing",IF(AND(H21>0,S21=""),"Unresolved, resource origin missing",IF(OR(ISNUMBER(SEARCH("No evidence",Q21)),ISNUMBER(SEARCH("Missing substantive",Q21)),ISNUMBER(SEARCH("Contested substantive",Q21))),"Unresolved, evidence missing",IF(AND(R21="Yes",S21<>"Public-welfare transfer"),"Unresolved, cross-ledger transfer missing",IF(I21<0,"Failed under stress",IF(AND(J21<>"",J21<0),"Conditional pass","Pass")))))))))))))) | Q21: =IF(A21="","",IF(P21="","No evidence ID",IFERROR(IF(VLOOKUP(P21,'Evidence Register'!A:M,11,FALSE)="Missing","Missing substantive evidence",IF(VLOOKUP(P21,'Evidence Register'!A:M,11,FALSE)="Contested","Contested substantive evidence",IF(VLOOKUP(P21,'Evidence Register'!A:M,10,FALSE)="Pinned","Pinned evidence",IF(VLOOKUP(P21,'Evidence Register'!A:M,10,FALSE)="Confidential-reviewable","Reviewable evidence","Pin issue: "&VLOOKUP(P21,'Evidence Register'!A:M,10,FALSE))))),"Missing evidence ID"))) | R21: =IF(A21="","",IF(OR(H21="",H21=0),"",IF(S21="","Missing origin",IF(S21<>"RTO Capacity","Yes","No"))))
A22: Total / dashboard line | F22: =IF(COUNTIF(B4:B21,"Triggered")=0,"",SUM(F4:F21)) | G22: =IF(COUNTIF(B4:B21,"Triggered")=0,"",IF(COUNT(G4:G21)=0,"",SUM(G4:G21))) | H22: =IF(COUNTIF(B4:B21,"Triggered")=0,"",SUM(H4:H21)) | I22: =IF(F22="","",H22-F22) | J22: =IF(OR(G22="",H22=""),"",H22-G22) | K22: =IF(COUNTIF(B4:B21,"Triggered")=0,"No entries yet",IF(COUNTIF(K4:K21,"*Failed*")>0,"Failed under stress",IF(COUNTIF(K4:K21,"Unresolved*")>0,"Unresolved",IF(COUNTIF(K4:K21,"Conditional pass")>0,"Conditional pass",IF(I22<0,"Failed under stress",IF(AND(J22<>"",J22<0),"Conditional pass","Pass")))))) | R22: =IF(OR(COUNTIFS(B4:B21,"Triggered",R4:R21,"Yes")>0,COUNTIFS(B4:B21,"Triggered",R4:R21,"Missing origin")>0),"Flag: cross-ledger or origin issue",IF(OR(COUNTIFS(B4:B21,"Triggered",Q4:Q21,"Missing evidence ID")>0,COUNTIFS(B4:B21,"Triggered",Q4:Q21,"Needs pin*")>0,COUNTIFS(B4:B21,"Triggered",Q4:Q21,"No evidence ID")>0),"Flag: evidence pin incomplete",""))

Sheet Local Fiscal
A1: Local Fiscal
A3: Ledger line | B3: Applicability | C3: Causation category | D3: Evidence band | E3: Unit | F3: Base exposure | G3: Stress exposure | H3: Credited resources | I3: Base gap | J3: Stress gap | K3: Status | L3: Evidence status | M3: Residual claimant | N3: Source URL / docket | O3: Page / table / order pin | P3: Evidence ID | Q3: Evidence quality check | R3: Cross-ledger check | S3: Resource ledger of origin | T3: Notes
A4: Tax abatement | B4: Unknown | C4: Local fiscal | E4: NPV | I4: =IF(OR(A4="",B4<>"Triggered",F4="",H4=""),"",H4-F4) | J4: =IF(OR(A4="",B4<>"Triggered",G4="",H4=""),"",H4-G4) | K4: =IF(A4="","",IF(B4="Not applicable","Not applicable",IF(B4="Not triggered","Not triggered",IF(B4="Unknown","Unresolved, evidence missing",IF(L4="Confidential-reviewable","Unresolved, confidential but reviewable",IF(L4="Contested","Unresolved, contested",IF(COUNTIFS('Stress Cases'!$K$4:$K$12,"Local Fiscal",'Stress Cases'!$L$4:$L$12,A4,'Stress Cases'!$I$4:$I$12,"Failed under stress")>0,"Failed under linked stress case",IF(COUNTIFS('Stress Cases'!$K$4:$K$12,"Local Fiscal",'Stress Cases'!$L$4:$L$12,A4,'Stress Cases'!$I$4:$I$12,"Unresolved*")>0,"Unresolved, linked stress missing",IF(OR(F4="",H4=""),"Unresolved, evidence missing",IF(AND(H4>0,S4=""),"Unresolved, resource origin missing",IF(OR(ISNUMBER(SEARCH("No evidence",Q4)),ISNUMBER(SEARCH("Missing substantive",Q4)),ISNUMBER(SEARCH("Contested substantive",Q4))),"Unresolved, evidence missing",IF(AND(R4="Yes",S4<>"Public-welfare transfer"),"Unresolved, cross-ledger transfer missing",IF(I4<0,"Failed under stress",IF(AND(J4<>"",J4<0),"Conditional pass","Pass")))))))))))))) | L4: Missing | Q4: =IF(A4="","",IF(P4="","No evidence ID",IFERROR(IF(VLOOKUP(P4,'Evidence Register'!A:M,11,FALSE)="Missing","Missing substantive evidence",IF(VLOOKUP(P4,'Evidence Register'!A:M,11,FALSE)="Contested","Contested substantive evidence",IF(VLOOKUP(P4,'Evidence Register'!A:M,10,FALSE)="Pinned","Pinned evidence",IF(VLOOKUP(P4,'Evidence Register'!A:M,10,FALSE)="Confidential-reviewable","Reviewable evidence","Pin issue: "&VLOOKUP(P4,'Evidence Register'!A:M,10,FALSE))))),"Missing evidence ID"))) | R4: =IF(A4="","",IF(OR(H4="",H4=0),"",IF(S4="","Missing origin",IF(S4<>"Local Fiscal","Yes","No"))))
A5: PILOT / fees | B5: Unknown | C5: Local fiscal | E5: NPV | I5: =IF(OR(A5="",B5<>"Triggered",F5="",H5=""),"",H5-F5) | J5: =IF(OR(A5="",B5<>"Triggered",G5="",H5=""),"",H5-G5) | K5: =IF(A5="","",IF(B5="Not applicable","Not applicable",IF(B5="Not triggered","Not triggered",IF(B5="Unknown","Unresolved, evidence missing",IF(L5="Confidential-reviewable","Unresolved, confidential but reviewable",IF(L5="Contested","Unresolved, contested",IF(COUNTIFS('Stress Cases'!$K$4:$K$12,"Local Fiscal",'Stress Cases'!$L$4:$L$12,A5,'Stress Cases'!$I$4:$I$12,"Failed under stress")>0,"Failed under linked stress case",IF(COUNTIFS('Stress Cases'!$K$4:$K$12,"Local Fiscal",'Stress Cases'!$L$4:$L$12,A5,'Stress Cases'!$I$4:$I$12,"Unresolved*")>0,"Unresolved, linked stress missing",IF(OR(F5="",H5=""),"Unresolved, evidence missing",IF(AND(H5>0,S5=""),"Unresolved, resource origin missing",IF(OR(ISNUMBER(SEARCH("No evidence",Q5)),ISNUMBER(SEARCH("Missing substantive",Q5)),ISNUMBER(SEARCH("Contested substantive",Q5))),"Unresolved, evidence missing",IF(AND(R5="Yes",S5<>"Public-welfare transfer"),"Unresolved, cross-ledger transfer missing",IF(I5<0,"Failed under stress",IF(AND(J5<>"",J5<0),"Conditional pass","Pass")))))))))))))) | L5: Missing | Q5: =IF(A5="","",IF(P5="","No evidence ID",IFERROR(IF(VLOOKUP(P5,'Evidence Register'!A:M,11,FALSE)="Missing","Missing substantive evidence",IF(VLOOKUP(P5,'Evidence Register'!A:M,11,FALSE)="Contested","Contested substantive evidence",IF(VLOOKUP(P5,'Evidence Register'!A:M,10,FALSE)="Pinned","Pinned evidence",IF(VLOOKUP(P5,'Evidence Register'!A:M,10,FALSE)="Confidential-reviewable","Reviewable evidence","Pin issue: "&VLOOKUP(P5,'Evidence Register'!A:M,10,FALSE))))),"Missing evidence ID"))) | R5: =IF(A5="","",IF(OR(H5="",H5=0),"",IF(S5="","Missing origin",IF(S5<>"Local Fiscal","Yes","No"))))
A6: School district effect | B6: Unknown | C6: Local fiscal | E6: NPV | I6: =IF(OR(A6="",B6<>"Triggered",F6="",H6=""),"",H6-F6) | J6: =IF(OR(A6="",B6<>"Triggered",G6="",H6=""),"",H6-G6) | K6: =IF(A6="","",IF(B6="Not applicable","Not applicable",IF(B6="Not triggered","Not triggered",IF(B6="Unknown","Unresolved, evidence missing",IF(L6="Confidential-reviewable","Unresolved, confidential but reviewable",IF(L6="Contested","Unresolved, contested",IF(COUNTIFS('Stress Cases'!$K$4:$K$12,"Local Fiscal",'Stress Cases'!$L$4:$L$12,A6,'Stress Cases'!$I$4:$I$12,"Failed under stress")>0,"Failed under linked stress case",IF(COUNTIFS('Stress Cases'!$K$4:$K$12,"Local Fiscal",'Stress Cases'!$L$4:$L$12,A6,'Stress Cases'!$I$4:$I$12,"Unresolved*")>0,"Unresolved, linked stress missing",IF(OR(F6="",H6=""),"Unresolved, evidence missing",IF(AND(H6>0,S6=""),"Unresolved, resource origin missing",IF(OR(ISNUMBER(SEARCH("No evidence",Q6)),ISNUMBER(SEARCH("Missing substantive",Q6)),ISNUMBER(SEARCH("Contested substantive",Q6))),"Unresolved, evidence missing",IF(AND(R6="Yes",S6<>"Public-welfare transfer"),"Unresolved, cross-ledger transfer missing",IF(I6<0,"Failed under stress",IF(AND(J6<>"",J6<0),"Conditional pass","Pass")))))))))))))) | L6: Missing | Q6: =IF(A6="","",IF(P6="","No evidence ID",IFERROR(IF(VLOOKUP(P6,'Evidence Register'!A:M,11,FALSE)="Missing","Missing substantive evidence",IF(VLOOKUP(P6,'Evidence Register'!A:M,11,FALSE)="Contested","Contested substantive evidence",IF(VLOOKUP(P6,'Evidence Register'!A:M,10,FALSE)="Pinned","Pinned evidence",IF(VLOOKUP(P6,'Evidence Register'!A:M,10,FALSE)="Confidential-reviewable","Reviewable evidence","Pin issue: "&VLOOKUP(P6,'Evidence Register'!A:M,10,FALSE))))),"Missing evidence ID"))) | R6: =IF(A6="","",IF(OR(H6="",H6=0),"",IF(S6="","Missing origin",IF(S6<>"Local Fiscal","Yes","No"))))
A7: Roads / fire / public safety | B7: Unknown | C7: Local fiscal | E7: NPV | I7: =IF(OR(A7="",B7<>"Triggered",F7="",H7=""),"",H7-F7) | J7: =IF(OR(A7="",B7<>"Triggered",G7="",H7=""),"",H7-G7) | K7: =IF(A7="","",IF(B7="Not applicable","Not applicable",IF(B7="Not triggered","Not triggered",IF(B7="Unknown","Unresolved, evidence missing",IF(L7="Confidential-reviewable","Unresolved, confidential but reviewable",IF(L7="Contested","Unresolved, contested",IF(COUNTIFS('Stress Cases'!$K$4:$K$12,"Local Fiscal",'Stress Cases'!$L$4:$L$12,A7,'Stress Cases'!$I$4:$I$12,"Failed under stress")>0,"Failed under linked stress case",IF(COUNTIFS('Stress Cases'!$K$4:$K$12,"Local Fiscal",'Stress Cases'!$L$4:$L$12,A7,'Stress Cases'!$I$4:$I$12,"Unresolved*")>0,"Unresolved, linked stress missing",IF(OR(F7="",H7=""),"Unresolved, evidence missing",IF(AND(H7>0,S7=""),"Unresolved, resource origin missing",IF(OR(ISNUMBER(SEARCH("No evidence",Q7)),ISNUMBER(SEARCH("Missing substantive",Q7)),ISNUMBER(SEARCH("Contested substantive",Q7))),"Unresolved, evidence missing",IF(AND(R7="Yes",S7<>"Public-welfare transfer"),"Unresolved, cross-ledger transfer missing",IF(I7<0,"Failed under stress",IF(AND(J7<>"",J7<0),"Conditional pass","Pass")))))))))))))) | L7: Missing | Q7: =IF(A7="","",IF(P7="","No evidence ID",IFERROR(IF(VLOOKUP(P7,'Evidence Register'!A:M,11,FALSE)="Missing","Missing substantive evidence",IF(VLOOKUP(P7,'Evidence Register'!A:M,11,FALSE)="Contested","Contested substantive evidence",IF(VLOOKUP(P7,'Evidence Register'!A:M,10,FALSE)="Pinned","Pinned evidence",IF(VLOOKUP(P7,'Evidence Register'!A:M,10,FALSE)="Confidential-reviewable","Reviewable evidence","Pin issue: "&VLOOKUP(P7,'Evidence Register'!A:M,10,FALSE))))),"Missing evidence ID"))) | R7: =IF(A7="","",IF(OR(H7="",H7=0),"",IF(S7="","Missing origin",IF(S7<>"Local Fiscal","Yes","No"))))
A8: Community benefit agreement | B8: Unknown | C8: Public welfare | E8: NPV / non-monetized | I8: =IF(OR(A8="",B8<>"Triggered",F8="",H8=""),"",H8-F8) | J8: =IF(OR(A8="",B8<>"Triggered",G8="",H8=""),"",H8-G8) | K8: =IF(A8="","",IF(B8="Not applicable","Not applicable",IF(B8="Not triggered","Not triggered",IF(B8="Unknown","Unresolved, evidence missing",IF(L8="Confidential-reviewable","Unresolved, confidential but reviewable",IF(L8="Contested","Unresolved, contested",IF(COUNTIFS('Stress Cases'!$K$4:$K$12,"Local Fiscal",'Stress Cases'!$L$4:$L$12,A8,'Stress Cases'!$I$4:$I$12,"Failed under stress")>0,"Failed under linked stress case",IF(COUNTIFS('Stress Cases'!$K$4:$K$12,"Local Fiscal",'Stress Cases'!$L$4:$L$12,A8,'Stress Cases'!$I$4:$I$12,"Unresolved*")>0,"Unresolved, linked stress missing",IF(OR(F8="",H8=""),"Unresolved, evidence missing",IF(AND(H8>0,S8=""),"Unresolved, resource origin missing",IF(OR(ISNUMBER(SEARCH("No evidence",Q8)),ISNUMBER(SEARCH("Missing substantive",Q8)),ISNUMBER(SEARCH("Contested substantive",Q8))),"Unresolved, evidence missing",IF(AND(R8="Yes",S8<>"Public-welfare transfer"),"Unresolved, cross-ledger transfer missing",IF(I8<0,"Failed under stress",IF(AND(J8<>"",J8<0),"Conditional pass","Pass")))))))))))))) | L8: Missing | Q8: =IF(A8="","",IF(P8="","No evidence ID",IFERROR(IF(VLOOKUP(P8,'Evidence Register'!A:M,11,FALSE)="Missing","Missing substantive evidence",IF(VLOOKUP(P8,'Evidence Register'!A:M,11,FALSE)="Contested","Contested substantive evidence",IF(VLOOKUP(P8,'Evidence Register'!A:M,10,FALSE)="Pinned","Pinned evidence",IF(VLOOKUP(P8,'Evidence Register'!A:M,10,FALSE)="Confidential-reviewable","Reviewable evidence","Pin issue: "&VLOOKUP(P8,'Evidence Register'!A:M,10,FALSE))))),"Missing evidence ID"))) | R8: =IF(A8="","",IF(OR(H8="",H8=0),"",IF(S8="","Missing origin",IF(S8<>"Local Fiscal","Yes","No"))))
I9: =IF(OR(A9="",B9<>"Triggered",F9="",H9=""),"",H9-F9) | J9: =IF(OR(A9="",B9<>"Triggered",G9="",H9=""),"",H9-G9) | K9: =IF(A9="","",IF(B9="Not applicable","Not applicable",IF(B9="Not triggered","Not triggered",IF(B9="Unknown","Unresolved, evidence missing",IF(L9="Confidential-reviewable","Unresolved, confidential but reviewable",IF(L9="Contested","Unresolved, contested",IF(COUNTIFS('Stress Cases'!$K$4:$K$12,"Local Fiscal",'Stress Cases'!$L$4:$L$12,A9,'Stress Cases'!$I$4:$I$12,"Failed under stress")>0,"Failed under linked stress case",IF(COUNTIFS('Stress Cases'!$K$4:$K$12,"Local Fiscal",'Stress Cases'!$L$4:$L$12,A9,'Stress Cases'!$I$4:$I$12,"Unresolved*")>0,"Unresolved, linked stress missing",IF(OR(F9="",H9=""),"Unresolved, evidence missing",IF(AND(H9>0,S9=""),"Unresolved, resource origin missing",IF(OR(ISNUMBER(SEARCH("No evidence",Q9)),ISNUMBER(SEARCH("Missing substantive",Q9)),ISNUMBER(SEARCH("Contested substantive",Q9))),"Unresolved, evidence missing",IF(AND(R9="Yes",S9<>"Public-welfare transfer"),"Unresolved, cross-ledger transfer missing",IF(I9<0,"Failed under stress",IF(AND(J9<>"",J9<0),"Conditional pass","Pass")))))))))))))) | Q9: =IF(A9="","",IF(P9="","No evidence ID",IFERROR(IF(VLOOKUP(P9,'Evidence Register'!A:M,11,FALSE)="Missing","Missing substantive evidence",IF(VLOOKUP(P9,'Evidence Register'!A:M,11,FALSE)="Contested","Contested substantive evidence",IF(VLOOKUP(P9,'Evidence Register'!A:M,10,FALSE)="Pinned","Pinned evidence",IF(VLOOKUP(P9,'Evidence Register'!A:M,10,FALSE)="Confidential-reviewable","Reviewable evidence","Pin issue: "&VLOOKUP(P9,'Evidence Register'!A:M,10,FALSE))))),"Missing evidence ID"))) | R9: =IF(A9="","",IF(OR(H9="",H9=0),"",IF(S9="","Missing origin",IF(S9<>"Local Fiscal","Yes","No"))))
I10: =IF(OR(A10="",B10<>"Triggered",F10="",H10=""),"",H10-F10) | J10: =IF(OR(A10="",B10<>"Triggered",G10="",H10=""),"",H10-G10) | K10: =IF(A10="","",IF(B10="Not applicable","Not applicable",IF(B10="Not triggered","Not triggered",IF(B10="Unknown","Unresolved, evidence missing",IF(L10="Confidential-reviewable","Unresolved, confidential but reviewable",IF(L10="Contested","Unresolved, contested",IF(COUNTIFS('Stress Cases'!$K$4:$K$12,"Local Fiscal",'Stress Cases'!$L$4:$L$12,A10,'Stress Cases'!$I$4:$I$12,"Failed under stress")>0,"Failed under linked stress case",IF(COUNTIFS('Stress Cases'!$K$4:$K$12,"Local Fiscal",'Stress Cases'!$L$4:$L$12,A10,'Stress Cases'!$I$4:$I$12,"Unresolved*")>0,"Unresolved, linked stress missing",IF(OR(F10="",H10=""),"Unresolved, evidence missing",IF(AND(H10>0,S10=""),"Unresolved, resource origin missing",IF(OR(ISNUMBER(SEARCH("No evidence",Q10)),ISNUMBER(SEARCH("Missing substantive",Q10)),ISNUMBER(SEARCH("Contested substantive",Q10))),"Unresolved, evidence missing",IF(AND(R10="Yes",S10<>"Public-welfare transfer"),"Unresolved, cross-ledger transfer missing",IF(I10<0,"Failed under stress",IF(AND(J10<>"",J10<0),"Conditional pass","Pass")))))))))))))) | Q10: =IF(A10="","",IF(P10="","No evidence ID",IFERROR(IF(VLOOKUP(P10,'Evidence Register'!A:M,11,FALSE)="Missing","Missing substantive evidence",IF(VLOOKUP(P10,'Evidence Register'!A:M,11,FALSE)="Contested","Contested substantive evidence",IF(VLOOKUP(P10,'Evidence Register'!A:M,10,FALSE)="Pinned","Pinned evidence",IF(VLOOKUP(P10,'Evidence Register'!A:M,10,FALSE)="Confidential-reviewable","Reviewable evidence","Pin issue: "&VLOOKUP(P10,'Evidence Register'!A:M,10,FALSE))))),"Missing evidence ID"))) | R10: =IF(A10="","",IF(OR(H10="",H10=0),"",IF(S10="","Missing origin",IF(S10<>"Local Fiscal","Yes","No"))))
I11: =IF(OR(A11="",B11<>"Triggered",F11="",H11=""),"",H11-F11) | J11: =IF(OR(A11="",B11<>"Triggered",G11="",H11=""),"",H11-G11) | K11: =IF(A11="","",IF(B11="Not applicable","Not applicable",IF(B11="Not triggered","Not triggered",IF(B11="Unknown","Unresolved, evidence missing",IF(L11="Confidential-reviewable","Unresolved, confidential but reviewable",IF(L11="Contested","Unresolved, contested",IF(COUNTIFS('Stress Cases'!$K$4:$K$12,"Local Fiscal",'Stress Cases'!$L$4:$L$12,A11,'Stress Cases'!$I$4:$I$12,"Failed under stress")>0,"Failed under linked stress case",IF(COUNTIFS('Stress Cases'!$K$4:$K$12,"Local Fiscal",'Stress Cases'!$L$4:$L$12,A11,'Stress Cases'!$I$4:$I$12,"Unresolved*")>0,"Unresolved, linked stress missing",IF(OR(F11="",H11=""),"Unresolved, evidence missing",IF(AND(H11>0,S11=""),"Unresolved, resource origin missing",IF(OR(ISNUMBER(SEARCH("No evidence",Q11)),ISNUMBER(SEARCH("Missing substantive",Q11)),ISNUMBER(SEARCH("Contested substantive",Q11))),"Unresolved, evidence missing",IF(AND(R11="Yes",S11<>"Public-welfare transfer"),"Unresolved, cross-ledger transfer missing",IF(I11<0,"Failed under stress",IF(AND(J11<>"",J11<0),"Conditional pass","Pass")))))))))))))) | Q11: =IF(A11="","",IF(P11="","No evidence ID",IFERROR(IF(VLOOKUP(P11,'Evidence Register'!A:M,11,FALSE)="Missing","Missing substantive evidence",IF(VLOOKUP(P11,'Evidence Register'!A:M,11,FALSE)="Contested","Contested substantive evidence",IF(VLOOKUP(P11,'Evidence Register'!A:M,10,FALSE)="Pinned","Pinned evidence",IF(VLOOKUP(P11,'Evidence Register'!A:M,10,FALSE)="Confidential-reviewable","Reviewable evidence","Pin issue: "&VLOOKUP(P11,'Evidence Register'!A:M,10,FALSE))))),"Missing evidence ID"))) | R11: =IF(A11="","",IF(OR(H11="",H11=0),"",IF(S11="","Missing origin",IF(S11<>"Local Fiscal","Yes","No"))))
I12: =IF(OR(A12="",B12<>"Triggered",F12="",H12=""),"",H12-F12) | J12: =IF(OR(A12="",B12<>"Triggered",G12="",H12=""),"",H12-G12) | K12: =IF(A12="","",IF(B12="Not applicable","Not applicable",IF(B12="Not triggered","Not triggered",IF(B12="Unknown","Unresolved, evidence missing",IF(L12="Confidential-reviewable","Unresolved, confidential but reviewable",IF(L12="Contested","Unresolved, contested",IF(COUNTIFS('Stress Cases'!$K$4:$K$12,"Local Fiscal",'Stress Cases'!$L$4:$L$12,A12,'Stress Cases'!$I$4:$I$12,"Failed under stress")>0,"Failed under linked stress case",IF(COUNTIFS('Stress Cases'!$K$4:$K$12,"Local Fiscal",'Stress Cases'!$L$4:$L$12,A12,'Stress Cases'!$I$4:$I$12,"Unresolved*")>0,"Unresolved, linked stress missing",IF(OR(F12="",H12=""),"Unresolved, evidence missing",IF(AND(H12>0,S12=""),"Unresolved, resource origin missing",IF(OR(ISNUMBER(SEARCH("No evidence",Q12)),ISNUMBER(SEARCH("Missing substantive",Q12)),ISNUMBER(SEARCH("Contested substantive",Q12))),"Unresolved, evidence missing",IF(AND(R12="Yes",S12<>"Public-welfare transfer"),"Unresolved, cross-ledger transfer missing",IF(I12<0,"Failed under stress",IF(AND(J12<>"",J12<0),"Conditional pass","Pass")))))))))))))) | Q12: =IF(A12="","",IF(P12="","No evidence ID",IFERROR(IF(VLOOKUP(P12,'Evidence Register'!A:M,11,FALSE)="Missing","Missing substantive evidence",IF(VLOOKUP(P12,'Evidence Register'!A:M,11,FALSE)="Contested","Contested substantive evidence",IF(VLOOKUP(P12,'Evidence Register'!A:M,10,FALSE)="Pinned","Pinned evidence",IF(VLOOKUP(P12,'Evidence Register'!A:M,10,FALSE)="Confidential-reviewable","Reviewable evidence","Pin issue: "&VLOOKUP(P12,'Evidence Register'!A:M,10,FALSE))))),"Missing evidence ID"))) | R12: =IF(A12="","",IF(OR(H12="",H12=0),"",IF(S12="","Missing origin",IF(S12<>"Local Fiscal","Yes","No"))))
I13: =IF(OR(A13="",B13<>"Triggered",F13="",H13=""),"",H13-F13) | J13: =IF(OR(A13="",B13<>"Triggered",G13="",H13=""),"",H13-G13) | K13: =IF(A13="","",IF(B13="Not applicable","Not applicable",IF(B13="Not triggered","Not triggered",IF(B13="Unknown","Unresolved, evidence missing",IF(L13="Confidential-reviewable","Unresolved, confidential but reviewable",IF(L13="Contested","Unresolved, contested",IF(COUNTIFS('Stress Cases'!$K$4:$K$12,"Local Fiscal",'Stress Cases'!$L$4:$L$12,A13,'Stress Cases'!$I$4:$I$12,"Failed under stress")>0,"Failed under linked stress case",IF(COUNTIFS('Stress Cases'!$K$4:$K$12,"Local Fiscal",'Stress Cases'!$L$4:$L$12,A13,'Stress Cases'!$I$4:$I$12,"Unresolved*")>0,"Unresolved, linked stress missing",IF(OR(F13="",H13=""),"Unresolved, evidence missing",IF(AND(H13>0,S13=""),"Unresolved, resource origin missing",IF(OR(ISNUMBER(SEARCH("No evidence",Q13)),ISNUMBER(SEARCH("Missing substantive",Q13)),ISNUMBER(SEARCH("Contested substantive",Q13))),"Unresolved, evidence missing",IF(AND(R13="Yes",S13<>"Public-welfare transfer"),"Unresolved, cross-ledger transfer missing",IF(I13<0,"Failed under stress",IF(AND(J13<>"",J13<0),"Conditional pass","Pass")))))))))))))) | Q13: =IF(A13="","",IF(P13="","No evidence ID",IFERROR(IF(VLOOKUP(P13,'Evidence Register'!A:M,11,FALSE)="Missing","Missing substantive evidence",IF(VLOOKUP(P13,'Evidence Register'!A:M,11,FALSE)="Contested","Contested substantive evidence",IF(VLOOKUP(P13,'Evidence Register'!A:M,10,FALSE)="Pinned","Pinned evidence",IF(VLOOKUP(P13,'Evidence Register'!A:M,10,FALSE)="Confidential-reviewable","Reviewable evidence","Pin issue: "&VLOOKUP(P13,'Evidence Register'!A:M,10,FALSE))))),"Missing evidence ID"))) | R13: =IF(A13="","",IF(OR(H13="",H13=0),"",IF(S13="","Missing origin",IF(S13<>"Local Fiscal","Yes","No"))))
I14: =IF(OR(A14="",B14<>"Triggered",F14="",H14=""),"",H14-F14) | J14: =IF(OR(A14="",B14<>"Triggered",G14="",H14=""),"",H14-G14) | K14: =IF(A14="","",IF(B14="Not applicable","Not applicable",IF(B14="Not triggered","Not triggered",IF(B14="Unknown","Unresolved, evidence missing",IF(L14="Confidential-reviewable","Unresolved, confidential but reviewable",IF(L14="Contested","Unresolved, contested",IF(COUNTIFS('Stress Cases'!$K$4:$K$12,"Local Fiscal",'Stress Cases'!$L$4:$L$12,A14,'Stress Cases'!$I$4:$I$12,"Failed under stress")>0,"Failed under linked stress case",IF(COUNTIFS('Stress Cases'!$K$4:$K$12,"Local Fiscal",'Stress Cases'!$L$4:$L$12,A14,'Stress Cases'!$I$4:$I$12,"Unresolved*")>0,"Unresolved, linked stress missing",IF(OR(F14="",H14=""),"Unresolved, evidence missing",IF(AND(H14>0,S14=""),"Unresolved, resource origin missing",IF(OR(ISNUMBER(SEARCH("No evidence",Q14)),ISNUMBER(SEARCH("Missing substantive",Q14)),ISNUMBER(SEARCH("Contested substantive",Q14))),"Unresolved, evidence missing",IF(AND(R14="Yes",S14<>"Public-welfare transfer"),"Unresolved, cross-ledger transfer missing",IF(I14<0,"Failed under stress",IF(AND(J14<>"",J14<0),"Conditional pass","Pass")))))))))))))) | Q14: =IF(A14="","",IF(P14="","No evidence ID",IFERROR(IF(VLOOKUP(P14,'Evidence Register'!A:M,11,FALSE)="Missing","Missing substantive evidence",IF(VLOOKUP(P14,'Evidence Register'!A:M,11,FALSE)="Contested","Contested substantive evidence",IF(VLOOKUP(P14,'Evidence Register'!A:M,10,FALSE)="Pinned","Pinned evidence",IF(VLOOKUP(P14,'Evidence Register'!A:M,10,FALSE)="Confidential-reviewable","Reviewable evidence","Pin issue: "&VLOOKUP(P14,'Evidence Register'!A:M,10,FALSE))))),"Missing evidence ID"))) | R14: =IF(A14="","",IF(OR(H14="",H14=0),"",IF(S14="","Missing origin",IF(S14<>"Local Fiscal","Yes","No"))))
I15: =IF(OR(A15="",B15<>"Triggered",F15="",H15=""),"",H15-F15) | J15: =IF(OR(A15="",B15<>"Triggered",G15="",H15=""),"",H15-G15) | K15: =IF(A15="","",IF(B15="Not applicable","Not applicable",IF(B15="Not triggered","Not triggered",IF(B15="Unknown","Unresolved, evidence missing",IF(L15="Confidential-reviewable","Unresolved, confidential but reviewable",IF(L15="Contested","Unresolved, contested",IF(COUNTIFS('Stress Cases'!$K$4:$K$12,"Local Fiscal",'Stress Cases'!$L$4:$L$12,A15,'Stress Cases'!$I$4:$I$12,"Failed under stress")>0,"Failed under linked stress case",IF(COUNTIFS('Stress Cases'!$K$4:$K$12,"Local Fiscal",'Stress Cases'!$L$4:$L$12,A15,'Stress Cases'!$I$4:$I$12,"Unresolved*")>0,"Unresolved, linked stress missing",IF(OR(F15="",H15=""),"Unresolved, evidence missing",IF(AND(H15>0,S15=""),"Unresolved, resource origin missing",IF(OR(ISNUMBER(SEARCH("No evidence",Q15)),ISNUMBER(SEARCH("Missing substantive",Q15)),ISNUMBER(SEARCH("Contested substantive",Q15))),"Unresolved, evidence missing",IF(AND(R15="Yes",S15<>"Public-welfare transfer"),"Unresolved, cross-ledger transfer missing",IF(I15<0,"Failed under stress",IF(AND(J15<>"",J15<0),"Conditional pass","Pass")))))))))))))) | Q15: =IF(A15="","",IF(P15="","No evidence ID",IFERROR(IF(VLOOKUP(P15,'Evidence Register'!A:M,11,FALSE)="Missing","Missing substantive evidence",IF(VLOOKUP(P15,'Evidence Register'!A:M,11,FALSE)="Contested","Contested substantive evidence",IF(VLOOKUP(P15,'Evidence Register'!A:M,10,FALSE)="Pinned","Pinned evidence",IF(VLOOKUP(P15,'Evidence Register'!A:M,10,FALSE)="Confidential-reviewable","Reviewable evidence","Pin issue: "&VLOOKUP(P15,'Evidence Register'!A:M,10,FALSE))))),"Missing evidence ID"))) | R15: =IF(A15="","",IF(OR(H15="",H15=0),"",IF(S15="","Missing origin",IF(S15<>"Local Fiscal","Yes","No"))))
I16: =IF(OR(A16="",B16<>"Triggered",F16="",H16=""),"",H16-F16) | J16: =IF(OR(A16="",B16<>"Triggered",G16="",H16=""),"",H16-G16) | K16: =IF(A16="","",IF(B16="Not applicable","Not applicable",IF(B16="Not triggered","Not triggered",IF(B16="Unknown","Unresolved, evidence missing",IF(L16="Confidential-reviewable","Unresolved, confidential but reviewable",IF(L16="Contested","Unresolved, contested",IF(COUNTIFS('Stress Cases'!$K$4:$K$12,"Local Fiscal",'Stress Cases'!$L$4:$L$12,A16,'Stress Cases'!$I$4:$I$12,"Failed under stress")>0,"Failed under linked stress case",IF(COUNTIFS('Stress Cases'!$K$4:$K$12,"Local Fiscal",'Stress Cases'!$L$4:$L$12,A16,'Stress Cases'!$I$4:$I$12,"Unresolved*")>0,"Unresolved, linked stress missing",IF(OR(F16="",H16=""),"Unresolved, evidence missing",IF(AND(H16>0,S16=""),"Unresolved, resource origin missing",IF(OR(ISNUMBER(SEARCH("No evidence",Q16)),ISNUMBER(SEARCH("Missing substantive",Q16)),ISNUMBER(SEARCH("Contested substantive",Q16))),"Unresolved, evidence missing",IF(AND(R16="Yes",S16<>"Public-welfare transfer"),"Unresolved, cross-ledger transfer missing",IF(I16<0,"Failed under stress",IF(AND(J16<>"",J16<0),"Conditional pass","Pass")))))))))))))) | Q16: =IF(A16="","",IF(P16="","No evidence ID",IFERROR(IF(VLOOKUP(P16,'Evidence Register'!A:M,11,FALSE)="Missing","Missing substantive evidence",IF(VLOOKUP(P16,'Evidence Register'!A:M,11,FALSE)="Contested","Contested substantive evidence",IF(VLOOKUP(P16,'Evidence Register'!A:M,10,FALSE)="Pinned","Pinned evidence",IF(VLOOKUP(P16,'Evidence Register'!A:M,10,FALSE)="Confidential-reviewable","Reviewable evidence","Pin issue: "&VLOOKUP(P16,'Evidence Register'!A:M,10,FALSE))))),"Missing evidence ID"))) | R16: =IF(A16="","",IF(OR(H16="",H16=0),"",IF(S16="","Missing origin",IF(S16<>"Local Fiscal","Yes","No"))))
I17: =IF(OR(A17="",B17<>"Triggered",F17="",H17=""),"",H17-F17) | J17: =IF(OR(A17="",B17<>"Triggered",G17="",H17=""),"",H17-G17) | K17: =IF(A17="","",IF(B17="Not applicable","Not applicable",IF(B17="Not triggered","Not triggered",IF(B17="Unknown","Unresolved, evidence missing",IF(L17="Confidential-reviewable","Unresolved, confidential but reviewable",IF(L17="Contested","Unresolved, contested",IF(COUNTIFS('Stress Cases'!$K$4:$K$12,"Local Fiscal",'Stress Cases'!$L$4:$L$12,A17,'Stress Cases'!$I$4:$I$12,"Failed under stress")>0,"Failed under linked stress case",IF(COUNTIFS('Stress Cases'!$K$4:$K$12,"Local Fiscal",'Stress Cases'!$L$4:$L$12,A17,'Stress Cases'!$I$4:$I$12,"Unresolved*")>0,"Unresolved, linked stress missing",IF(OR(F17="",H17=""),"Unresolved, evidence missing",IF(AND(H17>0,S17=""),"Unresolved, resource origin missing",IF(OR(ISNUMBER(SEARCH("No evidence",Q17)),ISNUMBER(SEARCH("Missing substantive",Q17)),ISNUMBER(SEARCH("Contested substantive",Q17))),"Unresolved, evidence missing",IF(AND(R17="Yes",S17<>"Public-welfare transfer"),"Unresolved, cross-ledger transfer missing",IF(I17<0,"Failed under stress",IF(AND(J17<>"",J17<0),"Conditional pass","Pass")))))))))))))) | Q17: =IF(A17="","",IF(P17="","No evidence ID",IFERROR(IF(VLOOKUP(P17,'Evidence Register'!A:M,11,FALSE)="Missing","Missing substantive evidence",IF(VLOOKUP(P17,'Evidence Register'!A:M,11,FALSE)="Contested","Contested substantive evidence",IF(VLOOKUP(P17,'Evidence Register'!A:M,10,FALSE)="Pinned","Pinned evidence",IF(VLOOKUP(P17,'Evidence Register'!A:M,10,FALSE)="Confidential-reviewable","Reviewable evidence","Pin issue: "&VLOOKUP(P17,'Evidence Register'!A:M,10,FALSE))))),"Missing evidence ID"))) | R17: =IF(A17="","",IF(OR(H17="",H17=0),"",IF(S17="","Missing origin",IF(S17<>"Local Fiscal","Yes","No"))))
I18: =IF(OR(A18="",B18<>"Triggered",F18="",H18=""),"",H18-F18) | J18: =IF(OR(A18="",B18<>"Triggered",G18="",H18=""),"",H18-G18) | K18: =IF(A18="","",IF(B18="Not applicable","Not applicable",IF(B18="Not triggered","Not triggered",IF(B18="Unknown","Unresolved, evidence missing",IF(L18="Confidential-reviewable","Unresolved, confidential but reviewable",IF(L18="Contested","Unresolved, contested",IF(COUNTIFS('Stress Cases'!$K$4:$K$12,"Local Fiscal",'Stress Cases'!$L$4:$L$12,A18,'Stress Cases'!$I$4:$I$12,"Failed under stress")>0,"Failed under linked stress case",IF(COUNTIFS('Stress Cases'!$K$4:$K$12,"Local Fiscal",'Stress Cases'!$L$4:$L$12,A18,'Stress Cases'!$I$4:$I$12,"Unresolved*")>0,"Unresolved, linked stress missing",IF(OR(F18="",H18=""),"Unresolved, evidence missing",IF(AND(H18>0,S18=""),"Unresolved, resource origin missing",IF(OR(ISNUMBER(SEARCH("No evidence",Q18)),ISNUMBER(SEARCH("Missing substantive",Q18)),ISNUMBER(SEARCH("Contested substantive",Q18))),"Unresolved, evidence missing",IF(AND(R18="Yes",S18<>"Public-welfare transfer"),"Unresolved, cross-ledger transfer missing",IF(I18<0,"Failed under stress",IF(AND(J18<>"",J18<0),"Conditional pass","Pass")))))))))))))) | Q18: =IF(A18="","",IF(P18="","No evidence ID",IFERROR(IF(VLOOKUP(P18,'Evidence Register'!A:M,11,FALSE)="Missing","Missing substantive evidence",IF(VLOOKUP(P18,'Evidence Register'!A:M,11,FALSE)="Contested","Contested substantive evidence",IF(VLOOKUP(P18,'Evidence Register'!A:M,10,FALSE)="Pinned","Pinned evidence",IF(VLOOKUP(P18,'Evidence Register'!A:M,10,FALSE)="Confidential-reviewable","Reviewable evidence","Pin issue: "&VLOOKUP(P18,'Evidence Register'!A:M,10,FALSE))))),"Missing evidence ID"))) | R18: =IF(A18="","",IF(OR(H18="",H18=0),"",IF(S18="","Missing origin",IF(S18<>"Local Fiscal","Yes","No"))))
I19: =IF(OR(A19="",B19<>"Triggered",F19="",H19=""),"",H19-F19) | J19: =IF(OR(A19="",B19<>"Triggered",G19="",H19=""),"",H19-G19) | K19: =IF(A19="","",IF(B19="Not applicable","Not applicable",IF(B19="Not triggered","Not triggered",IF(B19="Unknown","Unresolved, evidence missing",IF(L19="Confidential-reviewable","Unresolved, confidential but reviewable",IF(L19="Contested","Unresolved, contested",IF(COUNTIFS('Stress Cases'!$K$4:$K$12,"Local Fiscal",'Stress Cases'!$L$4:$L$12,A19,'Stress Cases'!$I$4:$I$12,"Failed under stress")>0,"Failed under linked stress case",IF(COUNTIFS('Stress Cases'!$K$4:$K$12,"Local Fiscal",'Stress Cases'!$L$4:$L$12,A19,'Stress Cases'!$I$4:$I$12,"Unresolved*")>0,"Unresolved, linked stress missing",IF(OR(F19="",H19=""),"Unresolved, evidence missing",IF(AND(H19>0,S19=""),"Unresolved, resource origin missing",IF(OR(ISNUMBER(SEARCH("No evidence",Q19)),ISNUMBER(SEARCH("Missing substantive",Q19)),ISNUMBER(SEARCH("Contested substantive",Q19))),"Unresolved, evidence missing",IF(AND(R19="Yes",S19<>"Public-welfare transfer"),"Unresolved, cross-ledger transfer missing",IF(I19<0,"Failed under stress",IF(AND(J19<>"",J19<0),"Conditional pass","Pass")))))))))))))) | Q19: =IF(A19="","",IF(P19="","No evidence ID",IFERROR(IF(VLOOKUP(P19,'Evidence Register'!A:M,11,FALSE)="Missing","Missing substantive evidence",IF(VLOOKUP(P19,'Evidence Register'!A:M,11,FALSE)="Contested","Contested substantive evidence",IF(VLOOKUP(P19,'Evidence Register'!A:M,10,FALSE)="Pinned","Pinned evidence",IF(VLOOKUP(P19,'Evidence Register'!A:M,10,FALSE)="Confidential-reviewable","Reviewable evidence","Pin issue: "&VLOOKUP(P19,'Evidence Register'!A:M,10,FALSE))))),"Missing evidence ID"))) | R19: =IF(A19="","",IF(OR(H19="",H19=0),"",IF(S19="","Missing origin",IF(S19<>"Local Fiscal","Yes","No"))))
I20: =IF(OR(A20="",B20<>"Triggered",F20="",H20=""),"",H20-F20) | J20: =IF(OR(A20="",B20<>"Triggered",G20="",H20=""),"",H20-G20) | K20: =IF(A20="","",IF(B20="Not applicable","Not applicable",IF(B20="Not triggered","Not triggered",IF(B20="Unknown","Unresolved, evidence missing",IF(L20="Confidential-reviewable","Unresolved, confidential but reviewable",IF(L20="Contested","Unresolved, contested",IF(COUNTIFS('Stress Cases'!$K$4:$K$12,"Local Fiscal",'Stress Cases'!$L$4:$L$12,A20,'Stress Cases'!$I$4:$I$12,"Failed under stress")>0,"Failed under linked stress case",IF(COUNTIFS('Stress Cases'!$K$4:$K$12,"Local Fiscal",'Stress Cases'!$L$4:$L$12,A20,'Stress Cases'!$I$4:$I$12,"Unresolved*")>0,"Unresolved, linked stress missing",IF(OR(F20="",H20=""),"Unresolved, evidence missing",IF(AND(H20>0,S20=""),"Unresolved, resource origin missing",IF(OR(ISNUMBER(SEARCH("No evidence",Q20)),ISNUMBER(SEARCH("Missing substantive",Q20)),ISNUMBER(SEARCH("Contested substantive",Q20))),"Unresolved, evidence missing",IF(AND(R20="Yes",S20<>"Public-welfare transfer"),"Unresolved, cross-ledger transfer missing",IF(I20<0,"Failed under stress",IF(AND(J20<>"",J20<0),"Conditional pass","Pass")))))))))))))) | Q20: =IF(A20="","",IF(P20="","No evidence ID",IFERROR(IF(VLOOKUP(P20,'Evidence Register'!A:M,11,FALSE)="Missing","Missing substantive evidence",IF(VLOOKUP(P20,'Evidence Register'!A:M,11,FALSE)="Contested","Contested substantive evidence",IF(VLOOKUP(P20,'Evidence Register'!A:M,10,FALSE)="Pinned","Pinned evidence",IF(VLOOKUP(P20,'Evidence Register'!A:M,10,FALSE)="Confidential-reviewable","Reviewable evidence","Pin issue: "&VLOOKUP(P20,'Evidence Register'!A:M,10,FALSE))))),"Missing evidence ID"))) | R20: =IF(A20="","",IF(OR(H20="",H20=0),"",IF(S20="","Missing origin",IF(S20<>"Local Fiscal","Yes","No"))))
I21: =IF(OR(A21="",B21<>"Triggered",F21="",H21=""),"",H21-F21) | J21: =IF(OR(A21="",B21<>"Triggered",G21="",H21=""),"",H21-G21) | K21: =IF(A21="","",IF(B21="Not applicable","Not applicable",IF(B21="Not triggered","Not triggered",IF(B21="Unknown","Unresolved, evidence missing",IF(L21="Confidential-reviewable","Unresolved, confidential but reviewable",IF(L21="Contested","Unresolved, contested",IF(COUNTIFS('Stress Cases'!$K$4:$K$12,"Local Fiscal",'Stress Cases'!$L$4:$L$12,A21,'Stress Cases'!$I$4:$I$12,"Failed under stress")>0,"Failed under linked stress case",IF(COUNTIFS('Stress Cases'!$K$4:$K$12,"Local Fiscal",'Stress Cases'!$L$4:$L$12,A21,'Stress Cases'!$I$4:$I$12,"Unresolved*")>0,"Unresolved, linked stress missing",IF(OR(F21="",H21=""),"Unresolved, evidence missing",IF(AND(H21>0,S21=""),"Unresolved, resource origin missing",IF(OR(ISNUMBER(SEARCH("No evidence",Q21)),ISNUMBER(SEARCH("Missing substantive",Q21)),ISNUMBER(SEARCH("Contested substantive",Q21))),"Unresolved, evidence missing",IF(AND(R21="Yes",S21<>"Public-welfare transfer"),"Unresolved, cross-ledger transfer missing",IF(I21<0,"Failed under stress",IF(AND(J21<>"",J21<0),"Conditional pass","Pass")))))))))))))) | Q21: =IF(A21="","",IF(P21="","No evidence ID",IFERROR(IF(VLOOKUP(P21,'Evidence Register'!A:M,11,FALSE)="Missing","Missing substantive evidence",IF(VLOOKUP(P21,'Evidence Register'!A:M,11,FALSE)="Contested","Contested substantive evidence",IF(VLOOKUP(P21,'Evidence Register'!A:M,10,FALSE)="Pinned","Pinned evidence",IF(VLOOKUP(P21,'Evidence Register'!A:M,10,FALSE)="Confidential-reviewable","Reviewable evidence","Pin issue: "&VLOOKUP(P21,'Evidence Register'!A:M,10,FALSE))))),"Missing evidence ID"))) | R21: =IF(A21="","",IF(OR(H21="",H21=0),"",IF(S21="","Missing origin",IF(S21<>"Local Fiscal","Yes","No"))))
A22: Total / dashboard line | F22: =IF(COUNTIF(B4:B21,"Triggered")=0,"",SUM(F4:F21)) | G22: =IF(COUNTIF(B4:B21,"Triggered")=0,"",IF(COUNT(G4:G21)=0,"",SUM(G4:G21))) | H22: =IF(COUNTIF(B4:B21,"Triggered")=0,"",SUM(H4:H21)) | I22: =IF(F22="","",H22-F22) | J22: =IF(OR(G22="",H22=""),"",H22-G22) | K22: =IF(COUNTIF(B4:B21,"Triggered")=0,"No entries yet",IF(COUNTIF(K4:K21,"*Failed*")>0,"Failed under stress",IF(COUNTIF(K4:K21,"Unresolved*")>0,"Unresolved",IF(COUNTIF(K4:K21,"Conditional pass")>0,"Conditional pass",IF(I22<0,"Failed under stress",IF(AND(J22<>"",J22<0),"Conditional pass","Pass")))))) | R22: =IF(OR(COUNTIFS(B4:B21,"Triggered",R4:R21,"Yes")>0,COUNTIFS(B4:B21,"Triggered",R4:R21,"Missing origin")>0),"Flag: cross-ledger or origin issue",IF(OR(COUNTIFS(B4:B21,"Triggered",Q4:Q21,"Missing evidence ID")>0,COUNTIFS(B4:B21,"Triggered",Q4:Q21,"Needs pin*")>0,COUNTIFS(B4:B21,"Triggered",Q4:Q21,"No evidence ID")>0),"Flag: evidence pin incomplete",""))

Sheet Water Env
A1: Water Env
A3: Ledger line | B3: Applicability | C3: Causation category | D3: Evidence band | E3: Unit | F3: Base exposure | G3: Stress exposure | H3: Credited resources | I3: Base gap | J3: Stress gap | K3: Status | L3: Evidence status | M3: Residual claimant | N3: Source URL / docket | O3: Page / table / order pin | P3: Evidence ID | Q3: Evidence quality check | R3: Cross-ledger check | S3: Resource ledger of origin | T3: Notes
A4: Water / wastewater debt | B4: Unknown | C4: Forecast-reliance | E4: bond-term NPV | I4: =IF(OR(A4="",B4<>"Triggered",F4="",H4=""),"",H4-F4) | J4: =IF(OR(A4="",B4<>"Triggered",G4="",H4=""),"",H4-G4) | K4: =IF(A4="","",IF(B4="Not applicable","Not applicable",IF(B4="Not triggered","Not triggered",IF(B4="Unknown","Unresolved, evidence missing",IF(L4="Confidential-reviewable","Unresolved, confidential but reviewable",IF(L4="Contested","Unresolved, contested",IF(COUNTIFS('Stress Cases'!$K$4:$K$12,"Water Env",'Stress Cases'!$L$4:$L$12,A4,'Stress Cases'!$I$4:$I$12,"Failed under stress")>0,"Failed under linked stress case",IF(COUNTIFS('Stress Cases'!$K$4:$K$12,"Water Env",'Stress Cases'!$L$4:$L$12,A4,'Stress Cases'!$I$4:$I$12,"Unresolved*")>0,"Unresolved, linked stress missing",IF(OR(F4="",H4=""),"Unresolved, evidence missing",IF(AND(H4>0,S4=""),"Unresolved, resource origin missing",IF(OR(ISNUMBER(SEARCH("No evidence",Q4)),ISNUMBER(SEARCH("Missing substantive",Q4)),ISNUMBER(SEARCH("Contested substantive",Q4))),"Unresolved, evidence missing",IF(AND(R4="Yes",S4<>"Public-welfare transfer"),"Unresolved, cross-ledger transfer missing",IF(I4<0,"Failed under stress",IF(AND(J4<>"",J4<0),"Conditional pass","Pass")))))))))))))) | L4: Missing | Q4: =IF(A4="","",IF(P4="","No evidence ID",IFERROR(IF(VLOOKUP(P4,'Evidence Register'!A:M,11,FALSE)="Missing","Missing substantive evidence",IF(VLOOKUP(P4,'Evidence Register'!A:M,11,FALSE)="Contested","Contested substantive evidence",IF(VLOOKUP(P4,'Evidence Register'!A:M,10,FALSE)="Pinned","Pinned evidence",IF(VLOOKUP(P4,'Evidence Register'!A:M,10,FALSE)="Confidential-reviewable","Reviewable evidence","Pin issue: "&VLOOKUP(P4,'Evidence Register'!A:M,10,FALSE))))),"Missing evidence ID"))) | R4: =IF(A4="","",IF(OR(H4="",H4=0),"",IF(S4="","Missing origin",IF(S4<>"Water Env","Yes","No"))))
A5: Drought-year / withdrawal limit | B5: Unknown | C5: Permit-governed | E5: non-monetized / $ | I5: =IF(OR(A5="",B5<>"Triggered",F5="",H5=""),"",H5-F5) | J5: =IF(OR(A5="",B5<>"Triggered",G5="",H5=""),"",H5-G5) | K5: =IF(A5="","",IF(B5="Not applicable","Not applicable",IF(B5="Not triggered","Not triggered",IF(B5="Unknown","Unresolved, evidence missing",IF(L5="Confidential-reviewable","Unresolved, confidential but reviewable",IF(L5="Contested","Unresolved, contested",IF(COUNTIFS('Stress Cases'!$K$4:$K$12,"Water Env",'Stress Cases'!$L$4:$L$12,A5,'Stress Cases'!$I$4:$I$12,"Failed under stress")>0,"Failed under linked stress case",IF(COUNTIFS('Stress Cases'!$K$4:$K$12,"Water Env",'Stress Cases'!$L$4:$L$12,A5,'Stress Cases'!$I$4:$I$12,"Unresolved*")>0,"Unresolved, linked stress missing",IF(OR(F5="",H5=""),"Unresolved, evidence missing",IF(AND(H5>0,S5=""),"Unresolved, resource origin missing",IF(OR(ISNUMBER(SEARCH("No evidence",Q5)),ISNUMBER(SEARCH("Missing substantive",Q5)),ISNUMBER(SEARCH("Contested substantive",Q5))),"Unresolved, evidence missing",IF(AND(R5="Yes",S5<>"Public-welfare transfer"),"Unresolved, cross-ledger transfer missing",IF(I5<0,"Failed under stress",IF(AND(J5<>"",J5<0),"Conditional pass","Pass")))))))))))))) | L5: Missing | Q5: =IF(A5="","",IF(P5="","No evidence ID",IFERROR(IF(VLOOKUP(P5,'Evidence Register'!A:M,11,FALSE)="Missing","Missing substantive evidence",IF(VLOOKUP(P5,'Evidence Register'!A:M,11,FALSE)="Contested","Contested substantive evidence",IF(VLOOKUP(P5,'Evidence Register'!A:M,10,FALSE)="Pinned","Pinned evidence",IF(VLOOKUP(P5,'Evidence Register'!A:M,10,FALSE)="Confidential-reviewable","Reviewable evidence","Pin issue: "&VLOOKUP(P5,'Evidence Register'!A:M,10,FALSE))))),"Missing evidence ID"))) | R5: =IF(A5="","",IF(OR(H5="",H5=0),"",IF(S5="","Missing origin",IF(S5<>"Water Env","Yes","No"))))
A6: Backup generation emissions | B6: Unknown | C6: Permit-governed | E6: permit / mitigation $ | I6: =IF(OR(A6="",B6<>"Triggered",F6="",H6=""),"",H6-F6) | J6: =IF(OR(A6="",B6<>"Triggered",G6="",H6=""),"",H6-G6) | K6: =IF(A6="","",IF(B6="Not applicable","Not applicable",IF(B6="Not triggered","Not triggered",IF(B6="Unknown","Unresolved, evidence missing",IF(L6="Confidential-reviewable","Unresolved, confidential but reviewable",IF(L6="Contested","Unresolved, contested",IF(COUNTIFS('Stress Cases'!$K$4:$K$12,"Water Env",'Stress Cases'!$L$4:$L$12,A6,'Stress Cases'!$I$4:$I$12,"Failed under stress")>0,"Failed under linked stress case",IF(COUNTIFS('Stress Cases'!$K$4:$K$12,"Water Env",'Stress Cases'!$L$4:$L$12,A6,'Stress Cases'!$I$4:$I$12,"Unresolved*")>0,"Unresolved, linked stress missing",IF(OR(F6="",H6=""),"Unresolved, evidence missing",IF(AND(H6>0,S6=""),"Unresolved, resource origin missing",IF(OR(ISNUMBER(SEARCH("No evidence",Q6)),ISNUMBER(SEARCH("Missing substantive",Q6)),ISNUMBER(SEARCH("Contested substantive",Q6))),"Unresolved, evidence missing",IF(AND(R6="Yes",S6<>"Public-welfare transfer"),"Unresolved, cross-ledger transfer missing",IF(I6<0,"Failed under stress",IF(AND(J6<>"",J6<0),"Conditional pass","Pass")))))))))))))) | L6: Missing | Q6: =IF(A6="","",IF(P6="","No evidence ID",IFERROR(IF(VLOOKUP(P6,'Evidence Register'!A:M,11,FALSE)="Missing","Missing substantive evidence",IF(VLOOKUP(P6,'Evidence Register'!A:M,11,FALSE)="Contested","Contested substantive evidence",IF(VLOOKUP(P6,'Evidence Register'!A:M,10,FALSE)="Pinned","Pinned evidence",IF(VLOOKUP(P6,'Evidence Register'!A:M,10,FALSE)="Confidential-reviewable","Reviewable evidence","Pin issue: "&VLOOKUP(P6,'Evidence Register'!A:M,10,FALSE))))),"Missing evidence ID"))) | R6: =IF(A6="","",IF(OR(H6="",H6=0),"",IF(S6="","Missing origin",IF(S6<>"Water Env","Yes","No"))))
A7: Noise / land-use burden | B7: Unknown | C7: Non-monetized | E7: mitigation / finding | I7: =IF(OR(A7="",B7<>"Triggered",F7="",H7=""),"",H7-F7) | J7: =IF(OR(A7="",B7<>"Triggered",G7="",H7=""),"",H7-G7) | K7: =IF(A7="","",IF(B7="Not applicable","Not applicable",IF(B7="Not triggered","Not triggered",IF(B7="Unknown","Unresolved, evidence missing",IF(L7="Confidential-reviewable","Unresolved, confidential but reviewable",IF(L7="Contested","Unresolved, contested",IF(COUNTIFS('Stress Cases'!$K$4:$K$12,"Water Env",'Stress Cases'!$L$4:$L$12,A7,'Stress Cases'!$I$4:$I$12,"Failed under stress")>0,"Failed under linked stress case",IF(COUNTIFS('Stress Cases'!$K$4:$K$12,"Water Env",'Stress Cases'!$L$4:$L$12,A7,'Stress Cases'!$I$4:$I$12,"Unresolved*")>0,"Unresolved, linked stress missing",IF(OR(F7="",H7=""),"Unresolved, evidence missing",IF(AND(H7>0,S7=""),"Unresolved, resource origin missing",IF(OR(ISNUMBER(SEARCH("No evidence",Q7)),ISNUMBER(SEARCH("Missing substantive",Q7)),ISNUMBER(SEARCH("Contested substantive",Q7))),"Unresolved, evidence missing",IF(AND(R7="Yes",S7<>"Public-welfare transfer"),"Unresolved, cross-ledger transfer missing",IF(I7<0,"Failed under stress",IF(AND(J7<>"",J7<0),"Conditional pass","Pass")))))))))))))) | L7: Missing | Q7: =IF(A7="","",IF(P7="","No evidence ID",IFERROR(IF(VLOOKUP(P7,'Evidence Register'!A:M,11,FALSE)="Missing","Missing substantive evidence",IF(VLOOKUP(P7,'Evidence Register'!A:M,11,FALSE)="Contested","Contested substantive evidence",IF(VLOOKUP(P7,'Evidence Register'!A:M,10,FALSE)="Pinned","Pinned evidence",IF(VLOOKUP(P7,'Evidence Register'!A:M,10,FALSE)="Confidential-reviewable","Reviewable evidence","Pin issue: "&VLOOKUP(P7,'Evidence Register'!A:M,10,FALSE))))),"Missing evidence ID"))) | R7: =IF(A7="","",IF(OR(H7="",H7=0),"",IF(S7="","Missing origin",IF(S7<>"Water Env","Yes","No"))))
A8: Permit compliance vs community settlement | B8: Unknown | C8: Permit-governed | E8: finding / mitigation | I8: =IF(OR(A8="",B8<>"Triggered",F8="",H8=""),"",H8-F8) | J8: =IF(OR(A8="",B8<>"Triggered",G8="",H8=""),"",H8-G8) | K8: =IF(A8="","",IF(B8="Not applicable","Not applicable",IF(B8="Not triggered","Not triggered",IF(B8="Unknown","Unresolved, evidence missing",IF(L8="Confidential-reviewable","Unresolved, confidential but reviewable",IF(L8="Contested","Unresolved, contested",IF(COUNTIFS('Stress Cases'!$K$4:$K$12,"Water Env",'Stress Cases'!$L$4:$L$12,A8,'Stress Cases'!$I$4:$I$12,"Failed under stress")>0,"Failed under linked stress case",IF(COUNTIFS('Stress Cases'!$K$4:$K$12,"Water Env",'Stress Cases'!$L$4:$L$12,A8,'Stress Cases'!$I$4:$I$12,"Unresolved*")>0,"Unresolved, linked stress missing",IF(OR(F8="",H8=""),"Unresolved, evidence missing",IF(AND(H8>0,S8=""),"Unresolved, resource origin missing",IF(OR(ISNUMBER(SEARCH("No evidence",Q8)),ISNUMBER(SEARCH("Missing substantive",Q8)),ISNUMBER(SEARCH("Contested substantive",Q8))),"Unresolved, evidence missing",IF(AND(R8="Yes",S8<>"Public-welfare transfer"),"Unresolved, cross-ledger transfer missing",IF(I8<0,"Failed under stress",IF(AND(J8<>"",J8<0),"Conditional pass","Pass")))))))))))))) | L8: Missing | Q8: =IF(A8="","",IF(P8="","No evidence ID",IFERROR(IF(VLOOKUP(P8,'Evidence Register'!A:M,11,FALSE)="Missing","Missing substantive evidence",IF(VLOOKUP(P8,'Evidence Register'!A:M,11,FALSE)="Contested","Contested substantive evidence",IF(VLOOKUP(P8,'Evidence Register'!A:M,10,FALSE)="Pinned","Pinned evidence",IF(VLOOKUP(P8,'Evidence Register'!A:M,10,FALSE)="Confidential-reviewable","Reviewable evidence","Pin issue: "&VLOOKUP(P8,'Evidence Register'!A:M,10,FALSE))))),"Missing evidence ID"))) | R8: =IF(A8="","",IF(OR(H8="",H8=0),"",IF(S8="","Missing origin",IF(S8<>"Water Env","Yes","No"))))
I9: =IF(OR(A9="",B9<>"Triggered",F9="",H9=""),"",H9-F9) | J9: =IF(OR(A9="",B9<>"Triggered",G9="",H9=""),"",H9-G9) | K9: =IF(A9="","",IF(B9="Not applicable","Not applicable",IF(B9="Not triggered","Not triggered",IF(B9="Unknown","Unresolved, evidence missing",IF(L9="Confidential-reviewable","Unresolved, confidential but reviewable",IF(L9="Contested","Unresolved, contested",IF(COUNTIFS('Stress Cases'!$K$4:$K$12,"Water Env",'Stress Cases'!$L$4:$L$12,A9,'Stress Cases'!$I$4:$I$12,"Failed under stress")>0,"Failed under linked stress case",IF(COUNTIFS('Stress Cases'!$K$4:$K$12,"Water Env",'Stress Cases'!$L$4:$L$12,A9,'Stress Cases'!$I$4:$I$12,"Unresolved*")>0,"Unresolved, linked stress missing",IF(OR(F9="",H9=""),"Unresolved, evidence missing",IF(AND(H9>0,S9=""),"Unresolved, resource origin missing",IF(OR(ISNUMBER(SEARCH("No evidence",Q9)),ISNUMBER(SEARCH("Missing substantive",Q9)),ISNUMBER(SEARCH("Contested substantive",Q9))),"Unresolved, evidence missing",IF(AND(R9="Yes",S9<>"Public-welfare transfer"),"Unresolved, cross-ledger transfer missing",IF(I9<0,"Failed under stress",IF(AND(J9<>"",J9<0),"Conditional pass","Pass")))))))))))))) | Q9: =IF(A9="","",IF(P9="","No evidence ID",IFERROR(IF(VLOOKUP(P9,'Evidence Register'!A:M,11,FALSE)="Missing","Missing substantive evidence",IF(VLOOKUP(P9,'Evidence Register'!A:M,11,FALSE)="Contested","Contested substantive evidence",IF(VLOOKUP(P9,'Evidence Register'!A:M,10,FALSE)="Pinned","Pinned evidence",IF(VLOOKUP(P9,'Evidence Register'!A:M,10,FALSE)="Confidential-reviewable","Reviewable evidence","Pin issue: "&VLOOKUP(P9,'Evidence Register'!A:M,10,FALSE))))),"Missing evidence ID"))) | R9: =IF(A9="","",IF(OR(H9="",H9=0),"",IF(S9="","Missing origin",IF(S9<>"Water Env","Yes","No"))))
I10: =IF(OR(A10="",B10<>"Triggered",F10="",H10=""),"",H10-F10) | J10: =IF(OR(A10="",B10<>"Triggered",G10="",H10=""),"",H10-G10) | K10: =IF(A10="","",IF(B10="Not applicable","Not applicable",IF(B10="Not triggered","Not triggered",IF(B10="Unknown","Unresolved, evidence missing",IF(L10="Confidential-reviewable","Unresolved, confidential but reviewable",IF(L10="Contested","Unresolved, contested",IF(COUNTIFS('Stress Cases'!$K$4:$K$12,"Water Env",'Stress Cases'!$L$4:$L$12,A10,'Stress Cases'!$I$4:$I$12,"Failed under stress")>0,"Failed under linked stress case",IF(COUNTIFS('Stress Cases'!$K$4:$K$12,"Water Env",'Stress Cases'!$L$4:$L$12,A10,'Stress Cases'!$I$4:$I$12,"Unresolved*")>0,"Unresolved, linked stress missing",IF(OR(F10="",H10=""),"Unresolved, evidence missing",IF(AND(H10>0,S10=""),"Unresolved, resource origin missing",IF(OR(ISNUMBER(SEARCH("No evidence",Q10)),ISNUMBER(SEARCH("Missing substantive",Q10)),ISNUMBER(SEARCH("Contested substantive",Q10))),"Unresolved, evidence missing",IF(AND(R10="Yes",S10<>"Public-welfare transfer"),"Unresolved, cross-ledger transfer missing",IF(I10<0,"Failed under stress",IF(AND(J10<>"",J10<0),"Conditional pass","Pass")))))))))))))) | Q10: =IF(A10="","",IF(P10="","No evidence ID",IFERROR(IF(VLOOKUP(P10,'Evidence Register'!A:M,11,FALSE)="Missing","Missing substantive evidence",IF(VLOOKUP(P10,'Evidence Register'!A:M,11,FALSE)="Contested","Contested substantive evidence",IF(VLOOKUP(P10,'Evidence Register'!A:M,10,FALSE)="Pinned","Pinned evidence",IF(VLOOKUP(P10,'Evidence Register'!A:M,10,FALSE)="Confidential-reviewable","Reviewable evidence","Pin issue: "&VLOOKUP(P10,'Evidence Register'!A:M,10,FALSE))))),"Missing evidence ID"))) | R10: =IF(A10="","",IF(OR(H10="",H10=0),"",IF(S10="","Missing origin",IF(S10<>"Water Env","Yes","No"))))
I11: =IF(OR(A11="",B11<>"Triggered",F11="",H11=""),"",H11-F11) | J11: =IF(OR(A11="",B11<>"Triggered",G11="",H11=""),"",H11-G11) | K11: =IF(A11="","",IF(B11="Not applicable","Not applicable",IF(B11="Not triggered","Not triggered",IF(B11="Unknown","Unresolved, evidence missing",IF(L11="Confidential-reviewable","Unresolved, confidential but reviewable",IF(L11="Contested","Unresolved, contested",IF(COUNTIFS('Stress Cases'!$K$4:$K$12,"Water Env",'Stress Cases'!$L$4:$L$12,A11,'Stress Cases'!$I$4:$I$12,"Failed under stress")>0,"Failed under linked stress case",IF(COUNTIFS('Stress Cases'!$K$4:$K$12,"Water Env",'Stress Cases'!$L$4:$L$12,A11,'Stress Cases'!$I$4:$I$12,"Unresolved*")>0,"Unresolved, linked stress missing",IF(OR(F11="",H11=""),"Unresolved, evidence missing",IF(AND(H11>0,S11=""),"Unresolved, resource origin missing",IF(OR(ISNUMBER(SEARCH("No evidence",Q11)),ISNUMBER(SEARCH("Missing substantive",Q11)),ISNUMBER(SEARCH("Contested substantive",Q11))),"Unresolved, evidence missing",IF(AND(R11="Yes",S11<>"Public-welfare transfer"),"Unresolved, cross-ledger transfer missing",IF(I11<0,"Failed under stress",IF(AND(J11<>"",J11<0),"Conditional pass","Pass")))))))))))))) | Q11: =IF(A11="","",IF(P11="","No evidence ID",IFERROR(IF(VLOOKUP(P11,'Evidence Register'!A:M,11,FALSE)="Missing","Missing substantive evidence",IF(VLOOKUP(P11,'Evidence Register'!A:M,11,FALSE)="Contested","Contested substantive evidence",IF(VLOOKUP(P11,'Evidence Register'!A:M,10,FALSE)="Pinned","Pinned evidence",IF(VLOOKUP(P11,'Evidence Register'!A:M,10,FALSE)="Confidential-reviewable","Reviewable evidence","Pin issue: "&VLOOKUP(P11,'Evidence Register'!A:M,10,FALSE))))),"Missing evidence ID"))) | R11: =IF(A11="","",IF(OR(H11="",H11=0),"",IF(S11="","Missing origin",IF(S11<>"Water Env","Yes","No"))))
I12: =IF(OR(A12="",B12<>"Triggered",F12="",H12=""),"",H12-F12) | J12: =IF(OR(A12="",B12<>"Triggered",G12="",H12=""),"",H12-G12) | K12: =IF(A12="","",IF(B12="Not applicable","Not applicable",IF(B12="Not triggered","Not triggered",IF(B12="Unknown","Unresolved, evidence missing",IF(L12="Confidential-reviewable","Unresolved, confidential but reviewable",IF(L12="Contested","Unresolved, contested",IF(COUNTIFS('Stress Cases'!$K$4:$K$12,"Water Env",'Stress Cases'!$L$4:$L$12,A12,'Stress Cases'!$I$4:$I$12,"Failed under stress")>0,"Failed under linked stress case",IF(COUNTIFS('Stress Cases'!$K$4:$K$12,"Water Env",'Stress Cases'!$L$4:$L$12,A12,'Stress Cases'!$I$4:$I$12,"Unresolved*")>0,"Unresolved, linked stress missing",IF(OR(F12="",H12=""),"Unresolved, evidence missing",IF(AND(H12>0,S12=""),"Unresolved, resource origin missing",IF(OR(ISNUMBER(SEARCH("No evidence",Q12)),ISNUMBER(SEARCH("Missing substantive",Q12)),ISNUMBER(SEARCH("Contested substantive",Q12))),"Unresolved, evidence missing",IF(AND(R12="Yes",S12<>"Public-welfare transfer"),"Unresolved, cross-ledger transfer missing",IF(I12<0,"Failed under stress",IF(AND(J12<>"",J12<0),"Conditional pass","Pass")))))))))))))) | Q12: =IF(A12="","",IF(P12="","No evidence ID",IFERROR(IF(VLOOKUP(P12,'Evidence Register'!A:M,11,FALSE)="Missing","Missing substantive evidence",IF(VLOOKUP(P12,'Evidence Register'!A:M,11,FALSE)="Contested","Contested substantive evidence",IF(VLOOKUP(P12,'Evidence Register'!A:M,10,FALSE)="Pinned","Pinned evidence",IF(VLOOKUP(P12,'Evidence Register'!A:M,10,FALSE)="Confidential-reviewable","Reviewable evidence","Pin issue: "&VLOOKUP(P12,'Evidence Register'!A:M,10,FALSE))))),"Missing evidence ID"))) | R12: =IF(A12="","",IF(OR(H12="",H12=0),"",IF(S12="","Missing origin",IF(S12<>"Water Env","Yes","No"))))
I13: =IF(OR(A13="",B13<>"Triggered",F13="",H13=""),"",H13-F13) | J13: =IF(OR(A13="",B13<>"Triggered",G13="",H13=""),"",H13-G13) | K13: =IF(A13="","",IF(B13="Not applicable","Not applicable",IF(B13="Not triggered","Not triggered",IF(B13="Unknown","Unresolved, evidence missing",IF(L13="Confidential-reviewable","Unresolved, confidential but reviewable",IF(L13="Contested","Unresolved, contested",IF(COUNTIFS('Stress Cases'!$K$4:$K$12,"Water Env",'Stress Cases'!$L$4:$L$12,A13,'Stress Cases'!$I$4:$I$12,"Failed under stress")>0,"Failed under linked stress case",IF(COUNTIFS('Stress Cases'!$K$4:$K$12,"Water Env",'Stress Cases'!$L$4:$L$12,A13,'Stress Cases'!$I$4:$I$12,"Unresolved*")>0,"Unresolved, linked stress missing",IF(OR(F13="",H13=""),"Unresolved, evidence missing",IF(AND(H13>0,S13=""),"Unresolved, resource origin missing",IF(OR(ISNUMBER(SEARCH("No evidence",Q13)),ISNUMBER(SEARCH("Missing substantive",Q13)),ISNUMBER(SEARCH("Contested substantive",Q13))),"Unresolved, evidence missing",IF(AND(R13="Yes",S13<>"Public-welfare transfer"),"Unresolved, cross-ledger transfer missing",IF(I13<0,"Failed under stress",IF(AND(J13<>"",J13<0),"Conditional pass","Pass")))))))))))))) | Q13: =IF(A13="","",IF(P13="","No evidence ID",IFERROR(IF(VLOOKUP(P13,'Evidence Register'!A:M,11,FALSE)="Missing","Missing substantive evidence",IF(VLOOKUP(P13,'Evidence Register'!A:M,11,FALSE)="Contested","Contested substantive evidence",IF(VLOOKUP(P13,'Evidence Register'!A:M,10,FALSE)="Pinned","Pinned evidence",IF(VLOOKUP(P13,'Evidence Register'!A:M,10,FALSE)="Confidential-reviewable","Reviewable evidence","Pin issue: "&VLOOKUP(P13,'Evidence Register'!A:M,10,FALSE))))),"Missing evidence ID"))) | R13: =IF(A13="","",IF(OR(H13="",H13=0),"",IF(S13="","Missing origin",IF(S13<>"Water Env","Yes","No"))))
I14: =IF(OR(A14="",B14<>"Triggered",F14="",H14=""),"",H14-F14) | J14: =IF(OR(A14="",B14<>"Triggered",G14="",H14=""),"",H14-G14) | K14: =IF(A14="","",IF(B14="Not applicable","Not applicable",IF(B14="Not triggered","Not triggered",IF(B14="Unknown","Unresolved, evidence missing",IF(L14="Confidential-reviewable","Unresolved, confidential but reviewable",IF(L14="Contested","Unresolved, contested",IF(COUNTIFS('Stress Cases'!$K$4:$K$12,"Water Env",'Stress Cases'!$L$4:$L$12,A14,'Stress Cases'!$I$4:$I$12,"Failed under stress")>0,"Failed under linked stress case",IF(COUNTIFS('Stress Cases'!$K$4:$K$12,"Water Env",'Stress Cases'!$L$4:$L$12,A14,'Stress Cases'!$I$4:$I$12,"Unresolved*")>0,"Unresolved, linked stress missing",IF(OR(F14="",H14=""),"Unresolved, evidence missing",IF(AND(H14>0,S14=""),"Unresolved, resource origin missing",IF(OR(ISNUMBER(SEARCH("No evidence",Q14)),ISNUMBER(SEARCH("Missing substantive",Q14)),ISNUMBER(SEARCH("Contested substantive",Q14))),"Unresolved, evidence missing",IF(AND(R14="Yes",S14<>"Public-welfare transfer"),"Unresolved, cross-ledger transfer missing",IF(I14<0,"Failed under stress",IF(AND(J14<>"",J14<0),"Conditional pass","Pass")))))))))))))) | Q14: =IF(A14="","",IF(P14="","No evidence ID",IFERROR(IF(VLOOKUP(P14,'Evidence Register'!A:M,11,FALSE)="Missing","Missing substantive evidence",IF(VLOOKUP(P14,'Evidence Register'!A:M,11,FALSE)="Contested","Contested substantive evidence",IF(VLOOKUP(P14,'Evidence Register'!A:M,10,FALSE)="Pinned","Pinned evidence",IF(VLOOKUP(P14,'Evidence Register'!A:M,10,FALSE)="Confidential-reviewable","Reviewable evidence","Pin issue: "&VLOOKUP(P14,'Evidence Register'!A:M,10,FALSE))))),"Missing evidence ID"))) | R14: =IF(A14="","",IF(OR(H14="",H14=0),"",IF(S14="","Missing origin",IF(S14<>"Water Env","Yes","No"))))
I15: =IF(OR(A15="",B15<>"Triggered",F15="",H15=""),"",H15-F15) | J15: =IF(OR(A15="",B15<>"Triggered",G15="",H15=""),"",H15-G15) | K15: =IF(A15="","",IF(B15="Not applicable","Not applicable",IF(B15="Not triggered","Not triggered",IF(B15="Unknown","Unresolved, evidence missing",IF(L15="Confidential-reviewable","Unresolved, confidential but reviewable",IF(L15="Contested","Unresolved, contested",IF(COUNTIFS('Stress Cases'!$K$4:$K$12,"Water Env",'Stress Cases'!$L$4:$L$12,A15,'Stress Cases'!$I$4:$I$12,"Failed under stress")>0,"Failed under linked stress case",IF(COUNTIFS('Stress Cases'!$K$4:$K$12,"Water Env",'Stress Cases'!$L$4:$L$12,A15,'Stress Cases'!$I$4:$I$12,"Unresolved*")>0,"Unresolved, linked stress missing",IF(OR(F15="",H15=""),"Unresolved, evidence missing",IF(AND(H15>0,S15=""),"Unresolved, resource origin missing",IF(OR(ISNUMBER(SEARCH("No evidence",Q15)),ISNUMBER(SEARCH("Missing substantive",Q15)),ISNUMBER(SEARCH("Contested substantive",Q15))),"Unresolved, evidence missing",IF(AND(R15="Yes",S15<>"Public-welfare transfer"),"Unresolved, cross-ledger transfer missing",IF(I15<0,"Failed under stress",IF(AND(J15<>"",J15<0),"Conditional pass","Pass")))))))))))))) | Q15: =IF(A15="","",IF(P15="","No evidence ID",IFERROR(IF(VLOOKUP(P15,'Evidence Register'!A:M,11,FALSE)="Missing","Missing substantive evidence",IF(VLOOKUP(P15,'Evidence Register'!A:M,11,FALSE)="Contested","Contested substantive evidence",IF(VLOOKUP(P15,'Evidence Register'!A:M,10,FALSE)="Pinned","Pinned evidence",IF(VLOOKUP(P15,'Evidence Register'!A:M,10,FALSE)="Confidential-reviewable","Reviewable evidence","Pin issue: "&VLOOKUP(P15,'Evidence Register'!A:M,10,FALSE))))),"Missing evidence ID"))) | R15: =IF(A15="","",IF(OR(H15="",H15=0),"",IF(S15="","Missing origin",IF(S15<>"Water Env","Yes","No"))))
I16: =IF(OR(A16="",B16<>"Triggered",F16="",H16=""),"",H16-F16) | J16: =IF(OR(A16="",B16<>"Triggered",G16="",H16=""),"",H16-G16) | K16: =IF(A16="","",IF(B16="Not applicable","Not applicable",IF(B16="Not triggered","Not triggered",IF(B16="Unknown","Unresolved, evidence missing",IF(L16="Confidential-reviewable","Unresolved, confidential but reviewable",IF(L16="Contested","Unresolved, contested",IF(COUNTIFS('Stress Cases'!$K$4:$K$12,"Water Env",'Stress Cases'!$L$4:$L$12,A16,'Stress Cases'!$I$4:$I$12,"Failed under stress")>0,"Failed under linked stress case",IF(COUNTIFS('Stress Cases'!$K$4:$K$12,"Water Env",'Stress Cases'!$L$4:$L$12,A16,'Stress Cases'!$I$4:$I$12,"Unresolved*")>0,"Unresolved, linked stress missing",IF(OR(F16="",H16=""),"Unresolved, evidence missing",IF(AND(H16>0,S16=""),"Unresolved, resource origin missing",IF(OR(ISNUMBER(SEARCH("No evidence",Q16)),ISNUMBER(SEARCH("Missing substantive",Q16)),ISNUMBER(SEARCH("Contested substantive",Q16))),"Unresolved, evidence missing",IF(AND(R16="Yes",S16<>"Public-welfare transfer"),"Unresolved, cross-ledger transfer missing",IF(I16<0,"Failed under stress",IF(AND(J16<>"",J16<0),"Conditional pass","Pass")))))))))))))) | Q16: =IF(A16="","",IF(P16="","No evidence ID",IFERROR(IF(VLOOKUP(P16,'Evidence Register'!A:M,11,FALSE)="Missing","Missing substantive evidence",IF(VLOOKUP(P16,'Evidence Register'!A:M,11,FALSE)="Contested","Contested substantive evidence",IF(VLOOKUP(P16,'Evidence Register'!A:M,10,FALSE)="Pinned","Pinned evidence",IF(VLOOKUP(P16,'Evidence Register'!A:M,10,FALSE)="Confidential-reviewable","Reviewable evidence","Pin issue: "&VLOOKUP(P16,'Evidence Register'!A:M,10,FALSE))))),"Missing evidence ID"))) | R16: =IF(A16="","",IF(OR(H16="",H16=0),"",IF(S16="","Missing origin",IF(S16<>"Water Env","Yes","No"))))
I17: =IF(OR(A17="",B17<>"Triggered",F17="",H17=""),"",H17-F17) | J17: =IF(OR(A17="",B17<>"Triggered",G17="",H17=""),"",H17-G17) | K17: =IF(A17="","",IF(B17="Not applicable","Not applicable",IF(B17="Not triggered","Not triggered",IF(B17="Unknown","Unresolved, evidence missing",IF(L17="Confidential-reviewable","Unresolved, confidential but reviewable",IF(L17="Contested","Unresolved, contested",IF(COUNTIFS('Stress Cases'!$K$4:$K$12,"Water Env",'Stress Cases'!$L$4:$L$12,A17,'Stress Cases'!$I$4:$I$12,"Failed under stress")>0,"Failed under linked stress case",IF(COUNTIFS('Stress Cases'!$K$4:$K$12,"Water Env",'Stress Cases'!$L$4:$L$12,A17,'Stress Cases'!$I$4:$I$12,"Unresolved*")>0,"Unresolved, linked stress missing",IF(OR(F17="",H17=""),"Unresolved, evidence missing",IF(AND(H17>0,S17=""),"Unresolved, resource origin missing",IF(OR(ISNUMBER(SEARCH("No evidence",Q17)),ISNUMBER(SEARCH("Missing substantive",Q17)),ISNUMBER(SEARCH("Contested substantive",Q17))),"Unresolved, evidence missing",IF(AND(R17="Yes",S17<>"Public-welfare transfer"),"Unresolved, cross-ledger transfer missing",IF(I17<0,"Failed under stress",IF(AND(J17<>"",J17<0),"Conditional pass","Pass")))))))))))))) | Q17: =IF(A17="","",IF(P17="","No evidence ID",IFERROR(IF(VLOOKUP(P17,'Evidence Register'!A:M,11,FALSE)="Missing","Missing substantive evidence",IF(VLOOKUP(P17,'Evidence Register'!A:M,11,FALSE)="Contested","Contested substantive evidence",IF(VLOOKUP(P17,'Evidence Register'!A:M,10,FALSE)="Pinned","Pinned evidence",IF(VLOOKUP(P17,'Evidence Register'!A:M,10,FALSE)="Confidential-reviewable","Reviewable evidence","Pin issue: "&VLOOKUP(P17,'Evidence Register'!A:M,10,FALSE))))),"Missing evidence ID"))) | R17: =IF(A17="","",IF(OR(H17="",H17=0),"",IF(S17="","Missing origin",IF(S17<>"Water Env","Yes","No"))))
I18: =IF(OR(A18="",B18<>"Triggered",F18="",H18=""),"",H18-F18) | J18: =IF(OR(A18="",B18<>"Triggered",G18="",H18=""),"",H18-G18) | K18: =IF(A18="","",IF(B18="Not applicable","Not applicable",IF(B18="Not triggered","Not triggered",IF(B18="Unknown","Unresolved, evidence missing",IF(L18="Confidential-reviewable","Unresolved, confidential but reviewable",IF(L18="Contested","Unresolved, contested",IF(COUNTIFS('Stress Cases'!$K$4:$K$12,"Water Env",'Stress Cases'!$L$4:$L$12,A18,'Stress Cases'!$I$4:$I$12,"Failed under stress")>0,"Failed under linked stress case",IF(COUNTIFS('Stress Cases'!$K$4:$K$12,"Water Env",'Stress Cases'!$L$4:$L$12,A18,'Stress Cases'!$I$4:$I$12,"Unresolved*")>0,"Unresolved, linked stress missing",IF(OR(F18="",H18=""),"Unresolved, evidence missing",IF(AND(H18>0,S18=""),"Unresolved, resource origin missing",IF(OR(ISNUMBER(SEARCH("No evidence",Q18)),ISNUMBER(SEARCH("Missing substantive",Q18)),ISNUMBER(SEARCH("Contested substantive",Q18))),"Unresolved, evidence missing",IF(AND(R18="Yes",S18<>"Public-welfare transfer"),"Unresolved, cross-ledger transfer missing",IF(I18<0,"Failed under stress",IF(AND(J18<>"",J18<0),"Conditional pass","Pass")))))))))))))) | Q18: =IF(A18="","",IF(P18="","No evidence ID",IFERROR(IF(VLOOKUP(P18,'Evidence Register'!A:M,11,FALSE)="Missing","Missing substantive evidence",IF(VLOOKUP(P18,'Evidence Register'!A:M,11,FALSE)="Contested","Contested substantive evidence",IF(VLOOKUP(P18,'Evidence Register'!A:M,10,FALSE)="Pinned","Pinned evidence",IF(VLOOKUP(P18,'Evidence Register'!A:M,10,FALSE)="Confidential-reviewable","Reviewable evidence","Pin issue: "&VLOOKUP(P18,'Evidence Register'!A:M,10,FALSE))))),"Missing evidence ID"))) | R18: =IF(A18="","",IF(OR(H18="",H18=0),"",IF(S18="","Missing origin",IF(S18<>"Water Env","Yes","No"))))
I19: =IF(OR(A19="",B19<>"Triggered",F19="",H19=""),"",H19-F19) | J19: =IF(OR(A19="",B19<>"Triggered",G19="",H19=""),"",H19-G19) | K19: =IF(A19="","",IF(B19="Not applicable","Not applicable",IF(B19="Not triggered","Not triggered",IF(B19="Unknown","Unresolved, evidence missing",IF(L19="Confidential-reviewable","Unresolved, confidential but reviewable",IF(L19="Contested","Unresolved, contested",IF(COUNTIFS('Stress Cases'!$K$4:$K$12,"Water Env",'Stress Cases'!$L$4:$L$12,A19,'Stress Cases'!$I$4:$I$12,"Failed under stress")>0,"Failed under linked stress case",IF(COUNTIFS('Stress Cases'!$K$4:$K$12,"Water Env",'Stress Cases'!$L$4:$L$12,A19,'Stress Cases'!$I$4:$I$12,"Unresolved*")>0,"Unresolved, linked stress missing",IF(OR(F19="",H19=""),"Unresolved, evidence missing",IF(AND(H19>0,S19=""),"Unresolved, resource origin missing",IF(OR(ISNUMBER(SEARCH("No evidence",Q19)),ISNUMBER(SEARCH("Missing substantive",Q19)),ISNUMBER(SEARCH("Contested substantive",Q19))),"Unresolved, evidence missing",IF(AND(R19="Yes",S19<>"Public-welfare transfer"),"Unresolved, cross-ledger transfer missing",IF(I19<0,"Failed under stress",IF(AND(J19<>"",J19<0),"Conditional pass","Pass")))))))))))))) | Q19: =IF(A19="","",IF(P19="","No evidence ID",IFERROR(IF(VLOOKUP(P19,'Evidence Register'!A:M,11,FALSE)="Missing","Missing substantive evidence",IF(VLOOKUP(P19,'Evidence Register'!A:M,11,FALSE)="Contested","Contested substantive evidence",IF(VLOOKUP(P19,'Evidence Register'!A:M,10,FALSE)="Pinned","Pinned evidence",IF(VLOOKUP(P19,'Evidence Register'!A:M,10,FALSE)="Confidential-reviewable","Reviewable evidence","Pin issue: "&VLOOKUP(P19,'Evidence Register'!A:M,10,FALSE))))),"Missing evidence ID"))) | R19: =IF(A19="","",IF(OR(H19="",H19=0),"",IF(S19="","Missing origin",IF(S19<>"Water Env","Yes","No"))))
I20: =IF(OR(A20="",B20<>"Triggered",F20="",H20=""),"",H20-F20) | J20: =IF(OR(A20="",B20<>"Triggered",G20="",H20=""),"",H20-G20) | K20: =IF(A20="","",IF(B20="Not applicable","Not applicable",IF(B20="Not triggered","Not triggered",IF(B20="Unknown","Unresolved, evidence missing",IF(L20="Confidential-reviewable","Unresolved, confidential but reviewable",IF(L20="Contested","Unresolved, contested",IF(COUNTIFS('Stress Cases'!$K$4:$K$12,"Water Env",'Stress Cases'!$L$4:$L$12,A20,'Stress Cases'!$I$4:$I$12,"Failed under stress")>0,"Failed under linked stress case",IF(COUNTIFS('Stress Cases'!$K$4:$K$12,"Water Env",'Stress Cases'!$L$4:$L$12,A20,'Stress Cases'!$I$4:$I$12,"Unresolved*")>0,"Unresolved, linked stress missing",IF(OR(F20="",H20=""),"Unresolved, evidence missing",IF(AND(H20>0,S20=""),"Unresolved, resource origin missing",IF(OR(ISNUMBER(SEARCH("No evidence",Q20)),ISNUMBER(SEARCH("Missing substantive",Q20)),ISNUMBER(SEARCH("Contested substantive",Q20))),"Unresolved, evidence missing",IF(AND(R20="Yes",S20<>"Public-welfare transfer"),"Unresolved, cross-ledger transfer missing",IF(I20<0,"Failed under stress",IF(AND(J20<>"",J20<0),"Conditional pass","Pass")))))))))))))) | Q20: =IF(A20="","",IF(P20="","No evidence ID",IFERROR(IF(VLOOKUP(P20,'Evidence Register'!A:M,11,FALSE)="Missing","Missing substantive evidence",IF(VLOOKUP(P20,'Evidence Register'!A:M,11,FALSE)="Contested","Contested substantive evidence",IF(VLOOKUP(P20,'Evidence Register'!A:M,10,FALSE)="Pinned","Pinned evidence",IF(VLOOKUP(P20,'Evidence Register'!A:M,10,FALSE)="Confidential-reviewable","Reviewable evidence","Pin issue: "&VLOOKUP(P20,'Evidence Register'!A:M,10,FALSE))))),"Missing evidence ID"))) | R20: =IF(A20="","",IF(OR(H20="",H20=0),"",IF(S20="","Missing origin",IF(S20<>"Water Env","Yes","No"))))
I21: =IF(OR(A21="",B21<>"Triggered",F21="",H21=""),"",H21-F21) | J21: =IF(OR(A21="",B21<>"Triggered",G21="",H21=""),"",H21-G21) | K21: =IF(A21="","",IF(B21="Not applicable","Not applicable",IF(B21="Not triggered","Not triggered",IF(B21="Unknown","Unresolved, evidence missing",IF(L21="Confidential-reviewable","Unresolved, confidential but reviewable",IF(L21="Contested","Unresolved, contested",IF(COUNTIFS('Stress Cases'!$K$4:$K$12,"Water Env",'Stress Cases'!$L$4:$L$12,A21,'Stress Cases'!$I$4:$I$12,"Failed under stress")>0,"Failed under linked stress case",IF(COUNTIFS('Stress Cases'!$K$4:$K$12,"Water Env",'Stress Cases'!$L$4:$L$12,A21,'Stress Cases'!$I$4:$I$12,"Unresolved*")>0,"Unresolved, linked stress missing",IF(OR(F21="",H21=""),"Unresolved, evidence missing",IF(AND(H21>0,S21=""),"Unresolved, resource origin missing",IF(OR(ISNUMBER(SEARCH("No evidence",Q21)),ISNUMBER(SEARCH("Missing substantive",Q21)),ISNUMBER(SEARCH("Contested substantive",Q21))),"Unresolved, evidence missing",IF(AND(R21="Yes",S21<>"Public-welfare transfer"),"Unresolved, cross-ledger transfer missing",IF(I21<0,"Failed under stress",IF(AND(J21<>"",J21<0),"Conditional pass","Pass")))))))))))))) | Q21: =IF(A21="","",IF(P21="","No evidence ID",IFERROR(IF(VLOOKUP(P21,'Evidence Register'!A:M,11,FALSE)="Missing","Missing substantive evidence",IF(VLOOKUP(P21,'Evidence Register'!A:M,11,FALSE)="Contested","Contested substantive evidence",IF(VLOOKUP(P21,'Evidence Register'!A:M,10,FALSE)="Pinned","Pinned evidence",IF(VLOOKUP(P21,'Evidence Register'!A:M,10,FALSE)="Confidential-reviewable","Reviewable evidence","Pin issue: "&VLOOKUP(P21,'Evidence Register'!A:M,10,FALSE))))),"Missing evidence ID"))) | R21: =IF(A21="","",IF(OR(H21="",H21=0),"",IF(S21="","Missing origin",IF(S21<>"Water Env","Yes","No"))))
A22: Total / dashboard line | F22: =IF(COUNTIF(B4:B21,"Triggered")=0,"",SUM(F4:F21)) | G22: =IF(COUNTIF(B4:B21,"Triggered")=0,"",IF(COUNT(G4:G21)=0,"",SUM(G4:G21))) | H22: =IF(COUNTIF(B4:B21,"Triggered")=0,"",SUM(H4:H21)) | I22: =IF(F22="","",H22-F22) | J22: =IF(OR(G22="",H22=""),"",H22-G22) | K22: =IF(COUNTIF(B4:B21,"Triggered")=0,"No entries yet",IF(COUNTIF(K4:K21,"*Failed*")>0,"Failed under stress",IF(COUNTIF(K4:K21,"Unresolved*")>0,"Unresolved",IF(COUNTIF(K4:K21,"Conditional pass")>0,"Conditional pass",IF(I22<0,"Failed under stress",IF(AND(J22<>"",J22<0),"Conditional pass","Pass")))))) | R22: =IF(OR(COUNTIFS(B4:B21,"Triggered",R4:R21,"Yes")>0,COUNTIFS(B4:B21,"Triggered",R4:R21,"Missing origin")>0),"Flag: cross-ledger or origin issue",IF(OR(COUNTIFS(B4:B21,"Triggered",Q4:Q21,"Missing evidence ID")>0,COUNTIFS(B4:B21,"Triggered",Q4:Q21,"Needs pin*")>0,COUNTIFS(B4:B21,"Triggered",Q4:Q21,"No evidence ID")>0),"Flag: evidence pin incomplete",""))

Sheet Credit Collateral
A1: Credit Collateral
A3: Ledger line | B3: Applicability | C3: Causation category | D3: Evidence band | E3: Unit | F3: Base exposure | G3: Stress exposure | H3: Credited resources | I3: Base gap | J3: Stress gap | K3: Status | L3: Evidence status | M3: Residual claimant | N3: Source URL / docket | O3: Page / table / order pin | P3: Evidence ID | Q3: Evidence quality check | R3: Cross-ledger check | S3: Resource ledger of origin | T3: Notes
A4: Cash / escrow | B4: Unknown | C4: Settlement resource | D4: Settled cash | E4: one-time $ | I4: =IF(OR(A4="",B4<>"Triggered",F4="",H4=""),"",H4-F4) | J4: =IF(OR(A4="",B4<>"Triggered",G4="",H4=""),"",H4-G4) | K4: =IF(A4="","",IF(B4="Not applicable","Not applicable",IF(B4="Not triggered","Not triggered",IF(B4="Unknown","Unresolved, evidence missing",IF(L4="Confidential-reviewable","Unresolved, confidential but reviewable",IF(L4="Contested","Unresolved, contested",IF(COUNTIFS('Stress Cases'!$K$4:$K$12,"Credit Collateral",'Stress Cases'!$L$4:$L$12,A4,'Stress Cases'!$I$4:$I$12,"Failed under stress")>0,"Failed under linked stress case",IF(COUNTIFS('Stress Cases'!$K$4:$K$12,"Credit Collateral",'Stress Cases'!$L$4:$L$12,A4,'Stress Cases'!$I$4:$I$12,"Unresolved*")>0,"Unresolved, linked stress missing",IF(OR(F4="",H4=""),"Unresolved, evidence missing",IF(AND(H4>0,S4=""),"Unresolved, resource origin missing",IF(OR(ISNUMBER(SEARCH("No evidence",Q4)),ISNUMBER(SEARCH("Missing substantive",Q4)),ISNUMBER(SEARCH("Contested substantive",Q4))),"Unresolved, evidence missing",IF(AND(R4="Yes",S4<>"Public-welfare transfer"),"Unresolved, cross-ledger transfer missing",IF(I4<0,"Failed under stress",IF(AND(J4<>"",J4<0),"Conditional pass","Pass")))))))))))))) | L4: Missing | Q4: =IF(A4="","",IF(P4="","No evidence ID",IFERROR(IF(VLOOKUP(P4,'Evidence Register'!A:M,11,FALSE)="Missing","Missing substantive evidence",IF(VLOOKUP(P4,'Evidence Register'!A:M,11,FALSE)="Contested","Contested substantive evidence",IF(VLOOKUP(P4,'Evidence Register'!A:M,10,FALSE)="Pinned","Pinned evidence",IF(VLOOKUP(P4,'Evidence Register'!A:M,10,FALSE)="Confidential-reviewable","Reviewable evidence","Pin issue: "&VLOOKUP(P4,'Evidence Register'!A:M,10,FALSE))))),"Missing evidence ID"))) | R4: =IF(A4="","",IF(OR(H4="",H4=0),"",IF(S4="","Missing origin",IF(S4<>"Credit Collateral","Yes","No"))))
A5: LOC / secured credit | B5: Unknown | C5: Settlement resource | D5: Callable secured credit | E5: one-time $ | I5: =IF(OR(A5="",B5<>"Triggered",F5="",H5=""),"",H5-F5) | J5: =IF(OR(A5="",B5<>"Triggered",G5="",H5=""),"",H5-G5) | K5: =IF(A5="","",IF(B5="Not applicable","Not applicable",IF(B5="Not triggered","Not triggered",IF(B5="Unknown","Unresolved, evidence missing",IF(L5="Confidential-reviewable","Unresolved, confidential but reviewable",IF(L5="Contested","Unresolved, contested",IF(COUNTIFS('Stress Cases'!$K$4:$K$12,"Credit Collateral",'Stress Cases'!$L$4:$L$12,A5,'Stress Cases'!$I$4:$I$12,"Failed under stress")>0,"Failed under linked stress case",IF(COUNTIFS('Stress Cases'!$K$4:$K$12,"Credit Collateral",'Stress Cases'!$L$4:$L$12,A5,'Stress Cases'!$I$4:$I$12,"Unresolved*")>0,"Unresolved, linked stress missing",IF(OR(F5="",H5=""),"Unresolved, evidence missing",IF(AND(H5>0,S5=""),"Unresolved, resource origin missing",IF(OR(ISNUMBER(SEARCH("No evidence",Q5)),ISNUMBER(SEARCH("Missing substantive",Q5)),ISNUMBER(SEARCH("Contested substantive",Q5))),"Unresolved, evidence missing",IF(AND(R5="Yes",S5<>"Public-welfare transfer"),"Unresolved, cross-ledger transfer missing",IF(I5<0,"Failed under stress",IF(AND(J5<>"",J5<0),"Conditional pass","Pass")))))))))))))) | L5: Missing | Q5: =IF(A5="","",IF(P5="","No evidence ID",IFERROR(IF(VLOOKUP(P5,'Evidence Register'!A:M,11,FALSE)="Missing","Missing substantive evidence",IF(VLOOKUP(P5,'Evidence Register'!A:M,11,FALSE)="Contested","Contested substantive evidence",IF(VLOOKUP(P5,'Evidence Register'!A:M,10,FALSE)="Pinned","Pinned evidence",IF(VLOOKUP(P5,'Evidence Register'!A:M,10,FALSE)="Confidential-reviewable","Reviewable evidence","Pin issue: "&VLOOKUP(P5,'Evidence Register'!A:M,10,FALSE))))),"Missing evidence ID"))) | R5: =IF(A5="","",IF(OR(H5="",H5=0),"",IF(S5="","Missing origin",IF(S5<>"Credit Collateral","Yes","No"))))
A6: Parent guarantee | B6: Unknown | C6: Settlement resource | D6: Enforceable scoped promise | E6: covered obligation $ | I6: =IF(OR(A6="",B6<>"Triggered",F6="",H6=""),"",H6-F6) | J6: =IF(OR(A6="",B6<>"Triggered",G6="",H6=""),"",H6-G6) | K6: =IF(A6="","",IF(B6="Not applicable","Not applicable",IF(B6="Not triggered","Not triggered",IF(B6="Unknown","Unresolved, evidence missing",IF(L6="Confidential-reviewable","Unresolved, confidential but reviewable",IF(L6="Contested","Unresolved, contested",IF(COUNTIFS('Stress Cases'!$K$4:$K$12,"Credit Collateral",'Stress Cases'!$L$4:$L$12,A6,'Stress Cases'!$I$4:$I$12,"Failed under stress")>0,"Failed under linked stress case",IF(COUNTIFS('Stress Cases'!$K$4:$K$12,"Credit Collateral",'Stress Cases'!$L$4:$L$12,A6,'Stress Cases'!$I$4:$I$12,"Unresolved*")>0,"Unresolved, linked stress missing",IF(OR(F6="",H6=""),"Unresolved, evidence missing",IF(AND(H6>0,S6=""),"Unresolved, resource origin missing",IF(OR(ISNUMBER(SEARCH("No evidence",Q6)),ISNUMBER(SEARCH("Missing substantive",Q6)),ISNUMBER(SEARCH("Contested substantive",Q6))),"Unresolved, evidence missing",IF(AND(R6="Yes",S6<>"Public-welfare transfer"),"Unresolved, cross-ledger transfer missing",IF(I6<0,"Failed under stress",IF(AND(J6<>"",J6<0),"Conditional pass","Pass")))))))))))))) | L6: Missing | Q6: =IF(A6="","",IF(P6="","No evidence ID",IFERROR(IF(VLOOKUP(P6,'Evidence Register'!A:M,11,FALSE)="Missing","Missing substantive evidence",IF(VLOOKUP(P6,'Evidence Register'!A:M,11,FALSE)="Contested","Contested substantive evidence",IF(VLOOKUP(P6,'Evidence Register'!A:M,10,FALSE)="Pinned","Pinned evidence",IF(VLOOKUP(P6,'Evidence Register'!A:M,10,FALSE)="Confidential-reviewable","Reviewable evidence","Pin issue: "&VLOOKUP(P6,'Evidence Register'!A:M,10,FALSE))))),"Missing evidence ID"))) | R6: =IF(A6="","",IF(OR(H6="",H6=0),"",IF(S6="","Missing origin",IF(S6<>"Credit Collateral","Yes","No"))))
A7: Affiliate / SPV promise | B7: Unknown | C7: Settlement resource | D7: Unsecured promise | E7: covered obligation $ | I7: =IF(OR(A7="",B7<>"Triggered",F7="",H7=""),"",H7-F7) | J7: =IF(OR(A7="",B7<>"Triggered",G7="",H7=""),"",H7-G7) | K7: =IF(A7="","",IF(B7="Not applicable","Not applicable",IF(B7="Not triggered","Not triggered",IF(B7="Unknown","Unresolved, evidence missing",IF(L7="Confidential-reviewable","Unresolved, confidential but reviewable",IF(L7="Contested","Unresolved, contested",IF(COUNTIFS('Stress Cases'!$K$4:$K$12,"Credit Collateral",'Stress Cases'!$L$4:$L$12,A7,'Stress Cases'!$I$4:$I$12,"Failed under stress")>0,"Failed under linked stress case",IF(COUNTIFS('Stress Cases'!$K$4:$K$12,"Credit Collateral",'Stress Cases'!$L$4:$L$12,A7,'Stress Cases'!$I$4:$I$12,"Unresolved*")>0,"Unresolved, linked stress missing",IF(OR(F7="",H7=""),"Unresolved, evidence missing",IF(AND(H7>0,S7=""),"Unresolved, resource origin missing",IF(OR(ISNUMBER(SEARCH("No evidence",Q7)),ISNUMBER(SEARCH("Missing substantive",Q7)),ISNUMBER(SEARCH("Contested substantive",Q7))),"Unresolved, evidence missing",IF(AND(R7="Yes",S7<>"Public-welfare transfer"),"Unresolved, cross-ledger transfer missing",IF(I7<0,"Failed under stress",IF(AND(J7<>"",J7<0),"Conditional pass","Pass")))))))))))))) | L7: Missing | Q7: =IF(A7="","",IF(P7="","No evidence ID",IFERROR(IF(VLOOKUP(P7,'Evidence Register'!A:M,11,FALSE)="Missing","Missing substantive evidence",IF(VLOOKUP(P7,'Evidence Register'!A:M,11,FALSE)="Contested","Contested substantive evidence",IF(VLOOKUP(P7,'Evidence Register'!A:M,10,FALSE)="Pinned","Pinned evidence",IF(VLOOKUP(P7,'Evidence Register'!A:M,10,FALSE)="Confidential-reviewable","Reviewable evidence","Pin issue: "&VLOOKUP(P7,'Evidence Register'!A:M,10,FALSE))))),"Missing evidence ID"))) | R7: =IF(A7="","",IF(OR(H7="",H7=0),"",IF(S7="","Missing origin",IF(S7<>"Credit Collateral","Yes","No"))))
A8: Narrative-only pledge | B8: Unknown | C8: Settlement resource | D8: Narrative-only promise | E8: screening band | I8: =IF(OR(A8="",B8<>"Triggered",F8="",H8=""),"",H8-F8) | J8: =IF(OR(A8="",B8<>"Triggered",G8="",H8=""),"",H8-G8) | K8: =IF(A8="","",IF(B8="Not applicable","Not applicable",IF(B8="Not triggered","Not triggered",IF(B8="Unknown","Unresolved, evidence missing",IF(L8="Confidential-reviewable","Unresolved, confidential but reviewable",IF(L8="Contested","Unresolved, contested",IF(COUNTIFS('Stress Cases'!$K$4:$K$12,"Credit Collateral",'Stress Cases'!$L$4:$L$12,A8,'Stress Cases'!$I$4:$I$12,"Failed under stress")>0,"Failed under linked stress case",IF(COUNTIFS('Stress Cases'!$K$4:$K$12,"Credit Collateral",'Stress Cases'!$L$4:$L$12,A8,'Stress Cases'!$I$4:$I$12,"Unresolved*")>0,"Unresolved, linked stress missing",IF(OR(F8="",H8=""),"Unresolved, evidence missing",IF(AND(H8>0,S8=""),"Unresolved, resource origin missing",IF(OR(ISNUMBER(SEARCH("No evidence",Q8)),ISNUMBER(SEARCH("Missing substantive",Q8)),ISNUMBER(SEARCH("Contested substantive",Q8))),"Unresolved, evidence missing",IF(AND(R8="Yes",S8<>"Public-welfare transfer"),"Unresolved, cross-ledger transfer missing",IF(I8<0,"Failed under stress",IF(AND(J8<>"",J8<0),"Conditional pass","Pass")))))))))))))) | L8: Missing | Q8: =IF(A8="","",IF(P8="","No evidence ID",IFERROR(IF(VLOOKUP(P8,'Evidence Register'!A:M,11,FALSE)="Missing","Missing substantive evidence",IF(VLOOKUP(P8,'Evidence Register'!A:M,11,FALSE)="Contested","Contested substantive evidence",IF(VLOOKUP(P8,'Evidence Register'!A:M,10,FALSE)="Pinned","Pinned evidence",IF(VLOOKUP(P8,'Evidence Register'!A:M,10,FALSE)="Confidential-reviewable","Reviewable evidence","Pin issue: "&VLOOKUP(P8,'Evidence Register'!A:M,10,FALSE))))),"Missing evidence ID"))) | R8: =IF(A8="","",IF(OR(H8="",H8=0),"",IF(S8="","Missing origin",IF(S8<>"Credit Collateral","Yes","No"))))
I9: =IF(OR(A9="",B9<>"Triggered",F9="",H9=""),"",H9-F9) | J9: =IF(OR(A9="",B9<>"Triggered",G9="",H9=""),"",H9-G9) | K9: =IF(A9="","",IF(B9="Not applicable","Not applicable",IF(B9="Not triggered","Not triggered",IF(B9="Unknown","Unresolved, evidence missing",IF(L9="Confidential-reviewable","Unresolved, confidential but reviewable",IF(L9="Contested","Unresolved, contested",IF(COUNTIFS('Stress Cases'!$K$4:$K$12,"Credit Collateral",'Stress Cases'!$L$4:$L$12,A9,'Stress Cases'!$I$4:$I$12,"Failed under stress")>0,"Failed under linked stress case",IF(COUNTIFS('Stress Cases'!$K$4:$K$12,"Credit Collateral",'Stress Cases'!$L$4:$L$12,A9,'Stress Cases'!$I$4:$I$12,"Unresolved*")>0,"Unresolved, linked stress missing",IF(OR(F9="",H9=""),"Unresolved, evidence missing",IF(AND(H9>0,S9=""),"Unresolved, resource origin missing",IF(OR(ISNUMBER(SEARCH("No evidence",Q9)),ISNUMBER(SEARCH("Missing substantive",Q9)),ISNUMBER(SEARCH("Contested substantive",Q9))),"Unresolved, evidence missing",IF(AND(R9="Yes",S9<>"Public-welfare transfer"),"Unresolved, cross-ledger transfer missing",IF(I9<0,"Failed under stress",IF(AND(J9<>"",J9<0),"Conditional pass","Pass")))))))))))))) | Q9: =IF(A9="","",IF(P9="","No evidence ID",IFERROR(IF(VLOOKUP(P9,'Evidence Register'!A:M,11,FALSE)="Missing","Missing substantive evidence",IF(VLOOKUP(P9,'Evidence Register'!A:M,11,FALSE)="Contested","Contested substantive evidence",IF(VLOOKUP(P9,'Evidence Register'!A:M,10,FALSE)="Pinned","Pinned evidence",IF(VLOOKUP(P9,'Evidence Register'!A:M,10,FALSE)="Confidential-reviewable","Reviewable evidence","Pin issue: "&VLOOKUP(P9,'Evidence Register'!A:M,10,FALSE))))),"Missing evidence ID"))) | R9: =IF(A9="","",IF(OR(H9="",H9=0),"",IF(S9="","Missing origin",IF(S9<>"Credit Collateral","Yes","No"))))
I10: =IF(OR(A10="",B10<>"Triggered",F10="",H10=""),"",H10-F10) | J10: =IF(OR(A10="",B10<>"Triggered",G10="",H10=""),"",H10-G10) | K10: =IF(A10="","",IF(B10="Not applicable","Not applicable",IF(B10="Not triggered","Not triggered",IF(B10="Unknown","Unresolved, evidence missing",IF(L10="Confidential-reviewable","Unresolved, confidential but reviewable",IF(L10="Contested","Unresolved, contested",IF(COUNTIFS('Stress Cases'!$K$4:$K$12,"Credit Collateral",'Stress Cases'!$L$4:$L$12,A10,'Stress Cases'!$I$4:$I$12,"Failed under stress")>0,"Failed under linked stress case",IF(COUNTIFS('Stress Cases'!$K$4:$K$12,"Credit Collateral",'Stress Cases'!$L$4:$L$12,A10,'Stress Cases'!$I$4:$I$12,"Unresolved*")>0,"Unresolved, linked stress missing",IF(OR(F10="",H10=""),"Unresolved, evidence missing",IF(AND(H10>0,S10=""),"Unresolved, resource origin missing",IF(OR(ISNUMBER(SEARCH("No evidence",Q10)),ISNUMBER(SEARCH("Missing substantive",Q10)),ISNUMBER(SEARCH("Contested substantive",Q10))),"Unresolved, evidence missing",IF(AND(R10="Yes",S10<>"Public-welfare transfer"),"Unresolved, cross-ledger transfer missing",IF(I10<0,"Failed under stress",IF(AND(J10<>"",J10<0),"Conditional pass","Pass")))))))))))))) | Q10: =IF(A10="","",IF(P10="","No evidence ID",IFERROR(IF(VLOOKUP(P10,'Evidence Register'!A:M,11,FALSE)="Missing","Missing substantive evidence",IF(VLOOKUP(P10,'Evidence Register'!A:M,11,FALSE)="Contested","Contested substantive evidence",IF(VLOOKUP(P10,'Evidence Register'!A:M,10,FALSE)="Pinned","Pinned evidence",IF(VLOOKUP(P10,'Evidence Register'!A:M,10,FALSE)="Confidential-reviewable","Reviewable evidence","Pin issue: "&VLOOKUP(P10,'Evidence Register'!A:M,10,FALSE))))),"Missing evidence ID"))) | R10: =IF(A10="","",IF(OR(H10="",H10=0),"",IF(S10="","Missing origin",IF(S10<>"Credit Collateral","Yes","No"))))
I11: =IF(OR(A11="",B11<>"Triggered",F11="",H11=""),"",H11-F11) | J11: =IF(OR(A11="",B11<>"Triggered",G11="",H11=""),"",H11-G11) | K11: =IF(A11="","",IF(B11="Not applicable","Not applicable",IF(B11="Not triggered","Not triggered",IF(B11="Unknown","Unresolved, evidence missing",IF(L11="Confidential-reviewable","Unresolved, confidential but reviewable",IF(L11="Contested","Unresolved, contested",IF(COUNTIFS('Stress Cases'!$K$4:$K$12,"Credit Collateral",'Stress Cases'!$L$4:$L$12,A11,'Stress Cases'!$I$4:$I$12,"Failed under stress")>0,"Failed under linked stress case",IF(COUNTIFS('Stress Cases'!$K$4:$K$12,"Credit Collateral",'Stress Cases'!$L$4:$L$12,A11,'Stress Cases'!$I$4:$I$12,"Unresolved*")>0,"Unresolved, linked stress missing",IF(OR(F11="",H11=""),"Unresolved, evidence missing",IF(AND(H11>0,S11=""),"Unresolved, resource origin missing",IF(OR(ISNUMBER(SEARCH("No evidence",Q11)),ISNUMBER(SEARCH("Missing substantive",Q11)),ISNUMBER(SEARCH("Contested substantive",Q11))),"Unresolved, evidence missing",IF(AND(R11="Yes",S11<>"Public-welfare transfer"),"Unresolved, cross-ledger transfer missing",IF(I11<0,"Failed under stress",IF(AND(J11<>"",J11<0),"Conditional pass","Pass")))))))))))))) | Q11: =IF(A11="","",IF(P11="","No evidence ID",IFERROR(IF(VLOOKUP(P11,'Evidence Register'!A:M,11,FALSE)="Missing","Missing substantive evidence",IF(VLOOKUP(P11,'Evidence Register'!A:M,11,FALSE)="Contested","Contested substantive evidence",IF(VLOOKUP(P11,'Evidence Register'!A:M,10,FALSE)="Pinned","Pinned evidence",IF(VLOOKUP(P11,'Evidence Register'!A:M,10,FALSE)="Confidential-reviewable","Reviewable evidence","Pin issue: "&VLOOKUP(P11,'Evidence Register'!A:M,10,FALSE))))),"Missing evidence ID"))) | R11: =IF(A11="","",IF(OR(H11="",H11=0),"",IF(S11="","Missing origin",IF(S11<>"Credit Collateral","Yes","No"))))
I12: =IF(OR(A12="",B12<>"Triggered",F12="",H12=""),"",H12-F12) | J12: =IF(OR(A12="",B12<>"Triggered",G12="",H12=""),"",H12-G12) | K12: =IF(A12="","",IF(B12="Not applicable","Not applicable",IF(B12="Not triggered","Not triggered",IF(B12="Unknown","Unresolved, evidence missing",IF(L12="Confidential-reviewable","Unresolved, confidential but reviewable",IF(L12="Contested","Unresolved, contested",IF(COUNTIFS('Stress Cases'!$K$4:$K$12,"Credit Collateral",'Stress Cases'!$L$4:$L$12,A12,'Stress Cases'!$I$4:$I$12,"Failed under stress")>0,"Failed under linked stress case",IF(COUNTIFS('Stress Cases'!$K$4:$K$12,"Credit Collateral",'Stress Cases'!$L$4:$L$12,A12,'Stress Cases'!$I$4:$I$12,"Unresolved*")>0,"Unresolved, linked stress missing",IF(OR(F12="",H12=""),"Unresolved, evidence missing",IF(AND(H12>0,S12=""),"Unresolved, resource origin missing",IF(OR(ISNUMBER(SEARCH("No evidence",Q12)),ISNUMBER(SEARCH("Missing substantive",Q12)),ISNUMBER(SEARCH("Contested substantive",Q12))),"Unresolved, evidence missing",IF(AND(R12="Yes",S12<>"Public-welfare transfer"),"Unresolved, cross-ledger transfer missing",IF(I12<0,"Failed under stress",IF(AND(J12<>"",J12<0),"Conditional pass","Pass")))))))))))))) | Q12: =IF(A12="","",IF(P12="","No evidence ID",IFERROR(IF(VLOOKUP(P12,'Evidence Register'!A:M,11,FALSE)="Missing","Missing substantive evidence",IF(VLOOKUP(P12,'Evidence Register'!A:M,11,FALSE)="Contested","Contested substantive evidence",IF(VLOOKUP(P12,'Evidence Register'!A:M,10,FALSE)="Pinned","Pinned evidence",IF(VLOOKUP(P12,'Evidence Register'!A:M,10,FALSE)="Confidential-reviewable","Reviewable evidence","Pin issue: "&VLOOKUP(P12,'Evidence Register'!A:M,10,FALSE))))),"Missing evidence ID"))) | R12: =IF(A12="","",IF(OR(H12="",H12=0),"",IF(S12="","Missing origin",IF(S12<>"Credit Collateral","Yes","No"))))
I13: =IF(OR(A13="",B13<>"Triggered",F13="",H13=""),"",H13-F13) | J13: =IF(OR(A13="",B13<>"Triggered",G13="",H13=""),"",H13-G13) | K13: =IF(A13="","",IF(B13="Not applicable","Not applicable",IF(B13="Not triggered","Not triggered",IF(B13="Unknown","Unresolved, evidence missing",IF(L13="Confidential-reviewable","Unresolved, confidential but reviewable",IF(L13="Contested","Unresolved, contested",IF(COUNTIFS('Stress Cases'!$K$4:$K$12,"Credit Collateral",'Stress Cases'!$L$4:$L$12,A13,'Stress Cases'!$I$4:$I$12,"Failed under stress")>0,"Failed under linked stress case",IF(COUNTIFS('Stress Cases'!$K$4:$K$12,"Credit Collateral",'Stress Cases'!$L$4:$L$12,A13,'Stress Cases'!$I$4:$I$12,"Unresolved*")>0,"Unresolved, linked stress missing",IF(OR(F13="",H13=""),"Unresolved, evidence missing",IF(AND(H13>0,S13=""),"Unresolved, resource origin missing",IF(OR(ISNUMBER(SEARCH("No evidence",Q13)),ISNUMBER(SEARCH("Missing substantive",Q13)),ISNUMBER(SEARCH("Contested substantive",Q13))),"Unresolved, evidence missing",IF(AND(R13="Yes",S13<>"Public-welfare transfer"),"Unresolved, cross-ledger transfer missing",IF(I13<0,"Failed under stress",IF(AND(J13<>"",J13<0),"Conditional pass","Pass")))))))))))))) | Q13: =IF(A13="","",IF(P13="","No evidence ID",IFERROR(IF(VLOOKUP(P13,'Evidence Register'!A:M,11,FALSE)="Missing","Missing substantive evidence",IF(VLOOKUP(P13,'Evidence Register'!A:M,11,FALSE)="Contested","Contested substantive evidence",IF(VLOOKUP(P13,'Evidence Register'!A:M,10,FALSE)="Pinned","Pinned evidence",IF(VLOOKUP(P13,'Evidence Register'!A:M,10,FALSE)="Confidential-reviewable","Reviewable evidence","Pin issue: "&VLOOKUP(P13,'Evidence Register'!A:M,10,FALSE))))),"Missing evidence ID"))) | R13: =IF(A13="","",IF(OR(H13="",H13=0),"",IF(S13="","Missing origin",IF(S13<>"Credit Collateral","Yes","No"))))
I14: =IF(OR(A14="",B14<>"Triggered",F14="",H14=""),"",H14-F14) | J14: =IF(OR(A14="",B14<>"Triggered",G14="",H14=""),"",H14-G14) | K14: =IF(A14="","",IF(B14="Not applicable","Not applicable",IF(B14="Not triggered","Not triggered",IF(B14="Unknown","Unresolved, evidence missing",IF(L14="Confidential-reviewable","Unresolved, confidential but reviewable",IF(L14="Contested","Unresolved, contested",IF(COUNTIFS('Stress Cases'!$K$4:$K$12,"Credit Collateral",'Stress Cases'!$L$4:$L$12,A14,'Stress Cases'!$I$4:$I$12,"Failed under stress")>0,"Failed under linked stress case",IF(COUNTIFS('Stress Cases'!$K$4:$K$12,"Credit Collateral",'Stress Cases'!$L$4:$L$12,A14,'Stress Cases'!$I$4:$I$12,"Unresolved*")>0,"Unresolved, linked stress missing",IF(OR(F14="",H14=""),"Unresolved, evidence missing",IF(AND(H14>0,S14=""),"Unresolved, resource origin missing",IF(OR(ISNUMBER(SEARCH("No evidence",Q14)),ISNUMBER(SEARCH("Missing substantive",Q14)),ISNUMBER(SEARCH("Contested substantive",Q14))),"Unresolved, evidence missing",IF(AND(R14="Yes",S14<>"Public-welfare transfer"),"Unresolved, cross-ledger transfer missing",IF(I14<0,"Failed under stress",IF(AND(J14<>"",J14<0),"Conditional pass","Pass")))))))))))))) | Q14: =IF(A14="","",IF(P14="","No evidence ID",IFERROR(IF(VLOOKUP(P14,'Evidence Register'!A:M,11,FALSE)="Missing","Missing substantive evidence",IF(VLOOKUP(P14,'Evidence Register'!A:M,11,FALSE)="Contested","Contested substantive evidence",IF(VLOOKUP(P14,'Evidence Register'!A:M,10,FALSE)="Pinned","Pinned evidence",IF(VLOOKUP(P14,'Evidence Register'!A:M,10,FALSE)="Confidential-reviewable","Reviewable evidence","Pin issue: "&VLOOKUP(P14,'Evidence Register'!A:M,10,FALSE))))),"Missing evidence ID"))) | R14: =IF(A14="","",IF(OR(H14="",H14=0),"",IF(S14="","Missing origin",IF(S14<>"Credit Collateral","Yes","No"))))
I15: =IF(OR(A15="",B15<>"Triggered",F15="",H15=""),"",H15-F15) | J15: =IF(OR(A15="",B15<>"Triggered",G15="",H15=""),"",H15-G15) | K15: =IF(A15="","",IF(B15="Not applicable","Not applicable",IF(B15="Not triggered","Not triggered",IF(B15="Unknown","Unresolved, evidence missing",IF(L15="Confidential-reviewable","Unresolved, confidential but reviewable",IF(L15="Contested","Unresolved, contested",IF(COUNTIFS('Stress Cases'!$K$4:$K$12,"Credit Collateral",'Stress Cases'!$L$4:$L$12,A15,'Stress Cases'!$I$4:$I$12,"Failed under stress")>0,"Failed under linked stress case",IF(COUNTIFS('Stress Cases'!$K$4:$K$12,"Credit Collateral",'Stress Cases'!$L$4:$L$12,A15,'Stress Cases'!$I$4:$I$12,"Unresolved*")>0,"Unresolved, linked stress missing",IF(OR(F15="",H15=""),"Unresolved, evidence missing",IF(AND(H15>0,S15=""),"Unresolved, resource origin missing",IF(OR(ISNUMBER(SEARCH("No evidence",Q15)),ISNUMBER(SEARCH("Missing substantive",Q15)),ISNUMBER(SEARCH("Contested substantive",Q15))),"Unresolved, evidence missing",IF(AND(R15="Yes",S15<>"Public-welfare transfer"),"Unresolved, cross-ledger transfer missing",IF(I15<0,"Failed under stress",IF(AND(J15<>"",J15<0),"Conditional pass","Pass")))))))))))))) | Q15: =IF(A15="","",IF(P15="","No evidence ID",IFERROR(IF(VLOOKUP(P15,'Evidence Register'!A:M,11,FALSE)="Missing","Missing substantive evidence",IF(VLOOKUP(P15,'Evidence Register'!A:M,11,FALSE)="Contested","Contested substantive evidence",IF(VLOOKUP(P15,'Evidence Register'!A:M,10,FALSE)="Pinned","Pinned evidence",IF(VLOOKUP(P15,'Evidence Register'!A:M,10,FALSE)="Confidential-reviewable","Reviewable evidence","Pin issue: "&VLOOKUP(P15,'Evidence Register'!A:M,10,FALSE))))),"Missing evidence ID"))) | R15: =IF(A15="","",IF(OR(H15="",H15=0),"",IF(S15="","Missing origin",IF(S15<>"Credit Collateral","Yes","No"))))
I16: =IF(OR(A16="",B16<>"Triggered",F16="",H16=""),"",H16-F16) | J16: =IF(OR(A16="",B16<>"Triggered",G16="",H16=""),"",H16-G16) | K16: =IF(A16="","",IF(B16="Not applicable","Not applicable",IF(B16="Not triggered","Not triggered",IF(B16="Unknown","Unresolved, evidence missing",IF(L16="Confidential-reviewable","Unresolved, confidential but reviewable",IF(L16="Contested","Unresolved, contested",IF(COUNTIFS('Stress Cases'!$K$4:$K$12,"Credit Collateral",'Stress Cases'!$L$4:$L$12,A16,'Stress Cases'!$I$4:$I$12,"Failed under stress")>0,"Failed under linked stress case",IF(COUNTIFS('Stress Cases'!$K$4:$K$12,"Credit Collateral",'Stress Cases'!$L$4:$L$12,A16,'Stress Cases'!$I$4:$I$12,"Unresolved*")>0,"Unresolved, linked stress missing",IF(OR(F16="",H16=""),"Unresolved, evidence missing",IF(AND(H16>0,S16=""),"Unresolved, resource origin missing",IF(OR(ISNUMBER(SEARCH("No evidence",Q16)),ISNUMBER(SEARCH("Missing substantive",Q16)),ISNUMBER(SEARCH("Contested substantive",Q16))),"Unresolved, evidence missing",IF(AND(R16="Yes",S16<>"Public-welfare transfer"),"Unresolved, cross-ledger transfer missing",IF(I16<0,"Failed under stress",IF(AND(J16<>"",J16<0),"Conditional pass","Pass")))))))))))))) | Q16: =IF(A16="","",IF(P16="","No evidence ID",IFERROR(IF(VLOOKUP(P16,'Evidence Register'!A:M,11,FALSE)="Missing","Missing substantive evidence",IF(VLOOKUP(P16,'Evidence Register'!A:M,11,FALSE)="Contested","Contested substantive evidence",IF(VLOOKUP(P16,'Evidence Register'!A:M,10,FALSE)="Pinned","Pinned evidence",IF(VLOOKUP(P16,'Evidence Register'!A:M,10,FALSE)="Confidential-reviewable","Reviewable evidence","Pin issue: "&VLOOKUP(P16,'Evidence Register'!A:M,10,FALSE))))),"Missing evidence ID"))) | R16: =IF(A16="","",IF(OR(H16="",H16=0),"",IF(S16="","Missing origin",IF(S16<>"Credit Collateral","Yes","No"))))
I17: =IF(OR(A17="",B17<>"Triggered",F17="",H17=""),"",H17-F17) | J17: =IF(OR(A17="",B17<>"Triggered",G17="",H17=""),"",H17-G17) | K17: =IF(A17="","",IF(B17="Not applicable","Not applicable",IF(B17="Not triggered","Not triggered",IF(B17="Unknown","Unresolved, evidence missing",IF(L17="Confidential-reviewable","Unresolved, confidential but reviewable",IF(L17="Contested","Unresolved, contested",IF(COUNTIFS('Stress Cases'!$K$4:$K$12,"Credit Collateral",'Stress Cases'!$L$4:$L$12,A17,'Stress Cases'!$I$4:$I$12,"Failed under stress")>0,"Failed under linked stress case",IF(COUNTIFS('Stress Cases'!$K$4:$K$12,"Credit Collateral",'Stress Cases'!$L$4:$L$12,A17,'Stress Cases'!$I$4:$I$12,"Unresolved*")>0,"Unresolved, linked stress missing",IF(OR(F17="",H17=""),"Unresolved, evidence missing",IF(AND(H17>0,S17=""),"Unresolved, resource origin missing",IF(OR(ISNUMBER(SEARCH("No evidence",Q17)),ISNUMBER(SEARCH("Missing substantive",Q17)),ISNUMBER(SEARCH("Contested substantive",Q17))),"Unresolved, evidence missing",IF(AND(R17="Yes",S17<>"Public-welfare transfer"),"Unresolved, cross-ledger transfer missing",IF(I17<0,"Failed under stress",IF(AND(J17<>"",J17<0),"Conditional pass","Pass")))))))))))))) | Q17: =IF(A17="","",IF(P17="","No evidence ID",IFERROR(IF(VLOOKUP(P17,'Evidence Register'!A:M,11,FALSE)="Missing","Missing substantive evidence",IF(VLOOKUP(P17,'Evidence Register'!A:M,11,FALSE)="Contested","Contested substantive evidence",IF(VLOOKUP(P17,'Evidence Register'!A:M,10,FALSE)="Pinned","Pinned evidence",IF(VLOOKUP(P17,'Evidence Register'!A:M,10,FALSE)="Confidential-reviewable","Reviewable evidence","Pin issue: "&VLOOKUP(P17,'Evidence Register'!A:M,10,FALSE))))),"Missing evidence ID"))) | R17: =IF(A17="","",IF(OR(H17="",H17=0),"",IF(S17="","Missing origin",IF(S17<>"Credit Collateral","Yes","No"))))
I18: =IF(OR(A18="",B18<>"Triggered",F18="",H18=""),"",H18-F18) | J18: =IF(OR(A18="",B18<>"Triggered",G18="",H18=""),"",H18-G18) | K18: =IF(A18="","",IF(B18="Not applicable","Not applicable",IF(B18="Not triggered","Not triggered",IF(B18="Unknown","Unresolved, evidence missing",IF(L18="Confidential-reviewable","Unresolved, confidential but reviewable",IF(L18="Contested","Unresolved, contested",IF(COUNTIFS('Stress Cases'!$K$4:$K$12,"Credit Collateral",'Stress Cases'!$L$4:$L$12,A18,'Stress Cases'!$I$4:$I$12,"Failed under stress")>0,"Failed under linked stress case",IF(COUNTIFS('Stress Cases'!$K$4:$K$12,"Credit Collateral",'Stress Cases'!$L$4:$L$12,A18,'Stress Cases'!$I$4:$I$12,"Unresolved*")>0,"Unresolved, linked stress missing",IF(OR(F18="",H18=""),"Unresolved, evidence missing",IF(AND(H18>0,S18=""),"Unresolved, resource origin missing",IF(OR(ISNUMBER(SEARCH("No evidence",Q18)),ISNUMBER(SEARCH("Missing substantive",Q18)),ISNUMBER(SEARCH("Contested substantive",Q18))),"Unresolved, evidence missing",IF(AND(R18="Yes",S18<>"Public-welfare transfer"),"Unresolved, cross-ledger transfer missing",IF(I18<0,"Failed under stress",IF(AND(J18<>"",J18<0),"Conditional pass","Pass")))))))))))))) | Q18: =IF(A18="","",IF(P18="","No evidence ID",IFERROR(IF(VLOOKUP(P18,'Evidence Register'!A:M,11,FALSE)="Missing","Missing substantive evidence",IF(VLOOKUP(P18,'Evidence Register'!A:M,11,FALSE)="Contested","Contested substantive evidence",IF(VLOOKUP(P18,'Evidence Register'!A:M,10,FALSE)="Pinned","Pinned evidence",IF(VLOOKUP(P18,'Evidence Register'!A:M,10,FALSE)="Confidential-reviewable","Reviewable evidence","Pin issue: "&VLOOKUP(P18,'Evidence Register'!A:M,10,FALSE))))),"Missing evidence ID"))) | R18: =IF(A18="","",IF(OR(H18="",H18=0),"",IF(S18="","Missing origin",IF(S18<>"Credit Collateral","Yes","No"))))
I19: =IF(OR(A19="",B19<>"Triggered",F19="",H19=""),"",H19-F19) | J19: =IF(OR(A19="",B19<>"Triggered",G19="",H19=""),"",H19-G19) | K19: =IF(A19="","",IF(B19="Not applicable","Not applicable",IF(B19="Not triggered","Not triggered",IF(B19="Unknown","Unresolved, evidence missing",IF(L19="Confidential-reviewable","Unresolved, confidential but reviewable",IF(L19="Contested","Unresolved, contested",IF(COUNTIFS('Stress Cases'!$K$4:$K$12,"Credit Collateral",'Stress Cases'!$L$4:$L$12,A19,'Stress Cases'!$I$4:$I$12,"Failed under stress")>0,"Failed under linked stress case",IF(COUNTIFS('Stress Cases'!$K$4:$K$12,"Credit Collateral",'Stress Cases'!$L$4:$L$12,A19,'Stress Cases'!$I$4:$I$12,"Unresolved*")>0,"Unresolved, linked stress missing",IF(OR(F19="",H19=""),"Unresolved, evidence missing",IF(AND(H19>0,S19=""),"Unresolved, resource origin missing",IF(OR(ISNUMBER(SEARCH("No evidence",Q19)),ISNUMBER(SEARCH("Missing substantive",Q19)),ISNUMBER(SEARCH("Contested substantive",Q19))),"Unresolved, evidence missing",IF(AND(R19="Yes",S19<>"Public-welfare transfer"),"Unresolved, cross-ledger transfer missing",IF(I19<0,"Failed under stress",IF(AND(J19<>"",J19<0),"Conditional pass","Pass")))))))))))))) | Q19: =IF(A19="","",IF(P19="","No evidence ID",IFERROR(IF(VLOOKUP(P19,'Evidence Register'!A:M,11,FALSE)="Missing","Missing substantive evidence",IF(VLOOKUP(P19,'Evidence Register'!A:M,11,FALSE)="Contested","Contested substantive evidence",IF(VLOOKUP(P19,'Evidence Register'!A:M,10,FALSE)="Pinned","Pinned evidence",IF(VLOOKUP(P19,'Evidence Register'!A:M,10,FALSE)="Confidential-reviewable","Reviewable evidence","Pin issue: "&VLOOKUP(P19,'Evidence Register'!A:M,10,FALSE))))),"Missing evidence ID"))) | R19: =IF(A19="","",IF(OR(H19="",H19=0),"",IF(S19="","Missing origin",IF(S19<>"Credit Collateral","Yes","No"))))
I20: =IF(OR(A20="",B20<>"Triggered",F20="",H20=""),"",H20-F20) | J20: =IF(OR(A20="",B20<>"Triggered",G20="",H20=""),"",H20-G20) | K20: =IF(A20="","",IF(B20="Not applicable","Not applicable",IF(B20="Not triggered","Not triggered",IF(B20="Unknown","Unresolved, evidence missing",IF(L20="Confidential-reviewable","Unresolved, confidential but reviewable",IF(L20="Contested","Unresolved, contested",IF(COUNTIFS('Stress Cases'!$K$4:$K$12,"Credit Collateral",'Stress Cases'!$L$4:$L$12,A20,'Stress Cases'!$I$4:$I$12,"Failed under stress")>0,"Failed under linked stress case",IF(COUNTIFS('Stress Cases'!$K$4:$K$12,"Credit Collateral",'Stress Cases'!$L$4:$L$12,A20,'Stress Cases'!$I$4:$I$12,"Unresolved*")>0,"Unresolved, linked stress missing",IF(OR(F20="",H20=""),"Unresolved, evidence missing",IF(AND(H20>0,S20=""),"Unresolved, resource origin missing",IF(OR(ISNUMBER(SEARCH("No evidence",Q20)),ISNUMBER(SEARCH("Missing substantive",Q20)),ISNUMBER(SEARCH("Contested substantive",Q20))),"Unresolved, evidence missing",IF(AND(R20="Yes",S20<>"Public-welfare transfer"),"Unresolved, cross-ledger transfer missing",IF(I20<0,"Failed under stress",IF(AND(J20<>"",J20<0),"Conditional pass","Pass")))))))))))))) | Q20: =IF(A20="","",IF(P20="","No evidence ID",IFERROR(IF(VLOOKUP(P20,'Evidence Register'!A:M,11,FALSE)="Missing","Missing substantive evidence",IF(VLOOKUP(P20,'Evidence Register'!A:M,11,FALSE)="Contested","Contested substantive evidence",IF(VLOOKUP(P20,'Evidence Register'!A:M,10,FALSE)="Pinned","Pinned evidence",IF(VLOOKUP(P20,'Evidence Register'!A:M,10,FALSE)="Confidential-reviewable","Reviewable evidence","Pin issue: "&VLOOKUP(P20,'Evidence Register'!A:M,10,FALSE))))),"Missing evidence ID"))) | R20: =IF(A20="","",IF(OR(H20="",H20=0),"",IF(S20="","Missing origin",IF(S20<>"Credit Collateral","Yes","No"))))
I21: =IF(OR(A21="",B21<>"Triggered",F21="",H21=""),"",H21-F21) | J21: =IF(OR(A21="",B21<>"Triggered",G21="",H21=""),"",H21-G21) | K21: =IF(A21="","",IF(B21="Not applicable","Not applicable",IF(B21="Not triggered","Not triggered",IF(B21="Unknown","Unresolved, evidence missing",IF(L21="Confidential-reviewable","Unresolved, confidential but reviewable",IF(L21="Contested","Unresolved, contested",IF(COUNTIFS('Stress Cases'!$K$4:$K$12,"Credit Collateral",'Stress Cases'!$L$4:$L$12,A21,'Stress Cases'!$I$4:$I$12,"Failed under stress")>0,"Failed under linked stress case",IF(COUNTIFS('Stress Cases'!$K$4:$K$12,"Credit Collateral",'Stress Cases'!$L$4:$L$12,A21,'Stress Cases'!$I$4:$I$12,"Unresolved*")>0,"Unresolved, linked stress missing",IF(OR(F21="",H21=""),"Unresolved, evidence missing",IF(AND(H21>0,S21=""),"Unresolved, resource origin missing",IF(OR(ISNUMBER(SEARCH("No evidence",Q21)),ISNUMBER(SEARCH("Missing substantive",Q21)),ISNUMBER(SEARCH("Contested substantive",Q21))),"Unresolved, evidence missing",IF(AND(R21="Yes",S21<>"Public-welfare transfer"),"Unresolved, cross-ledger transfer missing",IF(I21<0,"Failed under stress",IF(AND(J21<>"",J21<0),"Conditional pass","Pass")))))))))))))) | Q21: =IF(A21="","",IF(P21="","No evidence ID",IFERROR(IF(VLOOKUP(P21,'Evidence Register'!A:M,11,FALSE)="Missing","Missing substantive evidence",IF(VLOOKUP(P21,'Evidence Register'!A:M,11,FALSE)="Contested","Contested substantive evidence",IF(VLOOKUP(P21,'Evidence Register'!A:M,10,FALSE)="Pinned","Pinned evidence",IF(VLOOKUP(P21,'Evidence Register'!A:M,10,FALSE)="Confidential-reviewable","Reviewable evidence","Pin issue: "&VLOOKUP(P21,'Evidence Register'!A:M,10,FALSE))))),"Missing evidence ID"))) | R21: =IF(A21="","",IF(OR(H21="",H21=0),"",IF(S21="","Missing origin",IF(S21<>"Credit Collateral","Yes","No"))))
A22: Total / dashboard line | F22: =IF(COUNTIF(B4:B21,"Triggered")=0,"",SUM(F4:F21)) | G22: =IF(COUNTIF(B4:B21,"Triggered")=0,"",IF(COUNT(G4:G21)=0,"",SUM(G4:G21))) | H22: =IF(COUNTIF(B4:B21,"Triggered")=0,"",SUM(H4:H21)) | I22: =IF(F22="","",H22-F22) | J22: =IF(OR(G22="",H22=""),"",H22-G22) | K22: =IF(COUNTIF(B4:B21,"Triggered")=0,"No entries yet",IF(COUNTIF(K4:K21,"*Failed*")>0,"Failed under stress",IF(COUNTIF(K4:K21,"Unresolved*")>0,"Unresolved",IF(COUNTIF(K4:K21,"Conditional pass")>0,"Conditional pass",IF(I22<0,"Failed under stress",IF(AND(J22<>"",J22<0),"Conditional pass","Pass")))))) | R22: =IF(OR(COUNTIFS(B4:B21,"Triggered",R4:R21,"Yes")>0,COUNTIFS(B4:B21,"Triggered",R4:R21,"Missing origin")>0),"Flag: cross-ledger or origin issue",IF(OR(COUNTIFS(B4:B21,"Triggered",Q4:Q21,"Missing evidence ID")>0,COUNTIFS(B4:B21,"Triggered",Q4:Q21,"Needs pin*")>0,COUNTIFS(B4:B21,"Triggered",Q4:Q21,"No evidence ID")>0),"Flag: evidence pin incomplete",""))

Sheet Distributional
A1: Distributional Ledger
A3: Question | B3: Affected group | C3: Materiality trigger | D3: Evidence | E3: Material? (Y/N/Unknown) | F3: Mitigation | G3: Residual claimant | H3: Evidence ID | I3: Status
A4: Low-income bill burden | C4: Bill impact materially raises energy burden or exceeds affordability threshold | E4: Unknown | I4: =IF(E4="Y",IF(F4="","Unresolved, mitigation missing","Conditional pass"),IF(E4="N","Pass","Unresolved, evidence missing"))
A5: Small business exposure | C5: Class allocation or demand-charge exposure materially increases | E5: Unknown | I5: =IF(E5="Y",IF(F5="","Unresolved, mitigation missing","Conditional pass"),IF(E5="N","Pass","Unresolved, evidence missing"))
A6: School-district fiscal effect | C6: Abatement/PILOT produces school revenue loss above budget/per-pupil threshold | E6: Unknown | I6: =IF(E6="Y",IF(F6="","Unresolved, mitigation missing","Conditional pass"),IF(E6="N","Pass","Unresolved, evidence missing"))
A7: Water users vs electric ratepayers | C7: Existing water users carry bond risk not covered by project minimum payment | E7: Unknown | I7: =IF(E7="Y",IF(F7="","Unresolved, mitigation missing","Conditional pass"),IF(E7="N","Pass","Unresolved, evidence missing"))
A8: Nearby residents | C8: Noise, emissions, transmission, traffic, or land-use burden reaches mitigation trigger | E8: Unknown | I8: =IF(E8="Y",IF(F8="","Unresolved, mitigation missing","Conditional pass"),IF(E8="N","Pass","Unresolved, evidence missing"))
A9: Municipal / co-op customers | C9: Wholesale pass-through or local board exposure affects members | E9: Unknown | I9: =IF(E9="Y",IF(F9="","Unresolved, mitigation missing","Conditional pass"),IF(E9="N","Pass","Unresolved, evidence missing"))
A10: Renters | C10: Renters face bill exposure without property-tax benefit | E10: Unknown | I10: =IF(E10="Y",IF(F10="","Unresolved, mitigation missing","Conditional pass"),IF(E10="N","Pass","Unresolved, evidence missing"))
A11: Procedural access | C11: Notice, language access, intervention funding, or protected review is missing | E11: Unknown | I11: =IF(E11="Y",IF(F11="","Unresolved, mitigation missing","Conditional pass"),IF(E11="N","Pass","Unresolved, evidence missing"))
A22: Dashboard line | I22: =IF(COUNTIF(I4:I11,"Unresolved*")>0,"Unresolved",IF(COUNTIF(I4:I11,"Conditional pass")>0,"Conditional pass",IF(COUNTIF(I4:I11,"Pass")>0,"Pass","No entries yet")))

Sheet Stress Cases
A1: Stress Cases
A3: Stress case | B3: Default required for | C3: Required? (auto) | D3: Exposure tested | E3: Settlement resource | F3: Evidence | G3: Gap | H3: Residual claimant | I3: Status | J3: Notes | K3: Affected ledger | L3: Linked ledger line
A4: Two-year delay | B4: Most greenfield / forecast-reliance projects | C4: =IF(OR('Trigger Screen'!C6="Y",'Trigger Screen'!C7="Y",'Trigger Screen'!C8="Y",ISNUMBER(SEARCH("speculative",'Project Profile'!B9))),"Required",IF(COUNTIF('Trigger Screen'!C4:C10,"Unknown")>0,"Check trigger","Optional")) | I4: =IF(C4="Required",IF(OR(D4="",E4="",G4="",K4="",L4=""),"Unresolved, evidence missing",IF(G4<0,"Failed under stress","Pass")),IF(C4="Check trigger","Check trigger unresolved","Not triggered"))
A5: 60 percent realized load | B5: All projects seeking rate recovery | C5: =IF(OR('Trigger Screen'!C6="Y",'Trigger Screen'!C8="Y"),"Required",IF(COUNTIF('Trigger Screen'!C4:C10,"Unknown")>0,"Check trigger","Optional")) | I5: =IF(C5="Required",IF(OR(D5="",E5="",G5="",K5="",L5=""),"Unresolved, evidence missing",IF(G5<0,"Failed under stress","Pass")),IF(C5="Check trigger","Check trigger unresolved","Not triggered"))
A6: Exit in year 5 | B6: Utility-owned assets / public debt | C6: =IF(OR('Trigger Screen'!C6="Y",'Trigger Screen'!C8="Y",'Trigger Screen'!C10="Y"),"Required",IF(COUNTIF('Trigger Screen'!C4:C10,"Unknown")>0,"Check trigger","Optional")) | I6: =IF(C6="Required",IF(OR(D6="",E6="",G6="",K6="",L6=""),"Unresolved, evidence missing",IF(G6<0,"Failed under stress","Pass")),IF(C6="Check trigger","Check trigger unresolved","Not triggered"))
A7: Credit downgrade or affiliate default | B7: Parent / affiliate support | C7: =IF(OR('Trigger Screen'!C9="Y",ISNUMBER(SEARCH("colo",'Project Profile'!B9)),ISNUMBER(SEARCH("affiliate",'Project Profile'!B9))),"Required",IF(COUNTIF('Trigger Screen'!C4:C10,"Unknown")>0,"Check trigger","Optional")) | I7: =IF(C7="Required",IF(OR(D7="",E7="",G7="",K7="",L7=""),"Unresolved, evidence missing",IF(G7<0,"Failed under stress","Pass")),IF(C7="Check trigger","Check trigger unresolved","Not triggered"))
A8: Regional capacity price shock | B8: RTO / capacity market regions | C8: =IF(OR('Project Profile'!B6<>"",'Trigger Screen'!C7="Y"),"Required",IF(COUNTIF('Trigger Screen'!C4:C10,"Unknown")>0,"Check trigger","Optional")) | I8: =IF(C8="Required",IF(OR(D8="",E8="",G8="",K8="",L8=""),"Unresolved, evidence missing",IF(G8<0,"Failed under stress","Pass")),IF(C8="Check trigger","Check trigger unresolved","Not triggered"))
A9: Curtailment failure | B9: Flexible / interruptible load | C9: =IF(ISNUMBER(SEARCH("flexible",'Project Profile'!B9)),"Required",IF(COUNTIF('Trigger Screen'!C4:C10,"Unknown")>0,"Check trigger","Optional")) | I9: =IF(C9="Required",IF(OR(D9="",E9="",G9="",K9="",L9=""),"Unresolved, evidence missing",IF(G9<0,"Failed under stress","Pass")),IF(C9="Check trigger","Check trigger unresolved","Not triggered"))
A10: Local infrastructure underuse | B10: Water / road / public debt | C10: =IF('Trigger Screen'!C10="Y","Required",IF(COUNTIF('Trigger Screen'!C4:C10,"Unknown")>0,"Check trigger","Optional")) | I10: =IF(C10="Required",IF(OR(D10="",E10="",G10="",K10="",L10=""),"Unresolved, evidence missing",IF(G10<0,"Failed under stress","Pass")),IF(C10="Check trigger","Check trigger unresolved","Not triggered"))
A11: Tenant departure | B11: Colocation / lease | C11: =IF(ISNUMBER(SEARCH("colo",'Project Profile'!B9)),"Required",IF(COUNTIF('Trigger Screen'!C4:C10,"Unknown")>0,"Check trigger","Optional")) | I11: =IF(C11="Required",IF(OR(D11="",E11="",G11="",K11="",L11=""),"Unresolved, evidence missing",IF(G11<0,"Failed under stress","Pass")),IF(C11="Check trigger","Check trigger unresolved","Not triggered"))
A12: Fuel / deliverability failure | B12: Behind-the-meter | C12: =IF(ISNUMBER(SEARCH("behind-the-meter",'Project Profile'!B9)),"Required",IF(COUNTIF('Trigger Screen'!C4:C10,"Unknown")>0,"Check trigger","Optional")) | I12: =IF(C12="Required",IF(OR(D12="",E12="",G12="",K12="",L12=""),"Unresolved, evidence missing",IF(G12<0,"Failed under stress","Pass")),IF(C12="Check trigger","Check trigger unresolved","Not triggered"))

Sheet Evidence Register
A1: Evidence Register / Citation Lockdown
A3: Evidence ID | B3: Ledger sheet | C3: Ledger line | D3: Claim | E3: Source URL / docket | F3: Evidence type | G3: Page / table / order pin | H3: Status as of date | I3: Used for | J3: Pin status | K3: Substantive evidence status | L3: Notes | M3: Confidence
A4: EV-001 | D4: IEA 415 / 945 TWh | E4: https://www.iea.org/reports/energy-and-ai/executive-summary | F4: Official report | G4: Executive summary sections on 2024 data-center demand and 2030 projection | H4: May 22, 2026 | I4: Demand framing | J4: Pinned | K4: Public | M4: High
A5: EV-002 | D5: LBNL 176 / 325-580 TWh | E5: https://buildings.lbl.gov/publications/2024-lbnl-data-center-energy-usage-report | F5: National lab report | G5: Executive summary page 6; Figure 5.5 / page 51 | H5: May 22, 2026 | I5: U.S. demand framing | J5: Pinned | K5: Public | L5: Add extracted PDF table if filing. | M5: High
A6: EV-003 | D6: Monitoring Analytics $16.6B / $23.1B | E6: https://www.monitoringanalytics.com/reports/Reports/2025/IMM_Analysis_of_the_20262027_RPM_Base_Residual_Auction_Part_A_20251001.pdf ; https://www.monitoringanalytics.com/reports/Reports/2026/IMM_Analysis_of_the_20272028_RPM_Base_Residual_Auction_Part_A_20260105.pdf | F6: Market monitor | G6: 2026/2027 Part A pp. 2-3; 2027/2028 Part A pp. 20, 23 / Table 11 | H6: May 22, 2026 | I6: Market-level counterfactual | J6: Pinned | K6: Public | L6: Market pathway, not project bill. | M6: High
A7: EV-004 | D7: AEP Schedule DCT terms | E7: https://www.aepohio.com/company/about/rates/data-center-tariff/ | F7: Utility tariff / official page | G7: Important Tariff Information sections | H7: May 22, 2026 | I7: Case snapshot | J7: Pinned | K7: Public | L7: Add tariff sheet/docket for filing. | M7: Medium
A8: EV-005 | D8: Virginia GS-5 terms | E8: https://www.scc.virginia.gov/about-the-scc/newsreleases/release/scc-issues-order-on-dev-biennial-review-2025/scc-rules-in-dev-biennial-review-case.html ; https://www.scc.virginia.gov/about-the-scc/scc-facts/ | F8: SCC release / facts page | G8: Release for 25 MW, 85/60 floors, effective date; facts page for 14-year obligation | H8: May 22, 2026 | I8: Case snapshot | J8: Needs legal pin | K8: Public | L8: Add final order paragraph/page before filing. | M8: Medium
A9: EV-006 | D9: PJM RBP / connect-and-manage status | E9: https://www.pjm.com/-/media/DotCom/committees-groups/workshops/rbpw/2026/20260218/20260218-item-03---pjm-reliability-backstop-design-working-paper.pdf ; https://www.pjm.com/-/media/DotCom/committees-groups/cifp-rbp/2026/20260416/20260416-item-05---pjm-reliability-backstop-procurement-design---pjm-presentation.pdf | F9: RTO materials / status reporting | G9: Working paper p. 4; design presentation pp. 8-10, 20-21 | H9: May 22, 2026 | I9: Live status | J9: Needs update | K9: Public | L9: Update before filing or citation. | M9: Medium
A10: EV-007 | D10: E3 / Amazon surplus study | E10: https://www.ethree.com/wp-content/uploads/2025/12/RatepayerStudy.pdf | F10: Sponsored study | G10: Sponsor/data/scope disclosures and surplus case pages | H10: May 22, 2026 | I10: Supporter countercase | J10: Needs pin | K10: Proxy | L10: Verify current URL and report pages. | M10: Proxy
A11: EV-008 | D11: White House pledge | E11: https://www.whitehouse.gov/releases/2026/03/ratepayer-protection-pledge/ | F11: Federal pledge | G11: Pledge text: build/bring/buy, infrastructure payment, separate rate structures | H11: May 22, 2026 | I11: Pledge-to-instrument audit | J11: Pinned | K11: Public | L11: Political pledge; legal instrument still required. | M11: Medium
A12: EV-009 | D12: Local fiscal / water agreement | F12: Local public record | I12: Local ledger | J12: Missing | K12: Missing | L12: Project-specific evidence required. | M12: Missing
A13: EV-010 | D13: Credit support / guarantee | F13: Protected contract | I13: Credit ledger | J13: Missing | K13: Missing | L13: Project-specific evidence required. | M13: Missing

Sheet Lists
A1: Controlled Lists
A3: Applicability | B3: Y/N/Unknown | C3: Evidence status | D3: Evidence band | E3: Pin status | F3: Confidence | G3: Origin ledger | H3: Project type
A4: Triggered | B4: Y | C4: Public | D4: Settled cash | E4: Pinned | F4: High | G4: Electric Ledger | H4: Hyperscaler owned
A5: Not triggered | B5: N | C5: Confidential-reviewable | D5: Callable secured credit | E5: Confidential-reviewable | F5: Medium | G5: RTO Capacity | H5: Colo lease
A6: Not applicable | B6: Unknown | C6: Proxy | D6: Enforceable scoped promise | E6: Needs page pin | F6: Proxy | G6: Local Fiscal | H6: Speculative developer
A7: Unknown | C7: Missing | D7: Unsecured promise | E7: Needs legal pin | F7: Missing | G7: Water Env | H7: Behind-the-meter
C8: Contested | D8: Narrative-only promise | E8: Needs update | F8: Contested | G8: Credit Collateral | H8: Flexible load
D9: Unaccredited performance claim | E9: Needs pin | G9: Distributional | H9: Phased affiliate campus
D10: Strong / Medium / Proxy / Unknown | E10: Missing | G10: Public-welfare transfer | H10: Public power / co-op served
